Workbook

Sheet Слайд 1 тренды категорий (2)
B1: Продажи за июль-декабрь 2023, шт | C1: Продажи за январь - июнь 2024, шт | D1: Продажи за июль-декабрь 2024, шт. | E1: Продажи за январь - июнь 2025, шт | J1: Доход за июль-декабрь 2023, грн. | K1: Доход за январь - июнь 2024, грн. | L1: Доход за июль-декабрь 2024, грн. | M1: Доход за январь - июнь 2025, грн | R1: Маржа за июль-декабрь 2023, грн. | S1: Маржа за январь - июнь 2024, грн. | T1: Маржа за июль-декабрь 2024, грн. | U1: Маржа за январь - июнь 2025, грн
A2: Категория | B2: июль-декабрь 2023 | C2: январь-июнь 2024 | D2: июль-декабрь 2024 | E2: январь-июнь 2025 | F2: I 2024 к II 2023 | G2: II 2024 к I 2024 | H2: I 2025 к II 2024 | I2: I 2025 к I 2024 | J2: июль-декабрь 2023 | K2: январь-июнь 2024 | L2: июль-декабрь 2024 | M2: январь-июнь 2025 | N2: I 2024 к II 2023 | O2: II 2024 к I 2024 | P2: I 2025 к II 2024 | Q2: I 2025 к I 2024 | R2: июль-декабрь 2023 | S2: январь-июнь 2024 | T2: июль-декабрь 2024 | U2: январь-июнь 2025 | V2: I 2024 к II 2023 | W2: II 2024 к I 2024 | X2: I 2025 к II 2024 | Y2: I 2025 к I 2024
A3: КРЕСЛА РУКОВОДИТЕЛЯ | B3: 26725 | C3: 19187 | D3: 11862 | E3: 17643 | F3: =IFERROR(C3/B3-1,"") -> -0.282058 | G3: =IFERROR(D3/C3-1,"") -> -0.38176891 | H3: =IFERROR(E3/D3-1,"") -> 0.48735458 | I3: =IFERROR(E3/C3-1,"") -> -0.080471152 | J3: 1.0435148e+08 | K3: 76149864 | L3: 48903591 | M3: 80667045 | N3: =IFERROR(K3/J3-1,"") -> -0.27025604 | O3: =IFERROR(L3/K3-1,"") -> -0.35779805 | P3: =IFERROR(M3/L3-1,"") -> 0.64951169 | Q3: =IFERROR(M3/K3-1,"") -> 0.059319619 | R3: 41678917 | S3: 29293819 | T3: 20819003 | U3: 37262622 | V3: =IFERROR(S3/R3-1,"") -> -0.29715499 | W3: =IFERROR(T3/S3-1,"") -> -0.28930389 | X3: =IFERROR(U3/T3-1,"") -> 0.78983703 | Y3: =IFERROR(U3/S3-1,"") -> 0.2720302
A4: КРЕСЛА ОПЕРАТОРСКИЕ | B4: 54881 | C4: 31299 | D4: 22967 | E4: 25652 | F4: =IFERROR(C4/B4-1,"") -> -0.42969334 | G4: =IFERROR(D4/C4-1,"") -> -0.26620659 | H4: =IFERROR(E4/D4-1,"") -> 0.11690687 | I4: =IFERROR(E4/C4-1,"") -> -0.1804211 | J4: 1.0179829e+08 | K4: 64253469 | L4: 46903609 | M4: 55936401 | N4: =IFERROR(K4/J4-1,"") -> -0.36881584 | O4: =IFERROR(L4/K4-1,"") -> -0.27002215 | P4: =IFERROR(M4/L4-1,"") -> 0.19258204 | Q4: =IFERROR(M4/K4-1,"") -> -0.12944153 | R4: 36343788 | S4: 23321133 | T4: 18351033 | U4: 24679206 | V4: =IFERROR(S4/R4-1,"") -> -0.35831858 | W4: =IFERROR(T4/S4-1,"") -> -0.21311575 | X4: =IFERROR(U4/T4-1,"") -> 0.34484019 | Y4: =IFERROR(U4/S4-1,"") -> 0.058233567
A5: СТУЛЬЯ ПОСЕТИТЕЛЬСКИЕ | B5: 107526 | C5: 64256 | D5: 58364 | E5: 67148 | F5: =IFERROR(C5/B5-1,"") -> -0.4024143 | G5: =IFERROR(D5/C5-1,"") -> -0.091695717 | H5: =IFERROR(E5/D5-1,"") -> 0.15050374 | I5: =IFERROR(E5/C5-1,"") -> 0.04500747 | J5: 77193435 | K5: 51648131 | L5: 46674389 | M5: 54214244 | N5: =IFERROR(K5/J5-1,"") -> -0.33092587 | O5: =IFERROR(L5/K5-1,"") -> -0.096300531 | P5: =IFERROR(M5/L5-1,"") -> 0.16154161 | Q5: =IFERROR(M5/K5-1,"") -> 0.049684536 | R5: 33002287 | S5: 22045621 | T5: 19928779 | U5: 25520626 | V5: =IFERROR(S5/R5-1,"") -> -0.33199717 | W5: =IFERROR(T5/S5-1,"") -> -0.096020966 | X5: =IFERROR(U5/T5-1,"") -> 0.28059152 | Y5: =IFERROR(U5/S5-1,"") -> 0.15762789
A6: КРЕСЛА/СТУЛЬЯ ОБЕДЕННЫЕ | B6: 78009 | C6: 58965 | D6: 40156 | E6: 47534 | F6: =IFERROR(C6/B6-1,"") -> -0.24412568 | G6: =IFERROR(D6/C6-1,"") -> -0.31898584 | H6: =IFERROR(E6/D6-1,"") -> 0.18373344 | I6: =IFERROR(E6/C6-1,"") -> -0.19386076 | J6: 66683260 | K6: 49237455 | L6: 27945548 | M6: 43255800 | N6: =IFERROR(K6/J6-1,"") -> -0.26162195 | O6: =IFERROR(L6/K6-1,"") -> -0.43243313 | P6: =IFERROR(M6/L6-1,"") -> 0.54786015 | Q6: =IFERROR(M6/K6-1,"") -> -0.12148586 | R6: 24715841 | S6: 17502361 | T6: 10575011 | U6: 19039783 | V6: =IFERROR(S6/R6-1,"") -> -0.29185657 | W6: =IFERROR(T6/S6-1,"") -> -0.39579513 | X6: =IFERROR(U6/T6-1,"") -> 0.80045037 | Y6: =IFERROR(U6/S6-1,"") -> 0.087840878
A7: СТОЛЫ ОБЕДЕННЫЕ | B7: 6808 | C7: 7086 | D7: 1539 | E7: 5029 | F7: =IFERROR(C7/B7-1,"") -> 0.040834313 | G7: =IFERROR(D7/C7-1,"") -> -0.78281118 | H7: =IFERROR(E7/D7-1,"") -> 2.2677063 | I7: =IFERROR(E7/C7-1,"") -> -0.29029071 | J7: 13274969 | K7: 14856408 | L7: 3462301.8 | M7: 11801728 | N7: =IFERROR(K7/J7-1,"") -> 0.11912935 | O7: =IFERROR(L7/K7-1,"") -> -0.76694892 | P7: =IFERROR(M7/L7-1,"") -> 2.4086365 | Q7: =IFERROR(M7/K7-1,"") -> -0.20561359 | R7: 4245578 | S7: 4785922.3 | T7: 1236084.8 | U7: 5069490 | V7: =IFERROR(S7/R7-1,"") -> 0.12727227 | W7: =IFERROR(T7/S7-1,"") -> -0.74172485 | X7: =IFERROR(U7/T7-1,"") -> 3.1012477 | Y7: =IFERROR(U7/S7-1,"") -> 0.059250361
A8: МЕБЕЛЬ КОРПУСНАЯ | B8: 3932.5 | C8: 2361 | D8: 1622 | E8: 1498 | F8: =IFERROR(C8/B8-1,"") -> -0.39961856 | G8: =IFERROR(D8/C8-1,"") -> -0.31300296 | H8: =IFERROR(E8/D8-1,"") -> -0.076448829 | I8: =IFERROR(E8/C8-1,"") -> -0.36552308 | J8: 10065870 | K8: 5679902 | L8: 4934825.8 | M8: 4877919.2 | N8: =IFERROR(K8/J8-1,"") -> -0.43572666 | O8: =IFERROR(L8/K8-1,"") -> -0.13117765 | P8: =IFERROR(M8/L8-1,"") -> -0.011531623 | Q8: =IFERROR(M8/K8-1,"") -> -0.14119658 | R8: 4222096.4 | S8: 2198456.6 | T8: 2256819.9 | U8: 1975349.1 | V8: =IFERROR(S8/R8-1,"") -> -0.4792974 | W8: =IFERROR(T8/S8-1,"") -> 0.026547401 | X8: =IFERROR(U8/T8-1,"") -> -0.1247201 | Y8: =IFERROR(U8/S8-1,"") -> -0.10148369
A9: КРЕСЛА ДЕТСКИЕ | B9: 8503 | C9: 3416 | D9: 3012 | E9: 2295 | F9: =IFERROR(C9/B9-1,"") -> -0.59825944 | G9: =IFERROR(D9/C9-1,"") -> -0.11826698 | H9: =IFERROR(E9/D9-1,"") -> -0.23804781 | I9: =IFERROR(E9/C9-1,"") -> -0.32816159 | J9: 14549396 | K9: 6480186.7 | L9: 4671519.1 | M9: 4709913.3 | N9: =IFERROR(K9/J9-1,"") -> -0.55460786 | O9: =IFERROR(L9/K9-1,"") -> -0.27910733 | P9: =IFERROR(M9/L9-1,"") -> 0.0082187841 | Q9: =IFERROR(M9/K9-1,"") -> -0.27318247 | R9: 5928440.8 | S9: 2412246.8 | T9: 1930051.5 | U9: 2236567.4 | V9: =IFERROR(S9/R9-1,"") -> -0.59310603 | W9: =IFERROR(T9/S9-1,"") -> -0.19989468 | X9: =IFERROR(U9/T9-1,"") -> 0.15881226 | Y9: =IFERROR(U9/S9-1,"") -> -0.072828138
A10: ШКОЛЬНАЯ МЕБЕЛЬ | B10: 4475 | C10: 1917 | D10: 12977 | E10: 3475 | F10: =IFERROR(C10/B10-1,"") -> -0.57162011 | G10: =IFERROR(D10/C10-1,"") -> 5.7694314 | H10: =IFERROR(E10/D10-1,"") -> -0.73221854 | I10: =IFERROR(E10/C10-1,"") -> 0.81272822 | J10: 4239927.1 | K10: 1956771.5 | L10: 11816811 | M10: 3111446.5 | N10: =IFERROR(K10/J10-1,"") -> -0.53848937 | O10: =IFERROR(L10/K10-1,"") -> 5.0389327 | P10: =IFERROR(M10/L10-1,"") -> -0.73669322 | Q10: =IFERROR(M10/K10-1,"") -> 0.5900919 | R10: 1910384.6 | S10: 842104.97 | T10: 3649948.1 | U10: 1181067.2 | V10: =IFERROR(S10/R10-1,"") -> -0.55919611 | W10: =IFERROR(T10/S10-1,"") -> 3.3343149 | X10: =IFERROR(U10/T10-1,"") -> -0.67641535 | Y10: =IFERROR(U10/S10-1,"") -> 0.40251777
A11: КРЕСЛА И СТУЛЬЯ СПЕЦИАЛЬНЫЕ | B11: 2133 | C11: 1664 | D11: 1467 | E11: 1156 | F11: =IFERROR(C11/B11-1,"") -> -0.21987811 | G11: =IFERROR(D11/C11-1,"") -> -0.11838942 | H11: =IFERROR(E11/D11-1,"") -> -0.21199727 | I11: =IFERROR(E11/C11-1,"") -> -0.30528846 | J11: 3900269.6 | K11: 3364475.8 | L11: 3463375.8 | M11: 2953696 | N11: =IFERROR(K11/J11-1,"") -> -0.13737353 | O11: =IFERROR(L11/K11-1,"") -> 0.029395364 | P11: =IFERROR(M11/L11-1,"") -> -0.14716272 | Q11: =IFERROR(M11/K11-1,"") -> -0.12209325 | R11: 1710718.3 | S11: 1421269.6 | T11: 1324346 | U11: 1271305.7 | V11: =IFERROR(S11/R11-1,"") -> -0.16919717 | W11: =IFERROR(T11/S11-1,"") -> -0.068195105 | X11: =IFERROR(U11/T11-1,"") -> -0.040050189 | Y11: =IFERROR(U11/S11-1,"") -> -0.10551407
A12: КОМПЛЕКТУЮЩИЕ СТОЛОВ, КРЕСЕЛ И СТУЛЬЕВ ОБЕДЕННЫХ | B12: 15093 | C12: 9342 | D12: 6957 | E12: 7040 | F12: =IFERROR(C12/B12-1,"") -> -0.38103757 | G12: =IFERROR(D12/C12-1,"") -> -0.25529865 | H12: =IFERROR(E12/D12-1,"") -> 0.01193043 | I12: =IFERROR(E12/C12-1,"") -> -0.24641404 | J12: 5550667.4 | K12: 3071901.3 | L12: 2897245.4 | M12: 2445725 | N12: =IFERROR(K12/J12-1,"") -> -0.44657083 | O12: =IFERROR(L12/K12-1,"") -> -0.056855965 | P12: =IFERROR(M12/L12-1,"") -> -0.15584472 | Q12: =IFERROR(M12/K12-1,"") -> -0.20383998 | R12: 2409463.1 | S12: 1294452.3 | T12: 1293366.7 | U12: 1171741.6 | V12: =IFERROR(S12/R12-1,"") -> -0.46276318 | W12: =IFERROR(T12/S12-1,"") -> -0.00083867503 | X12: =IFERROR(U12/T12-1,"") -> -0.094037611 | Y12: =IFERROR(U12/S12-1,"") -> -0.094797419
A13: СТУЛЬЯ БАРНЫЕ | B13: 1764 | C13: 1714 | D13: 689 | E13: 1201 | F13: =IFERROR(C13/B13-1,"") -> -0.028344671 | G13: =IFERROR(D13/C13-1,"") -> -0.59801634 | H13: =IFERROR(E13/D13-1,"") -> 0.74310595 | I13: =IFERROR(E13/C13-1,"") -> -0.29929988 | J13: 3099852.1 | K13: 3128273.7 | L13: 1220087.1 | M13: 2434195.9 | N13: =IFERROR(K13/J13-1,"") -> 0.0091686728 | O13: =IFERROR(L13/K13-1,"") -> -0.6099807 | P13: =IFERROR(M13/L13-1,"") -> 0.99510007 | Q13: =IFERROR(M13/K13-1,"") -> -0.22187247 | R13: 1175832.6 | S13: 1174931.8 | T13: 526905.54 | U13: 1086764 | V13: =IFERROR(S13/R13-1,"") -> -0.00076616556 | W13: =IFERROR(T13/S13-1,"") -> -0.55154371 | X13: =IFERROR(U13/T13-1,"") -> 1.0625404 | Y13: =IFERROR(U13/S13-1,"") -> -0.07504076
A14: МЯГКАЯ МЕБЕЛЬ | B14: 444 | C14: 570 | D14: 630 | E14: 431 | F14: =IFERROR(C14/B14-1,"") -> 0.28378378 | G14: =IFERROR(D14/C14-1,"") -> 0.10526316 | H14: =IFERROR(E14/D14-1,"") -> -0.31587302 | I14: =IFERROR(E14/C14-1,"") -> -0.24385965 | J14: 2405433.6 | K14: 2617486.3 | L14: 2979997.7 | M14: 2066375.7 | N14: =IFERROR(K14/J14-1,"") -> 0.08815572 | O14: =IFERROR(L14/K14-1,"") -> 0.13849599 | P14: =IFERROR(M14/L14-1,"") -> -0.3065848 | Q14: =IFERROR(M14/K14-1,"") -> -0.21054958 | R14: 1086348.6 | S14: 892745.76 | T14: 1199134.5 | U14: 881718.07 | V14: =IFERROR(S14/R14-1,"") -> -0.17821428 | W14: =IFERROR(T14/S14-1,"") -> 0.34319824 | X14: =IFERROR(U14/T14-1,"") -> -0.26470463 | Y14: =IFERROR(U14/S14-1,"") -> -0.012352554
... A18: Общий итог | B18: 315257.5 | C18: 204938 | D18: 164270 | E18: 181722 | F18: =IFERROR(C18/B18-1,"") -> -0.34993458 | G18: =IFERROR(D18/C18-1,"") -> -0.1984405 | H18: =IFERROR(E18/D18-1,"") -> 0.10623973 | I18: =IFERROR(E18/C18-1,"") -> -0.11328304 | J18: 4.1703718e+08 | K18: 2.9029148e+08 | L18: 2.1029576e+08 | M18: 2.7197929e+08 | N18: =IFERROR(K18/J18-1,"") -> -0.30391941 | O18: =IFERROR(L18/K18-1,"") -> -0.27557035 | P18: =IFERROR(M18/L18-1,"") -> 0.29331799 | Q18: =IFERROR(M18/K18-1,"") -> -0.063082097 | R18: 1.6188722e+08 | S18: 1.0957985e+08 | T18: 84557444 | U18: 1.2280211e+08 | V18: =IFERROR(S18/R18-1,"") -> -0.32310996 | W18: =IFERROR(T18/S18-1,"") -> -0.22834858 | X18: =IFERROR(U18/T18-1,"") -> 0.45229209 | Y18: =IFERROR(U18/S18-1,"") -> 0.12066326
A19: Общий итог, млн. грн. | B19: 315257.5 | C19: 204938 | D19: 164270 | E19: 181722 | F19: =IFERROR(C19/B19-1,"") -> -0.34993458 | G19: =IFERROR(D19/C19-1,"") -> -0.1984405 | H19: =IFERROR(E19/D19-1,"") -> 0.10623973 | I19: =IFERROR(E19/C19-1,"") -> -0.11328304 | J19: =MROUND(J18/1000000,1) -> 417 | K19: =MROUND(K18/1000000,1) -> 290 | L19: =MROUND(L18/1000000,1) -> 210 | M19: =MROUND(M18/1000000,1) -> 272 | N19: =IFERROR(K19/J19-1,"") -> -0.30455635 | O19: =IFERROR(L19/K19-1,"") -> -0.27586207 | P19: =IFERROR(M19/L19-1,"") -> 0.2952381 | Q19: =IFERROR(M19/K19-1,"") -> -0.062068966 | R19: =MROUND(R18/1000000,1) -> 162 | S19: =MROUND(S18/1000000,1) -> 110 | T19: =MROUND(T18/1000000,1) -> 85 | U19: =MROUND(U18/1000000,1) -> 123 | V19: =IFERROR(S19/R19-1,"") -> -0.32098765 | W19: =IFERROR(T19/S19-1,"") -> -0.22727273 | X19: =IFERROR(U19/T19-1,"") -> 0.44705882 | Y19: =IFERROR(U19/S19-1,"") -> 0.11818182
A21: Общая динамика | B21: сравниваем 1 полугодие 2025 с 1 полугодием 2024 и со втормым полугодием 2024 | L21: КРЕСЛА/СТУЛЬЯ ОБЕДЕННЫЕ
A35: КРЕСЛА РУКОВОДИТЕЛЯ
L37: ШКОЛЬНАЯ МЕБЕЛЬ
A49: КРЕСЛА ОПЕРАТОРСКИЕ
A63: СТУЛЬЯ ПОСЕТИТЕЛЬСКИЕ

Sheet Слайд 1 тренды категорий
A1: Категория | B1: Доля в доходах за январь - июнь 2025
A2: КРЕСЛА РУКОВОДИТЕЛЯ | B2: 0.28335783
A3: КРЕСЛА ОПЕРАТОРСКИЕ | B3: 0.1964869
A4: СТУЛЬЯ ПОСЕТИТЕЛЬСКИЕ | B4: 0.1904375
A5: КРЕСЛА/СТУЛЬЯ ОБЕДЕННЫЕ | B5: 0.15194395
A6: СТОЛЫ ОБЕДЕННЫЕ | B6: 0.041455741
A7: МЕБЕЛЬ КОРПУСНАЯ | B7: 0.017134588
A8: КРЕСЛА ДЕТСКИЕ | B8: 0.016544437
A9: ШКОЛЬНАЯ МЕБЕЛЬ | B9: 0.010929528
A10: КРЕСЛА И СТУЛЬЯ СПЕЦИАЛЬНЫЕ | B10: 0.0103754
A11: КОМПЛЕКТУЮЩИЕ СТОЛОВ, КРЕСЕЛ И СТУЛЬЕВ ОБЕДЕННЫХ | B11: 0.0085910588
A12: СТУЛЬЯ БАРНЫЕ | B12: 0.0085505606
A13: МЯГКАЯ МЕБЕЛЬ | B13: 0.0072585246
... A17: Общий итог | B17: 0.95537727
A18: Прочие | B18: =100%-SUM(B2:B5) -> 0.17777381
B45: Продажи за июль-декабрь 2023, шт | C45: Продажи за январь - июнь 2024, шт | D45: Продажи за июль-декабрь 2024, шт. | E45: Продажи за январь - июнь 2025, шт | J45: Доход за июль-декабрь 2023, грн. | K45: Доход за январь - июнь 2024, грн. | L45: Доход за июль-декабрь 2024, грн. | M45: Доход за январь - июнь 2025, грн | R45: Маржа за июль-декабрь 2023, грн. | S45: Маржа за январь - июнь 2024, грн. | T45: Маржа за июль-декабрь 2024, грн. | U45: Маржа за январь - июнь 2025, грн
A46: Категория | B46: июль-декабрь 2023 | C46: январь-июнь 2024 | D46: июль-декабрь 2024 | E46: январь-июнь 2025 | F46: I 2024 к II 2023 | G46: II 2024 к I 2024 | H46: I 2025 к II 2024 | I46: I 2025 к I 2024 | J46: июль-декабрь 2023 | K46: январь-июнь 2024 | L46: июль-декабрь 2024 | M46: январь-июнь 2025 | N46: I 2024 к II 2023 | O46: II 2024 к I 2024 | P46: I 2025 к II 2024 | Q46: I 2025 к I 2024 | R46: июль-декабрь 2023 | S46: январь-июнь 2024 | T46: июль-декабрь 2024 | U46: январь-июнь 2025 | V46: I 2024 к II 2023 | W46: II 2024 к I 2024 | X46: I 2025 к II 2024 | Y46: I 2025 к I 2024
A47: КРЕСЛА РУКОВОДИТЕЛЯ | B47: 26725 | C47: 19187 | D47: 11862 | E47: 17643 | F47: =IFERROR(C47/B47-1,"") -> -0.282058 | G47: =IFERROR(D47/C47-1,"") -> -0.38176891 | H47: =IFERROR(E47/D47-1,"") -> 0.48735458 | I47: =IFERROR(E47/C47-1,"") -> -0.080471152 | J47: 1.0435148e+08 | K47: 76149864 | L47: 48903591 | M47: 80667045 | N47: =IFERROR(K47/J47-1,"") -> -0.27025604 | O47: =IFERROR(L47/K47-1,"") -> -0.35779805 | P47: =IFERROR(M47/L47-1,"") -> 0.64951169 | Q47: =IFERROR(M47/K47-1,"") -> 0.059319619 | R47: 41678917 | S47: 29293819 | T47: 20819003 | U47: 37262622 | V47: =IFERROR(S47/R47-1,"") -> -0.29715499 | W47: =IFERROR(T47/S47-1,"") -> -0.28930389 | X47: =IFERROR(U47/T47-1,"") -> 0.78983703 | Y47: =IFERROR(U47/S47-1,"") -> 0.2720302
A48: КРЕСЛА ОПЕРАТОРСКИЕ | B48: 54881 | C48: 31299 | D48: 22967 | E48: 25652 | F48: =IFERROR(C48/B48-1,"") -> -0.42969334 | G48: =IFERROR(D48/C48-1,"") -> -0.26620659 | H48: =IFERROR(E48/D48-1,"") -> 0.11690687 | I48: =IFERROR(E48/C48-1,"") -> -0.1804211 | J48: 1.0179829e+08 | K48: 64253469 | L48: 46903609 | M48: 55936401 | N48: =IFERROR(K48/J48-1,"") -> -0.36881584 | O48: =IFERROR(L48/K48-1,"") -> -0.27002215 | P48: =IFERROR(M48/L48-1,"") -> 0.19258204 | Q48: =IFERROR(M48/K48-1,"") -> -0.12944153 | R48: 36343788 | S48: 23321133 | T48: 18351033 | U48: 24679206 | V48: =IFERROR(S48/R48-1,"") -> -0.35831858 | W48: =IFERROR(T48/S48-1,"") -> -0.21311575 | X48: =IFERROR(U48/T48-1,"") -> 0.34484019 | Y48: =IFERROR(U48/S48-1,"") -> 0.058233567
A49: СТУЛЬЯ ПОСЕТИТЕЛЬСКИЕ | B49: 107526 | C49: 64256 | D49: 58364 | E49: 67148 | F49: =IFERROR(C49/B49-1,"") -> -0.4024143 | G49: =IFERROR(D49/C49-1,"") -> -0.091695717 | H49: =IFERROR(E49/D49-1,"") -> 0.15050374 | I49: =IFERROR(E49/C49-1,"") -> 0.04500747 | J49: 77193435 | K49: 51648131 | L49: 46674389 | M49: 54214244 | N49: =IFERROR(K49/J49-1,"") -> -0.33092587 | O49: =IFERROR(L49/K49-1,"") -> -0.096300531 | P49: =IFERROR(M49/L49-1,"") -> 0.16154161 | Q49: =IFERROR(M49/K49-1,"") -> 0.049684536 | R49: 33002287 | S49: 22045621 | T49: 19928779 | U49: 25520626 | V49: =IFERROR(S49/R49-1,"") -> -0.33199717 | W49: =IFERROR(T49/S49-1,"") -> -0.096020966 | X49: =IFERROR(U49/T49-1,"") -> 0.28059152 | Y49: =IFERROR(U49/S49-1,"") -> 0.15762789
A50: КРЕСЛА/СТУЛЬЯ ОБЕДЕННЫЕ | B50: 78009 | C50: 58965 | D50: 40156 | E50: 47534 | F50: =IFERROR(C50/B50-1,"") -> -0.24412568 | G50: =IFERROR(D50/C50-1,"") -> -0.31898584 | H50: =IFERROR(E50/D50-1,"") -> 0.18373344 | I50: =IFERROR(E50/C50-1,"") -> -0.19386076 | J50: 66683260 | K50: 49237455 | L50: 27945548 | M50: 43255800 | N50: =IFERROR(K50/J50-1,"") -> -0.26162195 | O50: =IFERROR(L50/K50-1,"") -> -0.43243313 | P50: =IFERROR(M50/L50-1,"") -> 0.54786015 | Q50: =IFERROR(M50/K50-1,"") -> -0.12148586 | R50: 24715841 | S50: 17502361 | T50: 10575011 | U50: 19039783 | V50: =IFERROR(S50/R50-1,"") -> -0.29185657 | W50: =IFERROR(T50/S50-1,"") -> -0.39579513 | X50: =IFERROR(U50/T50-1,"") -> 0.80045037 | Y50: =IFERROR(U50/S50-1,"") -> 0.087840878
A51: СТОЛЫ ОБЕДЕННЫЕ | B51: 6808 | C51: 7086 | D51: 1539 | E51: 5029 | F51: =IFERROR(C51/B51-1,"") -> 0.040834313 | G51: =IFERROR(D51/C51-1,"") -> -0.78281118 | H51: =IFERROR(E51/D51-1,"") -> 2.2677063 | I51: =IFERROR(E51/C51-1,"") -> -0.29029071 | J51: 13274969 | K51: 14856408 | L51: 3462301.8 | M51: 11801728 | N51: =IFERROR(K51/J51-1,"") -> 0.11912935 | O51: =IFERROR(L51/K51-1,"") -> -0.76694892 | P51: =IFERROR(M51/L51-1,"") -> 2.4086365 | Q51: =IFERROR(M51/K51-1,"") -> -0.20561359 | R51: 4245578 | S51: 4785922.3 | T51: 1236084.8 | U51: 5069490 | V51: =IFERROR(S51/R51-1,"") -> 0.12727227 | W51: =IFERROR(T51/S51-1,"") -> -0.74172485 | X51: =IFERROR(U51/T51-1,"") -> 3.1012477 | Y51: =IFERROR(U51/S51-1,"") -> 0.059250361
A52: МЕБЕЛЬ КОРПУСНАЯ | B52: 3932.5 | C52: 2361 | D52: 1622 | E52: 1498 | F52: =IFERROR(C52/B52-1,"") -> -0.39961856 | G52: =IFERROR(D52/C52-1,"") -> -0.31300296 | H52: =IFERROR(E52/D52-1,"") -> -0.076448829 | I52: =IFERROR(E52/C52-1,"") -> -0.36552308 | J52: 10065870 | K52: 5679902 | L52: 4934825.8 | M52: 4877919.2 | N52: =IFERROR(K52/J52-1,"") -> -0.43572666 | O52: =IFERROR(L52/K52-1,"") -> -0.13117765 | P52: =IFERROR(M52/L52-1,"") -> -0.011531623 | Q52: =IFERROR(M52/K52-1,"") -> -0.14119658 | R52: 4222096.4 | S52: 2198456.6 | T52: 2256819.9 | U52: 1975349.1 | V52: =IFERROR(S52/R52-1,"") -> -0.4792974 | W52: =IFERROR(T52/S52-1,"") -> 0.026547401 | X52: =IFERROR(U52/T52-1,"") -> -0.1247201 | Y52: =IFERROR(U52/S52-1,"") -> -0.10148369
A53: КРЕСЛА ДЕТСКИЕ | B53: 8503 | C53: 3416 | D53: 3012 | E53: 2295 | F53: =IFERROR(C53/B53-1,"") -> -0.59825944 | G53: =IFERROR(D53/C53-1,"") -> -0.11826698 | H53: =IFERROR(E53/D53-1,"") -> -0.23804781 | I53: =IFERROR(E53/C53-1,"") -> -0.32816159 | J53: 14549396 | K53: 6480186.7 | L53: 4671519.1 | M53: 4709913.3 | N53: =IFERROR(K53/J53-1,"") -> -0.55460786 | O53: =IFERROR(L53/K53-1,"") -> -0.27910733 | P53: =IFERROR(M53/L53-1,"") -> 0.0082187841 | Q53: =IFERROR(M53/K53-1,"") -> -0.27318247 | R53: 5928440.8 | S53: 2412246.8 | T53: 1930051.5 | U53: 2236567.4 | V53: =IFERROR(S53/R53-1,"") -> -0.59310603 | W53: =IFERROR(T53/S53-1,"") -> -0.19989468 | X53: =IFERROR(U53/T53-1,"") -> 0.15881226 | Y53: =IFERROR(U53/S53-1,"") -> -0.072828138
A54: ШКОЛЬНАЯ МЕБЕЛЬ | B54: 4475 | C54: 1917 | D54: 12977 | E54: 3475 | F54: =IFERROR(C54/B54-1,"") -> -0.57162011 | G54: =IFERROR(D54/C54-1,"") -> 5.7694314 | H54: =IFERROR(E54/D54-1,"") -> -0.73221854 | I54: =IFERROR(E54/C54-1,"") -> 0.81272822 | J54: 4239927.1 | K54: 1956771.5 | L54: 11816811 | M54: 3111446.5 | N54: =IFERROR(K54/J54-1,"") -> -0.53848937 | O54: =IFERROR(L54/K54-1,"") -> 5.0389327 | P54: =IFERROR(M54/L54-1,"") -> -0.73669322 | Q54: =IFERROR(M54/K54-1,"") -> 0.5900919 | R54: 1910384.6 | S54: 842104.97 | T54: 3649948.1 | U54: 1181067.2 | V54: =IFERROR(S54/R54-1,"") -> -0.55919611 | W54: =IFERROR(T54/S54-1,"") -> 3.3343149 | X54: =IFERROR(U54/T54-1,"") -> -0.67641535 | Y54: =IFERROR(U54/S54-1,"") -> 0.40251777
A55: КРЕСЛА И СТУЛЬЯ СПЕЦИАЛЬНЫЕ | B55: 2133 | C55: 1664 | D55: 1467 | E55: 1156 | F55: =IFERROR(C55/B55-1,"") -> -0.21987811 | G55: =IFERROR(D55/C55-1,"") -> -0.11838942 | H55: =IFERROR(E55/D55-1,"") -> -0.21199727 | I55: =IFERROR(E55/C55-1,"") -> -0.30528846 | J55: 3900269.6 | K55: 3364475.8 | L55: 3463375.8 | M55: 2953696 | N55: =IFERROR(K55/J55-1,"") -> -0.13737353 | O55: =IFERROR(L55/K55-1,"") -> 0.029395364 | P55: =IFERROR(M55/L55-1,"") -> -0.14716272 | Q55: =IFERROR(M55/K55-1,"") -> -0.12209325 | R55: 1710718.3 | S55: 1421269.6 | T55: 1324346 | U55: 1271305.7 | V55: =IFERROR(S55/R55-1,"") -> -0.16919717 | W55: =IFERROR(T55/S55-1,"") -> -0.068195105 | X55: =IFERROR(U55/T55-1,"") -> -0.040050189 | Y55: =IFERROR(U55/S55-1,"") -> -0.10551407
A56: КОМПЛЕКТУЮЩИЕ СТОЛОВ, КРЕСЕЛ И СТУЛЬЕВ ОБЕДЕННЫХ | B56: 15093 | C56: 9342 | D56: 6957 | E56: 7040 | F56: =IFERROR(C56/B56-1,"") -> -0.38103757 | G56: =IFERROR(D56/C56-1,"") -> -0.25529865 | H56: =IFERROR(E56/D56-1,"") -> 0.01193043 | I56: =IFERROR(E56/C56-1,"") -> -0.24641404 | J56: 5550667.4 | K56: 3071901.3 | L56: 2897245.4 | M56: 2445725 | N56: =IFERROR(K56/J56-1,"") -> -0.44657083 | O56: =IFERROR(L56/K56-1,"") -> -0.056855965 | P56: =IFERROR(M56/L56-1,"") -> -0.15584472 | Q56: =IFERROR(M56/K56-1,"") -> -0.20383998 | R56: 2409463.1 | S56: 1294452.3 | T56: 1293366.7 | U56: 1171741.6 | V56: =IFERROR(S56/R56-1,"") -> -0.46276318 | W56: =IFERROR(T56/S56-1,"") -> -0.00083867503 | X56: =IFERROR(U56/T56-1,"") -> -0.094037611 | Y56: =IFERROR(U56/S56-1,"") -> -0.094797419
A57: СТУЛЬЯ БАРНЫЕ | B57: 1764 | C57: 1714 | D57: 689 | E57: 1201 | F57: =IFERROR(C57/B57-1,"") -> -0.028344671 | G57: =IFERROR(D57/C57-1,"") -> -0.59801634 | H57: =IFERROR(E57/D57-1,"") -> 0.74310595 | I57: =IFERROR(E57/C57-1,"") -> -0.29929988 | J57: 3099852.1 | K57: 3128273.7 | L57: 1220087.1 | M57: 2434195.9 | N57: =IFERROR(K57/J57-1,"") -> 0.0091686728 | O57: =IFERROR(L57/K57-1,"") -> -0.6099807 | P57: =IFERROR(M57/L57-1,"") -> 0.99510007 | Q57: =IFERROR(M57/K57-1,"") -> -0.22187247 | R57: 1175832.6 | S57: 1174931.8 | T57: 526905.54 | U57: 1086764 | V57: =IFERROR(S57/R57-1,"") -> -0.00076616556 | W57: =IFERROR(T57/S57-1,"") -> -0.55154371 | X57: =IFERROR(U57/T57-1,"") -> 1.0625404 | Y57: =IFERROR(U57/S57-1,"") -> -0.07504076
A58: МЯГКАЯ МЕБЕЛЬ | B58: 444 | C58: 570 | D58: 630 | E58: 431 | F58: =IFERROR(C58/B58-1,"") -> 0.28378378 | G58: =IFERROR(D58/C58-1,"") -> 0.10526316 | H58: =IFERROR(E58/D58-1,"") -> -0.31587302 | I58: =IFERROR(E58/C58-1,"") -> -0.24385965 | J58: 2405433.6 | K58: 2617486.3 | L58: 2979997.7 | M58: 2066375.7 | N58: =IFERROR(K58/J58-1,"") -> 0.08815572 | O58: =IFERROR(L58/K58-1,"") -> 0.13849599 | P58: =IFERROR(M58/L58-1,"") -> -0.3065848 | Q58: =IFERROR(M58/K58-1,"") -> -0.21054958 | R58: 1086348.6 | S58: 892745.76 | T58: 1199134.5 | U58: 881718.07 | V58: =IFERROR(S58/R58-1,"") -> -0.17821428 | W58: =IFERROR(T58/S58-1,"") -> 0.34319824 | X58: =IFERROR(U58/T58-1,"") -> -0.26470463 | Y58: =IFERROR(U58/S58-1,"") -> -0.012352554
... A62: Общий итог | B62: 315257.5 | C62: 204938 | D62: 164270 | E62: 181722 | F62: =IFERROR(C62/B62-1,"") -> -0.34993458 | G62: =IFERROR(D62/C62-1,"") -> -0.1984405 | H62: =IFERROR(E62/D62-1,"") -> 0.10623973 | I62: =IFERROR(E62/C62-1,"") -> -0.11328304 | J62: 4.1703718e+08 | K62: 2.9029148e+08 | L62: 2.1029576e+08 | M62: 2.7197929e+08 | N62: =IFERROR(K62/J62-1,"") -> -0.30391941 | O62: =IFERROR(L62/K62-1,"") -> -0.27557035 | P62: =IFERROR(M62/L62-1,"") -> 0.29331799 | Q62: =IFERROR(M62/K62-1,"") -> -0.063082097 | R62: 1.6188722e+08 | S62: 1.0957985e+08 | T62: 84557444 | U62: 1.2280211e+08 | V62: =IFERROR(S62/R62-1,"") -> -0.32310996 | W62: =IFERROR(T62/S62-1,"") -> -0.22834858 | X62: =IFERROR(U62/T62-1,"") -> 0.45229209 | Y62: =IFERROR(U62/S62-1,"") -> 0.12066326
A63: Общий итог, млн. грн. | B63: 315257.5 | C63: 204938 | D63: 164270 | E63: 181722 | F63: =IFERROR(C63/B63-1,"") -> -0.34993458 | G63: =IFERROR(D63/C63-1,"") -> -0.1984405 | H63: =IFERROR(E63/D63-1,"") -> 0.10623973 | I63: =IFERROR(E63/C63-1,"") -> -0.11328304 | J63: =MROUND(J62/1000000,1) -> 417 | K63: =MROUND(K62/1000000,1) -> 290 | L63: =MROUND(L62/1000000,1) -> 210 | M63: =MROUND(M62/1000000,1) -> 272 | N63: =IFERROR(K63/J63-1,"") -> -0.30455635 | O63: =IFERROR(L63/K63-1,"") -> -0.27586207 | P63: =IFERROR(M63/L63-1,"") -> 0.2952381 | Q63: =IFERROR(M63/K63-1,"") -> -0.062068966 | R63: =MROUND(R62/1000000,1) -> 162 | S63: =MROUND(S62/1000000,1) -> 110 | T63: =MROUND(T62/1000000,1) -> 85 | U63: =MROUND(U62/1000000,1) -> 123 | V63: =IFERROR(S63/R63-1,"") -> -0.32098765 | W63: =IFERROR(T63/S63-1,"") -> -0.22727273 | X63: =IFERROR(U63/T63-1,"") -> 0.44705882 | Y63: =IFERROR(U63/S63-1,"") -> 0.11818182

Sheet Тренды категорий
A1: Категория | B1: Доход за июль-декабрь 2023, грн. | C1: Доход за январь - июнь 2024, грн. | D1: Доход за июль-декабрь 2024, грн. | E1: Доход за январь - июнь 2025, грн | F1: 01-06.2024 к 07-12.2023 | G1: 07-12.2024 к 01-06.2024 | H1: 01-06.2025 к 07-12.2024 | I1: Изменение 01-06.2025 к 01-06.2024
A2: КРЕСЛА РУКОВОДИТЕЛЯ | B2: 1.0435148e+08 | C2: 76149864 | D2: 48903591 | E2: 80667045 | F2: =IFERROR(C2/B2-1,"") -> -0.27025604 | G2: =IFERROR(D2/C2-1,"") -> -0.35779805 | H2: =IFERROR(E2/D2-1,"") -> 0.64951169 | I2: =IFERROR(E2/C2-1,"") -> 0.059319619
A3: КРЕСЛА ОПЕРАТОРСКИЕ | B3: 1.0179829e+08 | C3: 64253469 | D3: 46903609 | E3: 55936401 | F3: =IFERROR(C3/B3-1,"") -> -0.36881584 | G3: =IFERROR(D3/C3-1,"") -> -0.27002215 | H3: =IFERROR(E3/D3-1,"") -> 0.19258204 | I3: =IFERROR(E3/C3-1,"") -> -0.12944153
A4: СТУЛЬЯ ПОСЕТИТЕЛЬСКИЕ | B4: 77193435 | C4: 51648131 | D4: 46674389 | E4: 54214244 | F4: =IFERROR(C4/B4-1,"") -> -0.33092587 | G4: =IFERROR(D4/C4-1,"") -> -0.096300531 | H4: =IFERROR(E4/D4-1,"") -> 0.16154161 | I4: =IFERROR(E4/C4-1,"") -> 0.049684536
A5: КРЕСЛА/СТУЛЬЯ ОБЕДЕННЫЕ | B5: 66683260 | C5: 49237455 | D5: 27945548 | E5: 43255800 | F5: =IFERROR(C5/B5-1,"") -> -0.26162195 | G5: =IFERROR(D5/C5-1,"") -> -0.43243313 | H5: =IFERROR(E5/D5-1,"") -> 0.54786015 | I5: =IFERROR(E5/C5-1,"") -> -0.12148586
A6: СТОЛЫ ОБЕДЕННЫЕ | B6: 13274969 | C6: 14856408 | D6: 3462301.8 | E6: 11801728 | F6: =IFERROR(C6/B6-1,"") -> 0.11912935 | G6: =IFERROR(D6/C6-1,"") -> -0.76694892 | H6: =IFERROR(E6/D6-1,"") -> 2.4086365 | I6: =IFERROR(E6/C6-1,"") -> -0.20561359 | Y6: За счет столов Modern, argon, aqua, talio, calipso, casey
A7: МЕБЕЛЬ КОРПУСНАЯ | B7: 10065870 | C7: 5679902 | D7: 4934825.8 | E7: 4877919.2 | F7: =IFERROR(C7/B7-1,"") -> -0.43572666 | G7: =IFERROR(D7/C7-1,"") -> -0.13117765 | H7: =IFERROR(E7/D7-1,"") -> -0.011531623 | I7: =IFERROR(E7/C7-1,"") -> -0.14119658
A8: КРЕСЛА ДЕТСКИЕ | B8: 14549396 | C8: 6480186.7 | D8: 4671519.1 | E8: 4709913.3 | F8: =IFERROR(C8/B8-1,"") -> -0.55460786 | G8: =IFERROR(D8/C8-1,"") -> -0.27910733 | H8: =IFERROR(E8/D8-1,"") -> 0.0082187841 | I8: =IFERROR(E8/C8-1,"") -> -0.27318247
A9: ШКОЛЬНАЯ МЕБЕЛЬ | B9: 4239927.1 | C9: 1956771.5 | D9: 11816811 | E9: 3111446.5 | F9: =IFERROR(C9/B9-1,"") -> -0.53848937 | G9: =IFERROR(D9/C9-1,"") -> 5.0389327 | H9: =IFERROR(E9/D9-1,"") -> -0.73669322 | I9: =IFERROR(E9/C9-1,"") -> 0.5900919 | Y9: За счет стола 176 и стула и стула 279 в октябре
A10: КРЕСЛА И СТУЛЬЯ СПЕЦИАЛЬНЫЕ | B10: 3900269.6 | C10: 3364475.8 | D10: 3463375.8 | E10: 2953696 | F10: =IFERROR(C10/B10-1,"") -> -0.13737353 | G10: =IFERROR(D10/C10-1,"") -> 0.029395364 | H10: =IFERROR(E10/D10-1,"") -> -0.14716272 | I10: =IFERROR(E10/C10-1,"") -> -0.12209325
A11: КОМПЛЕКТУЮЩИЕ СТОЛОВ, КРЕСЕЛ И СТУЛЬЕВ ОБЕДЕННЫХ | B11: 5550667.4 | C11: 3071901.3 | D11: 2897245.4 | E11: 2445725 | F11: =IFERROR(C11/B11-1,"") -> -0.44657083 | G11: =IFERROR(D11/C11-1,"") -> -0.056855965 | H11: =IFERROR(E11/D11-1,"") -> -0.15584472 | I11: =IFERROR(E11/C11-1,"") -> -0.20383998
A12: СТУЛЬЯ БАРНЫЕ | B12: 3099852.1 | C12: 3128273.7 | D12: 1220087.1 | E12: 2434195.9 | F12: =IFERROR(C12/B12-1,"") -> 0.0091686728 | G12: =IFERROR(D12/C12-1,"") -> -0.6099807 | H12: =IFERROR(E12/D12-1,"") -> 0.99510007 | I12: =IFERROR(E12/C12-1,"") -> -0.22187247
A13: МЯГКАЯ МЕБЕЛЬ | B13: 2405433.6 | C13: 2617486.3 | D13: 2979997.7 | E13: 2066375.7 | F13: =IFERROR(C13/B13-1,"") -> 0.08815572 | G13: =IFERROR(D13/C13-1,"") -> 0.13849599 | H13: =IFERROR(E13/D13-1,"") -> -0.3065848 | I13: =IFERROR(E13/C13-1,"") -> -0.21054958
A14: КРЕСЛА ГЕЙМЕРСКИЕ | B14: 5191399 | C14: 5461875.9 | D14: 2641522.1 | E14: 1957770.3 | F14: =IFERROR(C14/B14-1,"") -> 0.052100957 | G14: =IFERROR(D14/C14-1,"") -> -0.5163709 | H14: =IFERROR(E14/D14-1,"") -> -0.25884767 | I14: =IFERROR(E14/C14-1,"") -> -0.64155716
A15: ВЕШАЛКИ НАПОЛЬНЫЕ | B15: 4732923.6 | C15: 2385283.9 | D15: 1569499.1 | E15: 1506205.4 | F15: =IFERROR(C15/B15-1,"") -> -0.49602316 | G15: =IFERROR(D15/C15-1,"") -> -0.34200743 | H15: =IFERROR(E15/D15-1,"") -> -0.04032729 | I15: =IFERROR(E15/C15-1,"") -> -0.36854249
A16: КРОВАТИ И МАТРАСЫ | B16: 0 | C16: 0 | D16: 211437.15 | E16: 40821.2 | F16: =IFERROR(C16/B16-1,"") | G16: =IFERROR(D16/C16-1,"") | H16: =IFERROR(E16/D16-1,"") -> -0.80693459 | I16: =IFERROR(E16/C16-1,"")
A17: Общий итог | B17: 4.1703718e+08 | C17: 2.9029148e+08 | D17: 2.1029576e+08 | E17: 2.7197929e+08 | F17: =IFERROR(C17/B17-1,"") -> -0.30391941 | G17: =IFERROR(D17/C17-1,"") -> -0.27557035 | H17: =IFERROR(E17/D17-1,"") -> 0.29331799 | I17: =IFERROR(E17/C17-1,"") -> -0.063082097
A20: Категория | B20: Маржа за июль-декабрь 2023, грн. | C20: Маржа за январь - июнь 2024, грн. | D20: Маржа за июль-декабрь 2024, грн. | E20: Маржа за январь - июнь 2025, грн | F20: Изменение 01-06.2024 к 07-12.2023 | G20: Изменение 07-12.2024 к 01-06.2024 | H20: Изменение 01-06.2025 к 07-12.2024 | I20: Изменение 01-06.2025 к 01-06.2024 | J20: Продажи за июль-декабрь 2023, шт | K20: Продажи за январь - июнь 2024, шт | L20: Продажи за июль-декабрь 2024, шт. | M20: Продажи за январь - июнь 2025, шт | N20: Изменение 01-06.2024 к 07-12.2023 | O20: Изменение 07-12.2024 к 01-06.2024 | P20: Изменение 01-06.2025 к 07-12.2024 | Q20: Изменение 01-06.2025 к 01-06.2024
A21: КРЕСЛА РУКОВОДИТЕЛЯ | B21: 41678917 | C21: 29293819 | D21: 20819003 | E21: 37262622 | F21: =IFERROR(C21/B21-1,"") -> -0.29715499 | G21: =IFERROR(D21/C21-1,"") -> -0.28930389 | H21: =IFERROR(E21/D21-1,"") -> 0.78983703 | I21: =IFERROR(E21/C21-1,"") -> 0.2720302 | J21: 26725 | K21: 19187 | L21: 11862 | M21: 17643 | N21: =IFERROR(K21/J21-1,"") -> -0.282058 | O21: =IFERROR(L21/K21-1,"") -> -0.38176891 | P21: =IFERROR(M21/L21-1,"") -> 0.48735458 | Q21: =IFERROR(M21/K21-1,"") -> -0.080471152
A22: КРЕСЛА ОПЕРАТОРСКИЕ | B22: 36343788 | C22: 23321133 | D22: 18351033 | E22: 24679206 | F22: =IFERROR(C22/B22-1,"") -> -0.35831858 | G22: =IFERROR(D22/C22-1,"") -> -0.21311575 | H22: =IFERROR(E22/D22-1,"") -> 0.34484019 | I22: =IFERROR(E22/C22-1,"") -> 0.058233567 | J22: 54881 | K22: 31299 | L22: 22967 | M22: 25652 | N22: =IFERROR(K22/J22-1,"") -> -0.42969334 | O22: =IFERROR(L22/K22-1,"") -> -0.26620659 | P22: =IFERROR(M22/L22-1,"") -> 0.11690687 | Q22: =IFERROR(M22/K22-1,"") -> -0.1804211
A23: СТУЛЬЯ ПОСЕТИТЕЛЬСКИЕ | B23: 33002287 | C23: 22045621 | D23: 19928779 | E23: 25520626 | F23: =IFERROR(C23/B23-1,"") -> -0.33199717 | G23: =IFERROR(D23/C23-1,"") -> -0.096020966 | H23: =IFERROR(E23/D23-1,"") -> 0.28059152 | I23: =IFERROR(E23/C23-1,"") -> 0.15762789 | J23: 107526 | K23: 64256 | L23: 58364 | M23: 67148 | N23: =IFERROR(K23/J23-1,"") -> -0.4024143 | O23: =IFERROR(L23/K23-1,"") -> -0.091695717 | P23: =IFERROR(M23/L23-1,"") -> 0.15050374 | Q23: =IFERROR(M23/K23-1,"") -> 0.04500747
A24: КРЕСЛА/СТУЛЬЯ ОБЕДЕННЫЕ | B24: 24715841 | C24: 17502361 | D24: 10575011 | E24: 19039783 | F24: =IFERROR(C24/B24-1,"") -> -0.29185657 | G24: =IFERROR(D24/C24-1,"") -> -0.39579513 | H24: =IFERROR(E24/D24-1,"") -> 0.80045037 | I24: =IFERROR(E24/C24-1,"") -> 0.087840878 | J24: 78009 | K24: 58965 | L24: 40156 | M24: 47534 | N24: =IFERROR(K24/J24-1,"") -> -0.24412568 | O24: =IFERROR(L24/K24-1,"") -> -0.31898584 | P24: =IFERROR(M24/L24-1,"") -> 0.18373344 | Q24: =IFERROR(M24/K24-1,"") -> -0.19386076
A25: СТОЛЫ ОБЕДЕННЫЕ | B25: 4245578 | C25: 4785922.3 | D25: 1236084.8 | E25: 5069490 | F25: =IFERROR(C25/B25-1,"") -> 0.12727227 | G25: =IFERROR(D25/C25-1,"") -> -0.74172485 | H25: =IFERROR(E25/D25-1,"") -> 3.1012477 | I25: =IFERROR(E25/C25-1,"") -> 0.059250361 | J25: 6808 | K25: 7086 | L25: 1539 | M25: 5029 | N25: =IFERROR(K25/J25-1,"") -> 0.040834313 | O25: =IFERROR(L25/K25-1,"") -> -0.78281118 | P25: =IFERROR(M25/L25-1,"") -> 2.2677063 | Q25: =IFERROR(M25/K25-1,"") -> -0.29029071 | Y25: За счет столов Modern, argon, aqua, talio, calipso, casey
A26: МЕБЕЛЬ КОРПУСНАЯ | B26: 4222096.4 | C26: 2198456.6 | D26: 2256819.9 | E26: 1975349.1 | F26: =IFERROR(C26/B26-1,"") -> -0.4792974 | G26: =IFERROR(D26/C26-1,"") -> 0.026547401 | H26: =IFERROR(E26/D26-1,"") -> -0.1247201 | I26: =IFERROR(E26/C26-1,"") -> -0.10148369 | J26: 3932.5 | K26: 2361 | L26: 1622 | M26: 1498 | N26: =IFERROR(K26/J26-1,"") -> -0.39961856 | O26: =IFERROR(L26/K26-1,"") -> -0.31300296 | P26: =IFERROR(M26/L26-1,"") -> -0.076448829 | Q26: =IFERROR(M26/K26-1,"") -> -0.36552308
A27: КРЕСЛА ДЕТСКИЕ | B27: 5928440.8 | C27: 2412246.8 | D27: 1930051.5 | E27: 2236567.4 | F27: =IFERROR(C27/B27-1,"") -> -0.59310603 | G27: =IFERROR(D27/C27-1,"") -> -0.19989468 | H27: =IFERROR(E27/D27-1,"") -> 0.15881226 | I27: =IFERROR(E27/C27-1,"") -> -0.072828138 | J27: 8503 | K27: 3416 | L27: 3012 | M27: 2295 | N27: =IFERROR(K27/J27-1,"") -> -0.59825944 | O27: =IFERROR(L27/K27-1,"") -> -0.11826698 | P27: =IFERROR(M27/L27-1,"") -> -0.23804781 | Q27: =IFERROR(M27/K27-1,"") -> -0.32816159
A28: ШКОЛЬНАЯ МЕБЕЛЬ | B28: 1910384.6 | C28: 842104.97 | D28: 3649948.1 | E28: 1181067.2 | F28: =IFERROR(C28/B28-1,"") -> -0.55919611 | G28: =IFERROR(D28/C28-1,"") -> 3.3343149 | H28: =IFERROR(E28/D28-1,"") -> -0.67641535 | I28: =IFERROR(E28/C28-1,"") -> 0.40251777 | J28: 4475 | K28: 1917 | L28: 12977 | M28: 3475 | N28: =IFERROR(K28/J28-1,"") -> -0.57162011 | O28: =IFERROR(L28/K28-1,"") -> 5.7694314 | P28: =IFERROR(M28/L28-1,"") -> -0.73221854 | Q28: =IFERROR(M28/K28-1,"") -> 0.81272822 | Y28: За счет стола 176 и стула и стула 279 в октябре
A29: КРЕСЛА И СТУЛЬЯ СПЕЦИАЛЬНЫЕ | B29: 1710718.3 | C29: 1421269.6 | D29: 1324346 | E29: 1271305.7 | F29: =IFERROR(C29/B29-1,"") -> -0.16919717 | G29: =IFERROR(D29/C29-1,"") -> -0.068195105 | H29: =IFERROR(E29/D29-1,"") -> -0.040050189 | I29: =IFERROR(E29/C29-1,"") -> -0.10551407 | J29: 2133 | K29: 1664 | L29: 1467 | M29: 1156 | N29: =IFERROR(K29/J29-1,"") -> -0.21987811 | O29: =IFERROR(L29/K29-1,"") -> -0.11838942 | P29: =IFERROR(M29/L29-1,"") -> -0.21199727 | Q29: =IFERROR(M29/K29-1,"") -> -0.30528846
A30: КОМПЛЕКТУЮЩИЕ СТОЛОВ, КРЕСЕЛ И СТУЛЬЕВ ОБЕДЕННЫХ | B30: 2409463.1 | C30: 1294452.3 | D30: 1293366.7 | E30: 1171741.6 | F30: =IFERROR(C30/B30-1,"") -> -0.46276318 | G30: =IFERROR(D30/C30-1,"") -> -0.00083867503 | H30: =IFERROR(E30/D30-1,"") -> -0.094037611 | I30: =IFERROR(E30/C30-1,"") -> -0.094797419 | J30: 15093 | K30: 9342 | L30: 6957 | M30: 7040 | N30: =IFERROR(K30/J30-1,"") -> -0.38103757 | O30: =IFERROR(L30/K30-1,"") -> -0.25529865 | P30: =IFERROR(M30/L30-1,"") -> 0.01193043 | Q30: =IFERROR(M30/K30-1,"") -> -0.24641404
A31: СТУЛЬЯ БАРНЫЕ | B31: 1175832.6 | C31: 1174931.8 | D31: 526905.54 | E31: 1086764 | F31: =IFERROR(C31/B31-1,"") -> -0.00076616556 | G31: =IFERROR(D31/C31-1,"") -> -0.55154371 | H31: =IFERROR(E31/D31-1,"") -> 1.0625404 | I31: =IFERROR(E31/C31-1,"") -> -0.07504076 | J31: 1764 | K31: 1714 | L31: 689 | M31: 1201 | N31: =IFERROR(K31/J31-1,"") -> -0.028344671 | O31: =IFERROR(L31/K31-1,"") -> -0.59801634 | P31: =IFERROR(M31/L31-1,"") -> 0.74310595 | Q31: =IFERROR(M31/K31-1,"") -> -0.29929988
A32: МЯГКАЯ МЕБЕЛЬ | B32: 1086348.6 | C32: 892745.76 | D32: 1199134.5 | E32: 881718.07 | F32: =IFERROR(C32/B32-1,"") -> -0.17821428 | G32: =IFERROR(D32/C32-1,"") -> 0.34319824 | H32: =IFERROR(E32/D32-1,"") -> -0.26470463 | I32: =IFERROR(E32/C32-1,"") -> -0.012352554 | J32: 444 | K32: 570 | L32: 630 | M32: 431 | N32: =IFERROR(K32/J32-1,"") -> 0.28378378 | O32: =IFERROR(L32/K32-1,"") -> 0.10526316 | P32: =IFERROR(M32/L32-1,"") -> -0.31587302 | Q32: =IFERROR(M32/K32-1,"") -> -0.24385965
A33: КРЕСЛА ГЕЙМЕРСКИЕ | B33: 1407241.6 | C33: 1342205.9 | D33: 671537.06 | E33: 687505.3 | F33: =IFERROR(C33/B33-1,"") -> -0.046215006 | G33: =IFERROR(D33/C33-1,"") -> -0.49967657 | H33: =IFERROR(E33/D33-1,"") -> 0.023778637 | I33: =IFERROR(E33/C33-1,"") -> -0.48777956 | J33: 1147 | K33: 1090 | L33: 544 | M33: 366 | N33: =IFERROR(K33/J33-1,"") -> -0.049694856 | O33: =IFERROR(L33/K33-1,"") -> -0.50091743 | P33: =IFERROR(M33/L33-1,"") -> -0.32720588 | Q33: =IFERROR(M33/K33-1,"") -> -0.66422018
A34: ВЕШАЛКИ НАПОЛЬНЫЕ | B34: 2050281.2 | C34: 1052575.6 | D34: 731319.49 | E34: 724816.76 | F34: =IFERROR(C34/B34-1,"") -> -0.48661892 | G34: =IFERROR(D34/C34-1,"") -> -0.30520951 | H34: =IFERROR(E34/D34-1,"") -> -0.0088917767 | I34: =IFERROR(E34/C34-1,"") -> -0.31138744 | J34: 3817 | K34: 2071 | L34: 1405 | M34: 1243 | N34: =IFERROR(K34/J34-1,"") -> -0.4574273 | O34: =IFERROR(L34/K34-1,"") -> -0.32158378 | P34: =IFERROR(M34/L34-1,"") -> -0.11530249 | Q34: =IFERROR(M34/K34-1,"") -> -0.39980686
A35: КРОВАТИ И МАТРАСЫ | B35: 0 | C35: 0 | D35: 64103.814 | E35: 13544.468 | F35: =IFERROR(C35/B35-1,"") | G35: =IFERROR(D35/C35-1,"") | H35: =IFERROR(E35/D35-1,"") -> -0.78871042 | I35: =IFERROR(E35/C35-1,"") | J35: 0 | K35: 0 | L35: 79 | M35: 11 | N35: =IFERROR(K35/J35-1,"") | O35: =IFERROR(L35/K35-1,"") | P35: =IFERROR(M35/L35-1,"") -> -0.86075949 | Q35: =IFERROR(M35/K35-1,"")
A36: Общий итог | B36: 1.6188722e+08 | C36: 1.0957985e+08 | D36: 84557444 | E36: 1.2280211e+08 | F36: =IFERROR(C36/B36-1,"") -> -0.32310996 | G36: =IFERROR(D36/C36-1,"") -> -0.22834858 | H36: =IFERROR(E36/D36-1,"") -> 0.45229209 | I36: =IFERROR(E36/C36-1,"") -> 0.12066326 | J36: 315257.5 | K36: 204938 | L36: 164270 | M36: 181722 | N36: =IFERROR(K36/J36-1,"") -> -0.34993458 | O36: =IFERROR(L36/K36-1,"") -> -0.1984405 | P36: =IFERROR(M36/L36-1,"") -> 0.10623973 | Q36: =IFERROR(M36/K36-1,"") -> -0.11328304

Sheet BCG
AB1: 0 | AC1: Темная лошадка | AD1: пользуются спросом, но еще слабо представлены на рынке | AM1: рост доли в доходах выше предыдущего периода, а доля в доходах ниже медианы
AB2: 1 | AC2: Звезда | AD2: прибыльны и продолжают захватывать рынок | AM2: рост доли в доходах выше предыдущего периода, а доля в доходах выше медианы
F3: медиана | J3: медиана | P3: медиана | V3: медиана | AB3: 11 | AC3: Корова | AD3: теряют популярность, но приносят прибыль | AM3: рост доли в доходах ниже предыдущего периода, а доля в доходах выше медианы
B4: внести новое и удалить выведенные | F4: ='Факт продаж'!D24 -> 0.00078193108 | J4: ='Факт продаж'!M24 -> 0.00082965831 | P4: ='Факт продаж'!V24 -> 0.00093074691 | V4: ='Факт продаж'!AE24 -> 0.00084150915 | AB4: 10 | AC4: Собака | AD4: не интересны потребителю и плохо продаются | AJ4: Плюс GAMER | AM4: рост доли в доходах ниже предыдущего периода, а доля в доходах ниже медианы
A5: КАТЕГОРИЯ | B5: ЛИНИЯ МОДЕЛИ | C5: Продажи за октябрь - декабрь 2024 (IV кв 2024), шт | D5: Доход за октябрь - декабрь 2024 (IV кв 2024), грн. | E5: Маржа за октябрь - декабрь 2024 (IV кв 2024), грн. | F5: Доля в доходах за октябрь - декабрь 2024 (IV кв 2024) | G5: Продажи за апрель - июнь 2025 (II кв 2025), шт | H5: Доход за апрель - июнь 2025 (II кв 2025), грн. | I5: Маржа за апрель - июнь 2025 (II кв 2025), грн. | J5: Доля в доходах за апрель - июнь 2025 (II кв 2025) | K5: РОСТ доходах апрель - июнь 2025 (II кв 2025) | L5: РОСТ доли в доходах апрель - июнь 2025 (II кв 2025) | M5: Продажи за июль - сентябрь 2025 (III кв 2025), шт. | N5: Доход за июль - сентябрь 2025 (III кв 2025), грн. | O5: Маржа за июль - сентябрь 2025 (III кв 2025), грн. | P5: Доля в доходах за июль - сентябрь 2025 (III кв 2025) | Q5: РОСТ доходах июль - сентябрь 2025 (III кв 2025) | R5: РОСТ доли в доходах июль - сентябрь 2025 (III кв 2025) | S5: Продажи за октябрь - декабрь 2025 (IV кв 2025), шт | T5: Доход за октябрь - декабрь 2025 (IV кв 2025), грн | U5: Маржа за октябрь - декабрь 2025 (IV кв 2025), грн | V5: Доля в доходах за октябрь - декабрь 2025 (IV кв 2025) | W5: РОСТ доходах октябрь - декабрь 2025 (IV кв 2025) | X5: РОСТ доли в доходах октябрь - декабрь 2025 (IV кв 2025) | Y5: РОСТ доходов за IV кв 2025 к III кв 2025 | Z5: РОСТ доли доходов за IV кв 2025 кIV кв 2024 | AB5: Группа по BCG | AF5: ABC анализ | AJ5: =COUNTIF(AJ7:AJ1048566,"PROMO") -> 39 | AK5: =COUNTIF(AK7:AK1048566,"PROMO") -> 0 | AL5: Инфо
AB6: октябрь - декабрь 2024 (IV кв 2024) | AC6: апрель - июнь 2025 (II кв 2025) | AD6: июль - сентябрь 2025 (III кв 2025) | AE6: октябрь - декабрь 2025 (IV кв 2025) | AF6: (IV кв 2024) | AG6: (II кв 2025) | AH6: (III кв 2025) | AI6: (IV кв 2025) | AJ6: PROMO old | AK6: PROMO new
A7: ДИВАНЫ НЕРАСКЛАДНЫЕ, ПУФЫ | B7: N-JOY | C7: =IFERROR(VLOOKUP(B7,'Факт продаж'!A:B,2,0),"нет продаж") -> нет продаж | D7: =IFERROR(VLOOKUP(B7,'Факт продаж'!A:C,3,0),"нет продаж") -> нет продаж | E7: =IFERROR(VLOOKUP(B7,'Факт продаж'!A:E,5,0),"нет продаж") -> нет продаж | F7: =IFERROR(VLOOKUP(B7,'Факт продаж'!A:C,3,0)/SUM('План Антонова'!$C$11:$C$13),0) -> 0 | G7: =IFERROR(VLOOKUP(B7,'Факт продаж'!J:K,2,0),"нет продаж") -> 3 | H7: =IFERROR(VLOOKUP(B7,'Факт продаж'!J:L,3,0),"нет продаж") -> 6373.8 | I7: =IFERROR(VLOOKUP(B7,'Факт продаж'!J:N,5,0),"нет продаж") -> 2945.7462 | J7: =IFERROR(VLOOKUP(B7,'Факт продаж'!J:L,3,0)/SUM('План Антонова'!$C$14:$C$16),0) -> 4.4010198e-05 | K7: =IFERROR(VLOOKUP(B7,'Факт продаж'!J:O,6,0),"-") -> 1 | L7: =IF(AND(F7=0,J7>0),5,IF(J7/F7>5,5,IF(J7/F7=0,0.0000001,J7/F7))) -> 5 | M7: =IFERROR(VLOOKUP(B7,'Факт продаж'!S:T,2,0),"нет продаж") -> 1 | N7: =IFERROR(VLOOKUP(B7,'Факт продаж'!S:U,3,0),"нет продаж") -> 2345.3 | O7: =IFERROR(VLOOKUP(B7,'Факт продаж'!S:W,5,0),"нет продаж") -> 991.63304 | P7: =IFERROR(VLOOKUP(B7,'Факт продаж'!S:U,3,0)/SUM('План Антонова'!$C$17:$C$19),0) -> 1.428534e-05 | Q7: =IFERROR(VLOOKUP(B7,'Факт продаж'!S:X,6,0),"-") -> -0.66336779 | R7: =IF(AND(J7=0,P7>0),5,IF(P7/J7>5,5,IF(P7/J7=0,0.0000001,P7/J7))) -> 0.3245916 | S7: =IFERROR(VLOOKUP(B7,'Факт продаж'!AB:AD,2,0),"нет продаж") -> нет продаж | T7: =IFERROR(VLOOKUP(B7,'Факт продаж'!AB:AD,3,0),"нет продаж") -> нет продаж | U7: =IFERROR(VLOOKUP(B7,'Факт продаж'!AB:AF,5,0),"нет продаж") -> нет продаж | V7: =IFERROR(VLOOKUP(B7,'Факт продаж'!AB:AD,3,0)/SUM('План Антонова'!$C$20:$C$22),0) -> 0 | W7: =IFERROR(VLOOKUP(B7,'Факт продаж'!AB:AG,6,0),"-") -> - | X7: =IF(AND(P7=0,V7>0),5,IF(V7/P7>5,5,IF(V7/P7=0,0.0000001,V7/P7))) -> 1e-07 | Y7: =IFERROR(VLOOKUP(B7,'Факт продаж'!AB:AH,7,0),"-") -> - | Z7: =IF(AND(F7=0,V7>0),5,IF(V7/F7>5,5,IF(V7/F7=0,0.0000001,V7/F7))) -> #DIV/0! | AB7: =IFERROR(VLOOKUP(VALUE(IF(L7<1,1,0)&IF(J7<'Факт продаж'!$M$24,0,1)),$AB$1:$AC$4,2,FALSE),"НЕТ ПРОДАЖ") -> Темная лошадка | AC7: =IFERROR(VLOOKUP(VALUE(IF(R7<1,1,0)&IF(P7<'Факт продаж'!$V$24,0,1)),$AB$1:$AC$4,2,FALSE),"НЕТ ПРОДАЖ") -> Собака | AD7: =IFERROR(VLOOKUP(VALUE(IF(X7<1,1,0)&IF(V7<'Факт продаж'!$AE$24,0,1)),$AB$1:$AC$4,2,FALSE),"НЕТ ПРОДАЖ") -> Собака | AE7: =IFERROR(VLOOKUP(VALUE(IF(Z7<1,1,0)&IF(V7<'Факт продаж'!$AE$24,0,1)),$AB$1:$AC$4,2,FALSE),"НЕТ ПРОДАЖ") -> НЕТ ПРОДАЖ | AF7: =VLOOKUP(B7,'ABC расчет'!B:G,6,0) -> C | AG7: =VLOOKUP(B7,'ABC расчет'!K:P,6,0) -> C | AH7: =VLOOKUP(B7,'ABC расчет'!T:Y,6,0) -> C | AI7: =VLOOKUP(B7,'ABC расчет'!AC:AH,6,0) -> C
A8: КОМПЛЕКТУЮЩИЕ СТОЛОВ, КРЕСЕЛ И СТУЛЬЕВ ОБЕДЕННЫХ | B8: KAJA | C8: =IFERROR(VLOOKUP(B8,'Факт продаж'!A:B,2,0),"нет продаж") -> нет продаж | D8: =IFERROR(VLOOKUP(B8,'Факт продаж'!A:C,3,0),"нет продаж") -> нет продаж | E8: =IFERROR(VLOOKUP(B8,'Факт продаж'!A:E,5,0),"нет продаж") -> нет продаж | F8: =IFERROR(VLOOKUP(B8,'Факт продаж'!A:C,3,0)/SUM('План Антонова'!$C$11:$C$13),0) -> 0 | G8: =IFERROR(VLOOKUP(B8,'Факт продаж'!J:K,2,0),"нет продаж") -> 20 | H8: =IFERROR(VLOOKUP(B8,'Факт продаж'!J:L,3,0),"нет продаж") -> 20577.1 | I8: =IFERROR(VLOOKUP(B8,'Факт продаж'!J:N,5,0),"нет продаж") -> 12818.378 | J8: =IFERROR(VLOOKUP(B8,'Факт продаж'!J:L,3,0)/SUM('План Антонова'!$C$14:$C$16),0) -> 0.000142082 | K8: =IFERROR(VLOOKUP(B8,'Факт продаж'!J:O,6,0),"-") -> 1 | L8: =IF(AND(F8=0,J8>0),5,IF(J8/F8>5,5,IF(J8/F8=0,0.0000001,J8/F8))) -> 5 | M8: =IFERROR(VLOOKUP(B8,'Факт продаж'!S:T,2,0),"нет продаж") -> 7 | N8: =IFERROR(VLOOKUP(B8,'Факт продаж'!S:U,3,0),"нет продаж") -> 7042 | O8: =IFERROR(VLOOKUP(B8,'Факт продаж'!S:W,5,0),"нет продаж") -> 4047.5662 | P8: =IFERROR(VLOOKUP(B8,'Факт продаж'!S:U,3,0)/SUM('План Антонова'!$C$17:$C$19),0) -> 4.2893177e-05 | Q8: =IFERROR(VLOOKUP(B8,'Факт продаж'!S:X,6,0),"-") -> -0.68423726 | R8: =IF(AND(J8=0,P8>0),5,IF(P8/J8>5,5,IF(P8/J8=0,0.0000001,P8/J8))) -> 0.30189029 | S8: =IFERROR(VLOOKUP(B8,'Факт продаж'!AB:AD,2,0),"нет продаж") -> нет продаж | T8: =IFERROR(VLOOKUP(B8,'Факт продаж'!AB:AD,3,0),"нет продаж") -> нет продаж | U8: =IFERROR(VLOOKUP(B8,'Факт продаж'!AB:AF,5,0),"нет продаж") -> нет продаж | V8: =IFERROR(VLOOKUP(B8,'Факт продаж'!AB:AD,3,0)/SUM('План Антонова'!$C$20:$C$22),0) -> 0 | W8: =IFERROR(VLOOKUP(B8,'Факт продаж'!AB:AG,6,0),"-") -> - | X8: =IF(AND(P8=0,V8>0),5,IF(V8/P8>5,5,IF(V8/P8=0,0.0000001,V8/P8))) -> 1e-07 | Y8: =IFERROR(VLOOKUP(B8,'Факт продаж'!AB:AH,7,0),"-") -> - | Z8: =IF(AND(F8=0,V8>0),5,IF(V8/F8>5,5,IF(V8/F8=0,0.0000001,V8/F8))) -> #DIV/0! | AB8: =IFERROR(VLOOKUP(VALUE(IF(L8<1,1,0)&IF(J8<'Факт продаж'!$M$24,0,1)),$AB$1:$AC$4,2,FALSE),"НЕТ ПРОДАЖ") -> Темная лошадка | AC8: =IFERROR(VLOOKUP(VALUE(IF(R8<1,1,0)&IF(P8<'Факт продаж'!$V$24,0,1)),$AB$1:$AC$4,2,FALSE),"НЕТ ПРОДАЖ") -> Собака | AD8: =IFERROR(VLOOKUP(VALUE(IF(X8<1,1,0)&IF(V8<'Факт продаж'!$AE$24,0,1)),$AB$1:$AC$4,2,FALSE),"НЕТ ПРОДАЖ") -> Собака | AE8: =IFERROR(VLOOKUP(VALUE(IF(Z8<1,1,0)&IF(V8<'Факт продаж'!$AE$24,0,1)),$AB$1:$AC$4,2,FALSE),"НЕТ ПРОДАЖ") -> НЕТ ПРОДАЖ | AF8: =VLOOKUP(B8,'ABC расчет'!B:G,6,0) -> C | AG8: =VLOOKUP(B8,'ABC расчет'!K:P,6,0) -> C | AH8: =VLOOKUP(B8,'ABC расчет'!T:Y,6,0) -> C | AI8: =VLOOKUP(B8,'ABC расчет'!AC:AH,6,0) -> C
A9: КОМПЛЕКТУЮЩИЕ СТОЛОВ, КРЕСЕЛ И СТУЛЬЕВ ОБЕДЕННЫХ | B9: РАМА CFS | C9: =IFERROR(VLOOKUP(B9,'Факт продаж'!A:B,2,0),"нет продаж") -> 80 | D9: =IFERROR(VLOOKUP(B9,'Факт продаж'!A:C,3,0),"нет продаж") -> 29918.327 | E9: =IFERROR(VLOOKUP(B9,'Факт продаж'!A:E,5,0),"нет продаж") -> 16304.501 | F9: =IFERROR(VLOOKUP(B9,'Факт продаж'!A:C,3,0)/SUM('План Антонова'!$C$11:$C$13),0) -> 0.00022717303 | G9: =IFERROR(VLOOKUP(B9,'Факт продаж'!J:K,2,0),"нет продаж") -> 15 | H9: =IFERROR(VLOOKUP(B9,'Факт продаж'!J:L,3,0),"нет продаж") -> 7035.2 | I9: =IFERROR(VLOOKUP(B9,'Факт продаж'!J:N,5,0),"нет продаж") -> 1246.4195 | J9: =IFERROR(VLOOKUP(B9,'Факт продаж'!J:L,3,0)/SUM('План Антонова'!$C$14:$C$16),0) -> 4.8577073e-05 | K9: =IFERROR(VLOOKUP(B9,'Факт продаж'!J:O,6,0),"-") -> -0.92355365 | L9: =IF(AND(F9=0,J9>0),5,IF(J9/F9>5,5,IF(J9/F9=0,0.0000001,J9/F9))) -> 0.21383292 | M9: =IFERROR(VLOOKUP(B9,'Факт продаж'!S:T,2,0),"нет продаж") -> 10 | N9: =IFERROR(VLOOKUP(B9,'Факт продаж'!S:U,3,0),"нет продаж") -> 5815 | O9: =IFERROR(VLOOKUP(B9,'Факт продаж'!S:W,5,0),"нет продаж") -> 1102.8124 | P9: =IFERROR(VLOOKUP(B9,'Факт продаж'!S:U,3,0)/SUM('План Антонова'!$C$17:$C$19),0) -> 3.5419458e-05 | Q9: =IFERROR(VLOOKUP(B9,'Факт продаж'!S:X,6,0),"-") -> -0.11521569 | R9: =IF(AND(J9=0,P9>0),5,IF(P9/J9>5,5,IF(P9/J9=0,0.0000001,P9/J9))) -> 0.72913941 | S9: =IFERROR(VLOOKUP(B9,'Факт продаж'!AB:AD,2,0),"нет продаж") -> нет продаж | T9: =IFERROR(VLOOKUP(B9,'Факт продаж'!AB:AD,3,0),"нет продаж") -> нет продаж | U9: =IFERROR(VLOOKUP(B9,'Факт продаж'!AB:AF,5,0),"нет продаж") -> нет продаж | V9: =IFERROR(VLOOKUP(B9,'Факт продаж'!AB:AD,3,0)/SUM('План Антонова'!$C$20:$C$22),0) -> 0 | W9: =IFERROR(VLOOKUP(B9,'Факт продаж'!AB:AG,6,0),"-") -> - | X9: =IF(AND(P9=0,V9>0),5,IF(V9/P9>5,5,IF(V9/P9=0,0.0000001,V9/P9))) -> 1e-07 | Y9: =IFERROR(VLOOKUP(B9,'Факт продаж'!AB:AH,7,0),"-") -> - | Z9: =IF(AND(F9=0,V9>0),5,IF(V9/F9>5,5,IF(V9/F9=0,0.0000001,V9/F9))) -> 1e-07 | AB9: =IFERROR(VLOOKUP(VALUE(IF(L9<1,1,0)&IF(J9<'Факт продаж'!$M$24,0,1)),$AB$1:$AC$4,2,FALSE),"НЕТ ПРОДАЖ") -> Собака | AC9: =IFERROR(VLOOKUP(VALUE(IF(R9<1,1,0)&IF(P9<'Факт продаж'!$V$24,0,1)),$AB$1:$AC$4,2,FALSE),"НЕТ ПРОДАЖ") -> Собака | AD9: =IFERROR(VLOOKUP(VALUE(IF(X9<1,1,0)&IF(V9<'Факт продаж'!$AE$24,0,1)),$AB$1:$AC$4,2,FALSE),"НЕТ ПРОДАЖ") -> Собака | AE9: =IFERROR(VLOOKUP(VALUE(IF(Z9<1,1,0)&IF(V9<'Факт продаж'!$AE$24,0,1)),$AB$1:$AC$4,2,FALSE),"НЕТ ПРОДАЖ") -> Собака | AF9: =VLOOKUP(B9,'ABC расчет'!B:G,6,0) -> A | AG9: =VLOOKUP(B9,'ABC расчет'!K:P,6,0) -> C | AH9: =VLOOKUP(B9,'ABC расчет'!T:Y,6,0) -> C | AI9: =VLOOKUP(B9,'ABC расчет'!AC:AH,6,0) -> C
A10: КОМПЛЕКТУЮЩИЕ СТОЛОВ, КРЕСЕЛ И СТУЛЬЕВ ОБЕДЕННЫХ | B10: РАМА NXL | C10: =IFERROR(VLOOKUP(B10,'Факт продаж'!A:B,2,0),"нет продаж") -> нет продаж | D10: =IFERROR(VLOOKUP(B10,'Факт продаж'!A:C,3,0),"нет продаж") -> нет продаж | E10: =IFERROR(VLOOKUP(B10,'Факт продаж'!A:E,5,0),"нет продаж") -> нет продаж | F10: =IFERROR(VLOOKUP(B10,'Факт продаж'!A:C,3,0)/SUM('План Антонова'!$C$11:$C$13),0) -> 0 | G10: =IFERROR(VLOOKUP(B10,'Факт продаж'!J:K,2,0),"нет продаж") -> нет продаж | H10: =IFERROR(VLOOKUP(B10,'Факт продаж'!J:L,3,0),"нет продаж") -> нет продаж | I10: =IFERROR(VLOOKUP(B10,'Факт продаж'!J:N,5,0),"нет продаж") -> нет продаж | J10: =IFERROR(VLOOKUP(B10,'Факт продаж'!J:L,3,0)/SUM('План Антонова'!$C$14:$C$16),0) -> 0 | K10: =IFERROR(VLOOKUP(B10,'Факт продаж'!J:O,6,0),"-") -> - | L10: =IF(AND(F10=0,J10>0),5,IF(J10/F10>5,5,IF(J10/F10=0,0.0000001,J10/F10))) -> #DIV/0! | M10: =IFERROR(VLOOKUP(B10,'Факт продаж'!S:T,2,0),"нет продаж") -> нет продаж | N10: =IFERROR(VLOOKUP(B10,'Факт продаж'!S:U,3,0),"нет продаж") -> нет продаж | O10: =IFERROR(VLOOKUP(B10,'Факт продаж'!S:W,5,0),"нет продаж") -> нет продаж | P10: =IFERROR(VLOOKUP(B10,'Факт продаж'!S:U,3,0)/SUM('План Антонова'!$C$17:$C$19),0) -> 0 | Q10: =IFERROR(VLOOKUP(B10,'Факт продаж'!S:X,6,0),"-") -> - | R10: =IF(AND(J10=0,P10>0),5,IF(P10/J10>5,5,IF(P10/J10=0,0.0000001,P10/J10))) -> #DIV/0! | S10: =IFERROR(VLOOKUP(B10,'Факт продаж'!AB:AD,2,0),"нет продаж") -> нет продаж | T10: =IFERROR(VLOOKUP(B10,'Факт продаж'!AB:AD,3,0),"нет продаж") -> нет продаж | U10: =IFERROR(VLOOKUP(B10,'Факт продаж'!AB:AF,5,0),"нет продаж") -> нет продаж | V10: =IFERROR(VLOOKUP(B10,'Факт продаж'!AB:AD,3,0)/SUM('План Антонова'!$C$20:$C$22),0) -> 0 | W10: =IFERROR(VLOOKUP(B10,'Факт продаж'!AB:AG,6,0),"-") -> - | X10: =IF(AND(P10=0,V10>0),5,IF(V10/P10>5,5,IF(V10/P10=0,0.0000001,V10/P10))) -> #DIV/0! | Y10: =IFERROR(VLOOKUP(B10,'Факт продаж'!AB:AH,7,0),"-") -> - | Z10: =IF(AND(F10=0,V10>0),5,IF(V10/F10>5,5,IF(V10/F10=0,0.0000001,V10/F10))) -> #DIV/0! | AB10: =IFERROR(VLOOKUP(VALUE(IF(L10<1,1,0)&IF(J10<'Факт продаж'!$M$24,0,1)),$AB$1:$AC$4,2,FALSE),"НЕТ ПРОДАЖ") -> НЕТ ПРОДАЖ | AC10: =IFERROR(VLOOKUP(VALUE(IF(R10<1,1,0)&IF(P10<'Факт продаж'!$V$24,0,1)),$AB$1:$AC$4,2,FALSE),"НЕТ ПРОДАЖ") -> НЕТ ПРОДАЖ | AD10: =IFERROR(VLOOKUP(VALUE(IF(X10<1,1,0)&IF(V10<'Факт продаж'!$AE$24,0,1)),$AB$1:$AC$4,2,FALSE),"НЕТ ПРОДАЖ") -> НЕТ ПРОДАЖ | AE10: =IFERROR(VLOOKUP(VALUE(IF(Z10<1,1,0)&IF(V10<'Факт продаж'!$AE$24,0,1)),$AB$1:$AC$4,2,FALSE),"НЕТ ПРОДАЖ") -> НЕТ ПРОДАЖ | AF10: =VLOOKUP(B10,'ABC расчет'!B:G,6,0) -> C | AG10: =VLOOKUP(B10,'ABC расчет'!K:P,6,0) -> C | AH10: =VLOOKUP(B10,'ABC расчет'!T:Y,6,0) -> C | AI10: =VLOOKUP(B10,'ABC расчет'!AC:AH,6,0) -> C | AL10: Есть продажи по ГП
A11: КРЕСЛА ДЕТСКИЕ | B11: MINISIT | C11: =IFERROR(VLOOKUP(B11,'Факт продаж'!A:B,2,0),"нет продаж") -> нет продаж | D11: =IFERROR(VLOOKUP(B11,'Факт продаж'!A:C,3,0),"нет продаж") -> нет продаж | E11: =IFERROR(VLOOKUP(B11,'Факт продаж'!A:E,5,0),"нет продаж") -> нет продаж | F11: =IFERROR(VLOOKUP(B11,'Факт продаж'!A:C,3,0)/SUM('План Антонова'!$C$11:$C$13),0) -> 0 | G11: =IFERROR(VLOOKUP(B11,'Факт продаж'!J:K,2,0),"нет продаж") -> нет продаж | H11: =IFERROR(VLOOKUP(B11,'Факт продаж'!J:L,3,0),"нет продаж") -> нет продаж | I11: =IFERROR(VLOOKUP(B11,'Факт продаж'!J:N,5,0),"нет продаж") -> нет продаж | J11: =IFERROR(VLOOKUP(B11,'Факт продаж'!J:L,3,0)/SUM('План Антонова'!$C$14:$C$16),0) -> 0 | K11: =IFERROR(VLOOKUP(B11,'Факт продаж'!J:O,6,0),"-") -> - | L11: =IF(AND(F11=0,J11>0),5,IF(J11/F11>5,5,IF(J11/F11=0,0.0000001,J11/F11))) -> #DIV/0! | M11: =IFERROR(VLOOKUP(B11,'Факт продаж'!S:T,2,0),"нет продаж") -> нет продаж | N11: =IFERROR(VLOOKUP(B11,'Факт продаж'!S:U,3,0),"нет продаж") -> нет продаж | O11: =IFERROR(VLOOKUP(B11,'Факт продаж'!S:W,5,0),"нет продаж") -> нет продаж | P11: =IFERROR(VLOOKUP(B11,'Факт продаж'!S:U,3,0)/SUM('План Антонова'!$C$17:$C$19),0) -> 0 | Q11: =IFERROR(VLOOKUP(B11,'Факт продаж'!S:X,6,0),"-") -> - | R11: =IF(AND(J11=0,P11>0),5,IF(P11/J11>5,5,IF(P11/J11=0,0.0000001,P11/J11))) -> #DIV/0! | S11: =IFERROR(VLOOKUP(B11,'Факт продаж'!AB:AD,2,0),"нет продаж") -> нет продаж | T11: =IFERROR(VLOOKUP(B11,'Факт продаж'!AB:AD,3,0),"нет продаж") -> нет продаж | U11: =IFERROR(VLOOKUP(B11,'Факт продаж'!AB:AF,5,0),"нет продаж") -> нет продаж | V11: =IFERROR(VLOOKUP(B11,'Факт продаж'!AB:AD,3,0)/SUM('План Антонова'!$C$20:$C$22),0) -> 0 | W11: =IFERROR(VLOOKUP(B11,'Факт продаж'!AB:AG,6,0),"-") -> - | X11: =IF(AND(P11=0,V11>0),5,IF(V11/P11>5,5,IF(V11/P11=0,0.0000001,V11/P11))) -> #DIV/0! | Y11: =IFERROR(VLOOKUP(B11,'Факт продаж'!AB:AH,7,0),"-") -> - | Z11: =IF(AND(F11=0,V11>0),5,IF(V11/F11>5,5,IF(V11/F11=0,0.0000001,V11/F11))) -> #DIV/0! | AB11: =IFERROR(VLOOKUP(VALUE(IF(L11<1,1,0)&IF(J11<'Факт продаж'!$M$24,0,1)),$AB$1:$AC$4,2,FALSE),"НЕТ ПРОДАЖ") -> НЕТ ПРОДАЖ | AC11: =IFERROR(VLOOKUP(VALUE(IF(R11<1,1,0)&IF(P11<'Факт продаж'!$V$24,0,1)),$AB$1:$AC$4,2,FALSE),"НЕТ ПРОДАЖ") -> НЕТ ПРОДАЖ | AD11: =IFERROR(VLOOKUP(VALUE(IF(X11<1,1,0)&IF(V11<'Факт продаж'!$AE$24,0,1)),$AB$1:$AC$4,2,FALSE),"НЕТ ПРОДАЖ") -> НЕТ ПРОДАЖ | AE11: =IFERROR(VLOOKUP(VALUE(IF(Z11<1,1,0)&IF(V11<'Факт продаж'!$AE$24,0,1)),$AB$1:$AC$4,2,FALSE),"НЕТ ПРОДАЖ") -> НЕТ ПРОДАЖ | AF11: =VLOOKUP(B11,'ABC расчет'!B:G,6,0) -> C | AG11: =VLOOKUP(B11,'ABC расчет'!K:P,6,0) -> C | AH11: =VLOOKUP(B11,'ABC расчет'!T:Y,6,0) -> C | AI11: =VLOOKUP(B11,'ABC расчет'!AC:AH,6,0) -> C | AL11: Новинка
A12: КРЕСЛА ОПЕРАТОРСКИЕ | B12: NAVIGO | C12: =IFERROR(VLOOKUP(B12,'Факт продаж'!A:B,2,0),"нет продаж") -> 71 | D12: =IFERROR(VLOOKUP(B12,'Факт продаж'!A:C,3,0),"нет продаж") -> 427449.99 | E12: =IFERROR(VLOOKUP(B12,'Факт продаж'!A:E,5,0),"нет продаж") -> 160292.53 | F12: =IFERROR(VLOOKUP(B12,'Факт продаж'!A:C,3,0)/SUM('План Антонова'!$C$11:$C$13),0) -> 0.003245673 | G12: =IFERROR(VLOOKUP(B12,'Факт продаж'!J:K,2,0),"нет продаж") -> 3 | H12: =IFERROR(VLOOKUP(B12,'Факт продаж'!J:L,3,0),"нет продаж") -> 20065.1 | I12: =IFERROR(VLOOKUP(B12,'Факт продаж'!J:N,5,0),"нет продаж") -> 8373.5612 | J12: =IFERROR(VLOOKUP(B12,'Факт продаж'!J:L,3,0)/SUM('План Антонова'!$C$14:$C$16),0) -> 0.00013854671 | K12: =IFERROR(VLOOKUP(B12,'Факт продаж'!J:O,6,0),"-") -> -0.94776075 | L12: =IF(AND(F12=0,J12>0),5,IF(J12/F12>5,5,IF(J12/F12=0,0.0000001,J12/F12))) -> 0.042686589 | M12: =IFERROR(VLOOKUP(B12,'Факт продаж'!S:T,2,0),"нет продаж") -> 1 | N12: =IFERROR(VLOOKUP(B12,'Факт продаж'!S:U,3,0),"нет продаж") -> 9082.5 | O12: =IFERROR(VLOOKUP(B12,'Факт продаж'!S:W,5,0),"нет продаж") -> 4485.7401 | P12: =IFERROR(VLOOKUP(B12,'Факт продаж'!S:U,3,0)/SUM('План Антонова'!$C$17:$C$19),0) -> 5.5321965e-05 | Q12: =IFERROR(VLOOKUP(B12,'Факт продаж'!S:X,6,0),"-") -> -0.46429721 | R12: =IF(AND(J12=0,P12>0),5,IF(P12/J12>5,5,IF(P12/J12=0,0.0000001,P12/J12))) -> 0.3993019 | S12: =IFERROR(VLOOKUP(B12,'Факт продаж'!AB:AD,2,0),"нет продаж") -> нет продаж | T12: =IFERROR(VLOOKUP(B12,'Факт продаж'!AB:AD,3,0),"нет продаж") -> нет продаж | U12: =IFERROR(VLOOKUP(B12,'Факт продаж'!AB:AF,5,0),"нет продаж") -> нет продаж | V12: =IFERROR(VLOOKUP(B12,'Факт продаж'!AB:AD,3,0)/SUM('План Антонова'!$C$20:$C$22),0) -> 0 | W12: =IFERROR(VLOOKUP(B12,'Факт продаж'!AB:AG,6,0),"-") -> - | X12: =IF(AND(P12=0,V12>0),5,IF(V12/P12>5,5,IF(V12/P12=0,0.0000001,V12/P12))) -> 1e-07 | Y12: =IFERROR(VLOOKUP(B12,'Факт продаж'!AB:AH,7,0),"-") -> - | Z12: =IF(AND(F12=0,V12>0),5,IF(V12/F12>5,5,IF(V12/F12=0,0.0000001,V12/F12))) -> 1e-07 | AB12: =IFERROR(VLOOKUP(VALUE(IF(L12<1,1,0)&IF(J12<'Факт продаж'!$M$24,0,1)),$AB$1:$AC$4,2,FALSE),"НЕТ ПРОДАЖ") -> Собака | AC12: =IFERROR(VLOOKUP(VALUE(IF(R12<1,1,0)&IF(P12<'Факт продаж'!$V$24,0,1)),$AB$1:$AC$4,2,FALSE),"НЕТ ПРОДАЖ") -> Собака | AD12: =IFERROR(VLOOKUP(VALUE(IF(X12<1,1,0)&IF(V12<'Факт продаж'!$AE$24,0,1)),$AB$1:$AC$4,2,FALSE),"НЕТ ПРОДАЖ") -> Собака | AE12: =IFERROR(VLOOKUP(VALUE(IF(Z12<1,1,0)&IF(V12<'Факт продаж'!$AE$24,0,1)),$AB$1:$AC$4,2,FALSE),"НЕТ ПРОДАЖ") -> Собака | AF12: =VLOOKUP(B12,'ABC расчет'!B:G,6,0) -> A | AG12: =VLOOKUP(B12,'ABC расчет'!K:P,6,0) -> C | AH12: =VLOOKUP(B12,'ABC расчет'!T:Y,6,0) -> C | AI12: =VLOOKUP(B12,'ABC расчет'!AC:AH,6,0) -> C
A13: КРЕСЛА РУКОВОДИТЕЛЯ | B13: FLORIDA | C13: =IFERROR(VLOOKUP(B13,'Факт продаж'!A:B,2,0),"нет продаж") -> 7 | D13: =IFERROR(VLOOKUP(B13,'Факт продаж'!A:C,3,0),"нет продаж") -> 36352.268 | E13: =IFERROR(VLOOKUP(B13,'Факт продаж'!A:E,5,0),"нет продаж") -> 18826.819 | F13: =IFERROR(VLOOKUP(B13,'Факт продаж'!A:C,3,0)/SUM('План Антонова'!$C$11:$C$13),0) -> 0.00027602662 | G13: =IFERROR(VLOOKUP(B13,'Факт продаж'!J:K,2,0),"нет продаж") -> нет продаж | H13: =IFERROR(VLOOKUP(B13,'Факт продаж'!J:L,3,0),"нет продаж") -> нет продаж | I13: =IFERROR(VLOOKUP(B13,'Факт продаж'!J:N,5,0),"нет продаж") -> нет продаж | J13: =IFERROR(VLOOKUP(B13,'Факт продаж'!J:L,3,0)/SUM('План Антонова'!$C$14:$C$16),0) -> 0 | K13: =IFERROR(VLOOKUP(B13,'Факт продаж'!J:O,6,0),"-") -> - | L13: =IF(AND(F13=0,J13>0),5,IF(J13/F13>5,5,IF(J13/F13=0,0.0000001,J13/F13))) -> 1e-07 | M13: =IFERROR(VLOOKUP(B13,'Факт продаж'!S:T,2,0),"нет продаж") -> нет продаж | N13: =IFERROR(VLOOKUP(B13,'Факт продаж'!S:U,3,0),"нет продаж") -> нет продаж | O13: =IFERROR(VLOOKUP(B13,'Факт продаж'!S:W,5,0),"нет продаж") -> нет продаж | P13: =IFERROR(VLOOKUP(B13,'Факт продаж'!S:U,3,0)/SUM('План Антонова'!$C$17:$C$19),0) -> 0 | Q13: =IFERROR(VLOOKUP(B13,'Факт продаж'!S:X,6,0),"-") -> - | R13: =IF(AND(J13=0,P13>0),5,IF(P13/J13>5,5,IF(P13/J13=0,0.0000001,P13/J13))) -> #DIV/0! | S13: =IFERROR(VLOOKUP(B13,'Факт продаж'!AB:AD,2,0),"нет продаж") -> нет продаж | T13: =IFERROR(VLOOKUP(B13,'Факт продаж'!AB:AD,3,0),"нет продаж") -> нет продаж | U13: =IFERROR(VLOOKUP(B13,'Факт продаж'!AB:AF,5,0),"нет продаж") -> нет продаж | V13: =IFERROR(VLOOKUP(B13,'Факт продаж'!AB:AD,3,0)/SUM('План Антонова'!$C$20:$C$22),0) -> 0 | W13: =IFERROR(VLOOKUP(B13,'Факт продаж'!AB:AG,6,0),"-") -> - | X13: =IF(AND(P13=0,V13>0),5,IF(V13/P13>5,5,IF(V13/P13=0,0.0000001,V13/P13))) -> #DIV/0! | Y13: =IFERROR(VLOOKUP(B13,'Факт продаж'!AB:AH,7,0),"-") -> - | Z13: =IF(AND(F13=0,V13>0),5,IF(V13/F13>5,5,IF(V13/F13=0,0.0000001,V13/F13))) -> 1e-07 | AB13: =IFERROR(VLOOKUP(VALUE(IF(L13<1,1,0)&IF(J13<'Факт продаж'!$M$24,0,1)),$AB$1:$AC$4,2,FALSE),"НЕТ ПРОДАЖ") -> Собака | AC13: =IFERROR(VLOOKUP(VALUE(IF(R13<1,1,0)&IF(P13<'Факт продаж'!$V$24,0,1)),$AB$1:$AC$4,2,FALSE),"НЕТ ПРОДАЖ") -> НЕТ ПРОДАЖ | AD13: =IFERROR(VLOOKUP(VALUE(IF(X13<1,1,0)&IF(V13<'Факт продаж'!$AE$24,0,1)),$AB$1:$AC$4,2,FALSE),"НЕТ ПРОДАЖ") -> НЕТ ПРОДАЖ | AE13: =IFERROR(VLOOKUP(VALUE(IF(Z13<1,1,0)&IF(V13<'Факт продаж'!$AE$24,0,1)),$AB$1:$AC$4,2,FALSE),"НЕТ ПРОДАЖ") -> Собака | AF13: =VLOOKUP(B13,'ABC расчет'!B:G,6,0) -> C | AG13: =VLOOKUP(B13,'ABC расчет'!K:P,6,0) -> C | AH13: =VLOOKUP(B13,'ABC расчет'!T:Y,6,0) -> C | AI13: =VLOOKUP(B13,'ABC расчет'!AC:AH,6,0) -> C
A14: МАТРАСЫ | B14: MAGRO | C14: =IFERROR(VLOOKUP(B14,'Факт продаж'!A:B,2,0),"нет продаж") -> нет продаж | D14: =IFERROR(VLOOKUP(B14,'Факт продаж'!A:C,3,0),"нет продаж") -> нет продаж | E14: =IFERROR(VLOOKUP(B14,'Факт продаж'!A:E,5,0),"нет продаж") -> нет продаж | F14: =IFERROR(VLOOKUP(B14,'Факт продаж'!A:C,3,0)/SUM('План Антонова'!$C$11:$C$13),0) -> 0 | G14: =IFERROR(VLOOKUP(B14,'Факт продаж'!J:K,2,0),"нет продаж") -> 4 | H14: =IFERROR(VLOOKUP(B14,'Факт продаж'!J:L,3,0),"нет продаж") -> 14156 | I14: =IFERROR(VLOOKUP(B14,'Факт продаж'!J:N,5,0),"нет продаж") -> 3040.7744 | J14: =IFERROR(VLOOKUP(B14,'Факт продаж'!J:L,3,0)/SUM('План Антонова'!$C$14:$C$16),0) -> 9.7745201e-05 | K14: =IFERROR(VLOOKUP(B14,'Факт продаж'!J:O,6,0),"-") -> 1 | L14: =IF(AND(F14=0,J14>0),5,IF(J14/F14>5,5,IF(J14/F14=0,0.0000001,J14/F14))) -> 5 | M14: =IFERROR(VLOOKUP(B14,'Факт продаж'!S:T,2,0),"нет продаж") -> 2 | N14: =IFERROR(VLOOKUP(B14,'Факт продаж'!S:U,3,0),"нет продаж") -> 7952 | O14: =IFERROR(VLOOKUP(B14,'Факт продаж'!S:W,5,0),"нет продаж") -> 1677.0747 | P14: =IFERROR(VLOOKUP(B14,'Факт продаж'!S:U,3,0)/SUM('План Антонова'!$C$17:$C$19),0) -> 4.8436033e-05 | Q14: =IFERROR(VLOOKUP(B14,'Факт продаж'!S:X,6,0),"-") -> -0.44847117 | R14: =IF(AND(J14=0,P14>0),5,IF(P14/J14>5,5,IF(P14/J14=0,0.0000001,P14/J14))) -> 0.49553361 | S14: =IFERROR(VLOOKUP(B14,'Факт продаж'!AB:AD,2,0),"нет продаж") -> нет продаж | T14: =IFERROR(VLOOKUP(B14,'Факт продаж'!AB:AD,3,0),"нет продаж") -> нет продаж | U14: =IFERROR(VLOOKUP(B14,'Факт продаж'!AB:AF,5,0),"нет продаж") -> нет продаж | V14: =IFERROR(VLOOKUP(B14,'Факт продаж'!AB:AD,3,0)/SUM('План Антонова'!$C$20:$C$22),0) -> 0 | W14: =IFERROR(VLOOKUP(B14,'Факт продаж'!AB:AG,6,0),"-") -> - | X14: =IF(AND(P14=0,V14>0),5,IF(V14/P14>5,5,IF(V14/P14=0,0.0000001,V14/P14))) -> 1e-07 | Y14: =IFERROR(VLOOKUP(B14,'Факт продаж'!AB:AH,7,0),"-") -> - | Z14: =IF(AND(F14=0,V14>0),5,IF(V14/F14>5,5,IF(V14/F14=0,0.0000001,V14/F14))) -> #DIV/0! | AB14: =IFERROR(VLOOKUP(VALUE(IF(L14<1,1,0)&IF(J14<'Факт продаж'!$M$24,0,1)),$AB$1:$AC$4,2,FALSE),"НЕТ ПРОДАЖ") -> Темная лошадка | AC14: =IFERROR(VLOOKUP(VALUE(IF(R14<1,1,0)&IF(P14<'Факт продаж'!$V$24,0,1)),$AB$1:$AC$4,2,FALSE),"НЕТ ПРОДАЖ") -> Собака | AD14: =IFERROR(VLOOKUP(VALUE(IF(X14<1,1,0)&IF(V14<'Факт продаж'!$AE$24,0,1)),$AB$1:$AC$4,2,FALSE),"НЕТ ПРОДАЖ") -> Собака | AE14: =IFERROR(VLOOKUP(VALUE(IF(Z14<1,1,0)&IF(V14<'Факт продаж'!$AE$24,0,1)),$AB$1:$AC$4,2,FALSE),"НЕТ ПРОДАЖ") -> НЕТ ПРОДАЖ | AF14: =VLOOKUP(B14,'ABC расчет'!B:G,6,0) -> A | AG14: =VLOOKUP(B14,'ABC расчет'!K:P,6,0) -> C | AH14: =VLOOKUP(B14,'ABC расчет'!T:Y,6,0) -> C | AI14: =VLOOKUP(B14,'ABC расчет'!AC:AH,6,0) -> C
A15: МАТРАСЫ | B15: WEENY | C15: =IFERROR(VLOOKUP(B15,'Факт продаж'!A:B,2,0),"нет продаж") -> нет продаж | D15: =IFERROR(VLOOKUP(B15,'Факт продаж'!A:C,3,0),"нет продаж") -> нет продаж | E15: =IFERROR(VLOOKUP(B15,'Факт продаж'!A:E,5,0),"нет продаж") -> нет продаж | F15: =IFERROR(VLOOKUP(B15,'Факт продаж'!A:C,3,0)/SUM('План Антонова'!$C$11:$C$13),0) -> 0 | G15: =IFERROR(VLOOKUP(B15,'Факт продаж'!J:K,2,0),"нет продаж") -> нет продаж | H15: =IFERROR(VLOOKUP(B15,'Факт продаж'!J:L,3,0),"нет продаж") -> нет продаж | I15: =IFERROR(VLOOKUP(B15,'Факт продаж'!J:N,5,0),"нет продаж") -> нет продаж | J15: =IFERROR(VLOOKUP(B15,'Факт продаж'!J:L,3,0)/SUM('План Антонова'!$C$14:$C$16),0) -> 0 | K15: =IFERROR(VLOOKUP(B15,'Факт продаж'!J:O,6,0),"-") -> - | L15: =IF(AND(F15=0,J15>0),5,IF(J15/F15>5,5,IF(J15/F15=0,0.0000001,J15/F15))) -> #DIV/0! | M15: =IFERROR(VLOOKUP(B15,'Факт продаж'!S:T,2,0),"нет продаж") -> нет продаж | N15: =IFERROR(VLOOKUP(B15,'Факт продаж'!S:U,3,0),"нет продаж") -> нет продаж | O15: =IFERROR(VLOOKUP(B15,'Факт продаж'!S:W,5,0),"нет продаж") -> нет продаж | P15: =IFERROR(VLOOKUP(B15,'Факт продаж'!S:U,3,0)/SUM('План Антонова'!$C$17:$C$19),0) -> 0 | Q15: =IFERROR(VLOOKUP(B15,'Факт продаж'!S:X,6,0),"-") -> - | R15: =IF(AND(J15=0,P15>0),5,IF(P15/J15>5,5,IF(P15/J15=0,0.0000001,P15/J15))) -> #DIV/0! | S15: =IFERROR(VLOOKUP(B15,'Факт продаж'!AB:AD,2,0),"нет продаж") -> нет продаж | T15: =IFERROR(VLOOKUP(B15,'Факт продаж'!AB:AD,3,0),"нет продаж") -> нет продаж | U15: =IFERROR(VLOOKUP(B15,'Факт продаж'!AB:AF,5,0),"нет продаж") -> нет продаж | V15: =IFERROR(VLOOKUP(B15,'Факт продаж'!AB:AD,3,0)/SUM('План Антонова'!$C$20:$C$22),0) -> 0 | W15: =IFERROR(VLOOKUP(B15,'Факт продаж'!AB:AG,6,0),"-") -> - | X15: =IF(AND(P15=0,V15>0),5,IF(V15/P15>5,5,IF(V15/P15=0,0.0000001,V15/P15))) -> #DIV/0! | Y15: =IFERROR(VLOOKUP(B15,'Факт продаж'!AB:AH,7,0),"-") -> - | Z15: =IF(AND(F15=0,V15>0),5,IF(V15/F15>5,5,IF(V15/F15=0,0.0000001,V15/F15))) -> #DIV/0! | AB15: =IFERROR(VLOOKUP(VALUE(IF(L15<1,1,0)&IF(J15<'Факт продаж'!$M$24,0,1)),$AB$1:$AC$4,2,FALSE),"НЕТ ПРОДАЖ") -> НЕТ ПРОДАЖ | AC15: =IFERROR(VLOOKUP(VALUE(IF(R15<1,1,0)&IF(P15<'Факт продаж'!$V$24,0,1)),$AB$1:$AC$4,2,FALSE),"НЕТ ПРОДАЖ") -> НЕТ ПРОДАЖ | AD15: =IFERROR(VLOOKUP(VALUE(IF(X15<1,1,0)&IF(V15<'Факт продаж'!$AE$24,0,1)),$AB$1:$AC$4,2,FALSE),"НЕТ ПРОДАЖ") -> НЕТ ПРОДАЖ | AE15: =IFERROR(VLOOKUP(VALUE(IF(Z15<1,1,0)&IF(V15<'Факт продаж'!$AE$24,0,1)),$AB$1:$AC$4,2,FALSE),"НЕТ ПРОДАЖ") -> НЕТ ПРОДАЖ | AF15: =VLOOKUP(B15,'ABC расчет'!B:G,6,0) -> A | AG15: =VLOOKUP(B15,'ABC расчет'!K:P,6,0) -> C | AH15: =VLOOKUP(B15,'ABC расчет'!T:Y,6,0) -> C | AI15: =VLOOKUP(B15,'ABC расчет'!AC:AH,6,0) -> C
A16: МЕБЕЛЬ КОРПУСНАЯ | B16: Верона | C16: =IFERROR(VLOOKUP(B16,'Факт продаж'!A:B,2,0),"нет продаж") -> нет продаж | D16: =IFERROR(VLOOKUP(B16,'Факт продаж'!A:C,3,0),"нет продаж") -> нет продаж | E16: =IFERROR(VLOOKUP(B16,'Факт продаж'!A:E,5,0),"нет продаж") -> нет продаж | F16: =IFERROR(VLOOKUP(B16,'Факт продаж'!A:C,3,0)/SUM('План Антонова'!$C$11:$C$13),0) -> 0 | G16: =IFERROR(VLOOKUP(B16,'Факт продаж'!J:K,2,0),"нет продаж") -> 9 | H16: =IFERROR(VLOOKUP(B16,'Факт продаж'!J:L,3,0),"нет продаж") -> 85401.95 | I16: =IFERROR(VLOOKUP(B16,'Факт продаж'!J:N,5,0),"нет продаж") -> 42933.705 | J16: =IFERROR(VLOOKUP(B16,'Факт продаж'!J:L,3,0)/SUM('План Антонова'!$C$14:$C$16),0) -> 0.00058968853 | K16: =IFERROR(VLOOKUP(B16,'Факт продаж'!J:O,6,0),"-") -> 1 | L16: =IF(AND(F16=0,J16>0),5,IF(J16/F16>5,5,IF(J16/F16=0,0.0000001,J16/F16))) -> 5 | M16: =IFERROR(VLOOKUP(B16,'Факт продаж'!S:T,2,0),"нет продаж") -> нет продаж | N16: =IFERROR(VLOOKUP(B16,'Факт продаж'!S:U,3,0),"нет продаж") -> нет продаж | O16: =IFERROR(VLOOKUP(B16,'Факт продаж'!S:W,5,0),"нет продаж") -> нет продаж | P16: =IFERROR(VLOOKUP(B16,'Факт продаж'!S:U,3,0)/SUM('План Антонова'!$C$17:$C$19),0) -> 0 | Q16: =IFERROR(VLOOKUP(B16,'Факт продаж'!S:X,6,0),"-") -> - | R16: =IF(AND(J16=0,P16>0),5,IF(P16/J16>5,5,IF(P16/J16=0,0.0000001,P16/J16))) -> 1e-07 | S16: =IFERROR(VLOOKUP(B16,'Факт продаж'!AB:AD,2,0),"нет продаж") -> нет продаж | T16: =IFERROR(VLOOKUP(B16,'Факт продаж'!AB:AD,3,0),"нет продаж") -> нет продаж | U16: =IFERROR(VLOOKUP(B16,'Факт продаж'!AB:AF,5,0),"нет продаж") -> нет продаж | V16: =IFERROR(VLOOKUP(B16,'Факт продаж'!AB:AD,3,0)/SUM('План Антонова'!$C$20:$C$22),0) -> 0 | W16: =IFERROR(VLOOKUP(B16,'Факт продаж'!AB:AG,6,0),"-") -> - | X16: =IF(AND(P16=0,V16>0),5,IF(V16/P16>5,5,IF(V16/P16=0,0.0000001,V16/P16))) -> #DIV/0! | Y16: =IFERROR(VLOOKUP(B16,'Факт продаж'!AB:AH,7,0),"-") -> - | Z16: =IF(AND(F16=0,V16>0),5,IF(V16/F16>5,5,IF(V16/F16=0,0.0000001,V16/F16))) -> #DIV/0! | AB16: =IFERROR(VLOOKUP(VALUE(IF(L16<1,1,0)&IF(J16<'Факт продаж'!$M$24,0,1)),$AB$1:$AC$4,2,FALSE),"НЕТ ПРОДАЖ") -> Темная лошадка | AC16: =IFERROR(VLOOKUP(VALUE(IF(R16<1,1,0)&IF(P16<'Факт продаж'!$V$24,0,1)),$AB$1:$AC$4,2,FALSE),"НЕТ ПРОДАЖ") -> Собака | AD16: =IFERROR(VLOOKUP(VALUE(IF(X16<1,1,0)&IF(V16<'Факт продаж'!$AE$24,0,1)),$AB$1:$AC$4,2,FALSE),"НЕТ ПРОДАЖ") -> НЕТ ПРОДАЖ | AE16: =IFERROR(VLOOKUP(VALUE(IF(Z16<1,1,0)&IF(V16<'Факт продаж'!$AE$24,0,1)),$AB$1:$AC$4,2,FALSE),"НЕТ ПРОДАЖ") -> НЕТ ПРОДАЖ | AF16: =VLOOKUP(B16,'ABC расчет'!B:G,6,0) -> C | AG16: =VLOOKUP(B16,'ABC расчет'!K:P,6,0) -> C | AH16: =VLOOKUP(B16,'ABC расчет'!T:Y,6,0) -> C | AI16: =VLOOKUP(B16,'ABC расчет'!AC:AH,6,0) -> C
A17: МЕБЕЛЬ КОРПУСНАЯ | B17: Сплит | C17: =IFERROR(VLOOKUP(B17,'Факт продаж'!A:B,2,0),"нет продаж") -> нет продаж | D17: =IFERROR(VLOOKUP(B17,'Факт продаж'!A:C,3,0),"нет продаж") -> нет продаж | E17: =IFERROR(VLOOKUP(B17,'Факт продаж'!A:E,5,0),"нет продаж") -> нет продаж | F17: =IFERROR(VLOOKUP(B17,'Факт продаж'!A:C,3,0)/SUM('План Антонова'!$C$11:$C$13),0) -> 0 | G17: =IFERROR(VLOOKUP(B17,'Факт продаж'!J:K,2,0),"нет продаж") -> нет продаж | H17: =IFERROR(VLOOKUP(B17,'Факт продаж'!J:L,3,0),"нет продаж") -> нет продаж | I17: =IFERROR(VLOOKUP(B17,'Факт продаж'!J:N,5,0),"нет продаж") -> нет продаж | J17: =IFERROR(VLOOKUP(B17,'Факт продаж'!J:L,3,0)/SUM('План Антонова'!$C$14:$C$16),0) -> 0 | K17: =IFERROR(VLOOKUP(B17,'Факт продаж'!J:O,6,0),"-") -> - | L17: =IF(AND(F17=0,J17>0),5,IF(J17/F17>5,5,IF(J17/F17=0,0.0000001,J17/F17))) -> #DIV/0! | M17: =IFERROR(VLOOKUP(B17,'Факт продаж'!S:T,2,0),"нет продаж") -> нет продаж | N17: =IFERROR(VLOOKUP(B17,'Факт продаж'!S:U,3,0),"нет продаж") -> нет продаж | O17: =IFERROR(VLOOKUP(B17,'Факт продаж'!S:W,5,0),"нет продаж") -> нет продаж | P17: =IFERROR(VLOOKUP(B17,'Факт продаж'!S:U,3,0)/SUM('План Антонова'!$C$17:$C$19),0) -> 0 | Q17: =IFERROR(VLOOKUP(B17,'Факт продаж'!S:X,6,0),"-") -> - | R17: =IF(AND(J17=0,P17>0),5,IF(P17/J17>5,5,IF(P17/J17=0,0.0000001,P17/J17))) -> #DIV/0! | S17: =IFERROR(VLOOKUP(B17,'Факт продаж'!AB:AD,2,0),"нет продаж") -> нет продаж | T17: =IFERROR(VLOOKUP(B17,'Факт продаж'!AB:AD,3,0),"нет продаж") -> нет продаж | U17: =IFERROR(VLOOKUP(B17,'Факт продаж'!AB:AF,5,0),"нет продаж") -> нет продаж | V17: =IFERROR(VLOOKUP(B17,'Факт продаж'!AB:AD,3,0)/SUM('План Антонова'!$C$20:$C$22),0) -> 0 | W17: =IFERROR(VLOOKUP(B17,'Факт продаж'!AB:AG,6,0),"-") -> - | X17: =IF(AND(P17=0,V17>0),5,IF(V17/P17>5,5,IF(V17/P17=0,0.0000001,V17/P17))) -> #DIV/0! | Y17: =IFERROR(VLOOKUP(B17,'Факт продаж'!AB:AH,7,0),"-") -> - | Z17: =IF(AND(F17=0,V17>0),5,IF(V17/F17>5,5,IF(V17/F17=0,0.0000001,V17/F17))) -> #DIV/0! | AB17: =IFERROR(VLOOKUP(VALUE(IF(L17<1,1,0)&IF(J17<'Факт продаж'!$M$24,0,1)),$AB$1:$AC$4,2,FALSE),"НЕТ ПРОДАЖ") -> НЕТ ПРОДАЖ | AC17: =IFERROR(VLOOKUP(VALUE(IF(R17<1,1,0)&IF(P17<'Факт продаж'!$V$24,0,1)),$AB$1:$AC$4,2,FALSE),"НЕТ ПРОДАЖ") -> НЕТ ПРОДАЖ | AD17: =IFERROR(VLOOKUP(VALUE(IF(X17<1,1,0)&IF(V17<'Факт продаж'!$AE$24,0,1)),$AB$1:$AC$4,2,FALSE),"НЕТ ПРОДАЖ") -> НЕТ ПРОДАЖ | AE17: =IFERROR(VLOOKUP(VALUE(IF(Z17<1,1,0)&IF(V17<'Факт продаж'!$AE$24,0,1)),$AB$1:$AC$4,2,FALSE),"НЕТ ПРОДАЖ") -> НЕТ ПРОДАЖ | AF17: =VLOOKUP(B17,'ABC расчет'!B:G,6,0) -> C | AG17: =VLOOKUP(B17,'ABC расчет'!K:P,6,0) -> C | AH17: =VLOOKUP(B17,'ABC расчет'!T:Y,6,0) -> C | AI17: =VLOOKUP(B17,'ABC расчет'!AC:AH,6,0) -> C
A18: ПАРТЫ УЧЕНИЧЕСКИЕ | B18: СТОЛ ДЛЯ СТОЛОВОЙ E-561 | C18: =IFERROR(VLOOKUP(B18,'Факт продаж'!A:B,2,0),"нет продаж") -> нет продаж | D18: =IFERROR(VLOOKUP(B18,'Факт продаж'!A:C,3,0),"нет продаж") -> нет продаж | E18: =IFERROR(VLOOKUP(B18,'Факт продаж'!A:E,5,0),"нет продаж") -> нет продаж | F18: =IFERROR(VLOOKUP(B18,'Факт продаж'!A:C,3,0)/SUM('План Антонова'!$C$11:$C$13),0) -> 0 | G18: =IFERROR(VLOOKUP(B18,'Факт продаж'!J:K,2,0),"нет продаж") -> 18 | H18: =IFERROR(VLOOKUP(B18,'Факт продаж'!J:L,3,0),"нет продаж") -> 37980 | I18: =IFERROR(VLOOKUP(B18,'Факт продаж'!J:N,5,0),"нет продаж") -> 14200.867 | J18: =IFERROR(VLOOKUP(B18,'Факт продаж'!J:L,3,0)/SUM('План Антонова'!$C$14:$C$16),0) -> 0.00026224659 | K18: =IFERROR(VLOOKUP(B18,'Факт продаж'!J:O,6,0),"-") -> 1 | L18: =IF(AND(F18=0,J18>0),5,IF(J18/F18>5,5,IF(J18/F18=0,0.0000001,J18/F18))) -> 5 | M18: =IFERROR(VLOOKUP(B18,'Факт продаж'!S:T,2,0),"нет продаж") -> нет продаж | N18: =IFERROR(VLOOKUP(B18,'Факт продаж'!S:U,3,0),"нет продаж") -> нет продаж | O18: =IFERROR(VLOOKUP(B18,'Факт продаж'!S:W,5,0),"нет продаж") -> нет продаж | P18: =IFERROR(VLOOKUP(B18,'Факт продаж'!S:U,3,0)/SUM('План Антонова'!$C$17:$C$19),0) -> 0 | Q18: =IFERROR(VLOOKUP(B18,'Факт продаж'!S:X,6,0),"-") -> - | R18: =IF(AND(J18=0,P18>0),5,IF(P18/J18>5,5,IF(P18/J18=0,0.0000001,P18/J18))) -> 1e-07 | S18: =IFERROR(VLOOKUP(B18,'Факт продаж'!AB:AD,2,0),"нет продаж") -> нет продаж | T18: =IFERROR(VLOOKUP(B18,'Факт продаж'!AB:AD,3,0),"нет продаж") -> нет продаж | U18: =IFERROR(VLOOKUP(B18,'Факт продаж'!AB:AF,5,0),"нет продаж") -> нет продаж | V18: =IFERROR(VLOOKUP(B18,'Факт продаж'!AB:AD,3,0)/SUM('План Антонова'!$C$20:$C$22),0) -> 0 | W18: =IFERROR(VLOOKUP(B18,'Факт продаж'!AB:AG,6,0),"-") -> - | X18: =IF(AND(P18=0,V18>0),5,IF(V18/P18>5,5,IF(V18/P18=0,0.0000001,V18/P18))) -> #DIV/0! | Y18: =IFERROR(VLOOKUP(B18,'Факт продаж'!AB:AH,7,0),"-") -> - | Z18: =IF(AND(F18=0,V18>0),5,IF(V18/F18>5,5,IF(V18/F18=0,0.0000001,V18/F18))) -> #DIV/0! | AB18: =IFERROR(VLOOKUP(VALUE(IF(L18<1,1,0)&IF(J18<'Факт продаж'!$M$24,0,1)),$AB$1:$AC$4,2,FALSE),"НЕТ ПРОДАЖ") -> Темная лошадка | AC18: =IFERROR(VLOOKUP(VALUE(IF(R18<1,1,0)&IF(P18<'Факт продаж'!$V$24,0,1)),$AB$1:$AC$4,2,FALSE),"НЕТ ПРОДАЖ") -> Собака | AD18: =IFERROR(VLOOKUP(VALUE(IF(X18<1,1,0)&IF(V18<'Факт продаж'!$AE$24,0,1)),$AB$1:$AC$4,2,FALSE),"НЕТ ПРОДАЖ") -> НЕТ ПРОДАЖ | AE18: =IFERROR(VLOOKUP(VALUE(IF(Z18<1,1,0)&IF(V18<'Факт продаж'!$AE$24,0,1)),$AB$1:$AC$4,2,FALSE),"НЕТ ПРОДАЖ") -> НЕТ ПРОДАЖ | AF18: =VLOOKUP(B18,'ABC расчет'!B:G,6,0) -> C | AG18: =VLOOKUP(B18,'ABC расчет'!K:P,6,0) -> B | AH18: =VLOOKUP(B18,'ABC расчет'!T:Y,6,0) -> C | AI18: =VLOOKUP(B18,'ABC расчет'!AC:AH,6,0) -> C
A19: ПАРТЫ УЧЕНИЧЕСКИЕ | B19: СТОЛ УЧЕН. E-163 | C19: =IFERROR(VLOOKUP(B19,'Факт продаж'!A:B,2,0),"нет продаж") -> нет продаж | D19: =IFERROR(VLOOKUP(B19,'Факт продаж'!A:C,3,0),"нет продаж") -> нет продаж | E19: =IFERROR(VLOOKUP(B19,'Факт продаж'!A:E,5,0),"нет продаж") -> нет продаж | F19: =IFERROR(VLOOKUP(B19,'Факт продаж'!A:C,3,0)/SUM('План Антонова'!$C$11:$C$13),0) -> 0 | G19: =IFERROR(VLOOKUP(B19,'Факт продаж'!J:K,2,0),"нет продаж") -> нет продаж | H19: =IFERROR(VLOOKUP(B19,'Факт продаж'!J:L,3,0),"нет продаж") -> нет продаж | I19: =IFERROR(VLOOKUP(B19,'Факт продаж'!J:N,5,0),"нет продаж") -> нет продаж | J19: =IFERROR(VLOOKUP(B19,'Факт продаж'!J:L,3,0)/SUM('План Антонова'!$C$14:$C$16),0) -> 0 | K19: =IFERROR(VLOOKUP(B19,'Факт продаж'!J:O,6,0),"-") -> - | L19: =IF(AND(F19=0,J19>0),5,IF(J19/F19>5,5,IF(J19/F19=0,0.0000001,J19/F19))) -> #DIV/0! | M19: =IFERROR(VLOOKUP(B19,'Факт продаж'!S:T,2,0),"нет продаж") -> 20 | N19: =IFERROR(VLOOKUP(B19,'Факт продаж'!S:U,3,0),"нет продаж") -> 29516 | O19: =IFERROR(VLOOKUP(B19,'Факт продаж'!S:W,5,0),"нет продаж") -> 12249.326 | P19: =IFERROR(VLOOKUP(B19,'Факт продаж'!S:U,3,0)/SUM('План Антонова'!$C$17:$C$19),0) -> 0.00017978344 | Q19: =IFERROR(VLOOKUP(B19,'Факт продаж'!S:X,6,0),"-") -> 1 | R19: =IF(AND(J19=0,P19>0),5,IF(P19/J19>5,5,IF(P19/J19=0,0.0000001,P19/J19))) -> 5 | S19: =IFERROR(VLOOKUP(B19,'Факт продаж'!AB:AD,2,0),"нет продаж") -> нет продаж | T19: =IFERROR(VLOOKUP(B19,'Факт продаж'!AB:AD,3,0),"нет продаж") -> нет продаж | U19: =IFERROR(VLOOKUP(B19,'Факт продаж'!AB:AF,5,0),"нет продаж") -> нет продаж | V19: =IFERROR(VLOOKUP(B19,'Факт продаж'!AB:AD,3,0)/SUM('План Антонова'!$C$20:$C$22),0) -> 0 | W19: =IFERROR(VLOOKUP(B19,'Факт продаж'!AB:AG,6,0),"-") -> - | X19: =IF(AND(P19=0,V19>0),5,IF(V19/P19>5,5,IF(V19/P19=0,0.0000001,V19/P19))) -> 1e-07 | Y19: =IFERROR(VLOOKUP(B19,'Факт продаж'!AB:AH,7,0),"-") -> - | Z19: =IF(AND(F19=0,V19>0),5,IF(V19/F19>5,5,IF(V19/F19=0,0.0000001,V19/F19))) -> #DIV/0! | AB19: =IFERROR(VLOOKUP(VALUE(IF(L19<1,1,0)&IF(J19<'Факт продаж'!$M$24,0,1)),$AB$1:$AC$4,2,FALSE),"НЕТ ПРОДАЖ") -> НЕТ ПРОДАЖ | AC19: =IFERROR(VLOOKUP(VALUE(IF(R19<1,1,0)&IF(P19<'Факт продаж'!$V$24,0,1)),$AB$1:$AC$4,2,FALSE),"НЕТ ПРОДАЖ") -> Темная лошадка | AD19: =IFERROR(VLOOKUP(VALUE(IF(X19<1,1,0)&IF(V19<'Факт продаж'!$AE$24,0,1)),$AB$1:$AC$4,2,FALSE),"НЕТ ПРОДАЖ") -> Собака | AE19: =IFERROR(VLOOKUP(VALUE(IF(Z19<1,1,0)&IF(V19<'Факт продаж'!$AE$24,0,1)),$AB$1:$AC$4,2,FALSE),"НЕТ ПРОДАЖ") -> НЕТ ПРОДАЖ | AF19: =VLOOKUP(B19,'ABC расчет'!B:G,6,0) -> C | AG19: =VLOOKUP(B19,'ABC расчет'!K:P,6,0) -> C | AH19: =VLOOKUP(B19,'ABC расчет'!T:Y,6,0) -> C | AI19: =VLOOKUP(B19,'ABC расчет'!AC:AH,6,0) -> C
A20: ПАРТЫ УЧЕНИЧЕСКИЕ | B20: СТОЛ УЧЕН. E-172 | C20: =IFERROR(VLOOKUP(B20,'Факт продаж'!A:B,2,0),"нет продаж") -> 92 | D20: =IFERROR(VLOOKUP(B20,'Факт продаж'!A:C,3,0),"нет продаж") -> 140746.16 | E20: =IFERROR(VLOOKUP(B20,'Факт продаж'!A:E,5,0),"нет продаж") -> 47721.353 | F20: =IFERROR(VLOOKUP(B20,'Факт продаж'!A:C,3,0)/SUM('План Антонова'!$C$11:$C$13),0) -> 0.0010687005 | G20: =IFERROR(VLOOKUP(B20,'Факт продаж'!J:K,2,0),"нет продаж") -> 10 | H20: =IFERROR(VLOOKUP(B20,'Факт продаж'!J:L,3,0),"нет продаж") -> 21936 | I20: =IFERROR(VLOOKUP(B20,'Факт продаж'!J:N,5,0),"нет продаж") -> 10788.577 | J20: =IFERROR(VLOOKUP(B20,'Факт продаж'!J:L,3,0)/SUM('План Антонова'!$C$14:$C$16),0) -> 0.00015146501 | K20: =IFERROR(VLOOKUP(B20,'Факт продаж'!J:O,6,0),"-") -> -0.77392557 | L20: =IF(AND(F20=0,J20>0),5,IF(J20/F20>5,5,IF(J20/F20=0,0.0000001,J20/F20))) -> 0.14172822 | M20: =IFERROR(VLOOKUP(B20,'Факт продаж'!S:T,2,0),"нет продаж") -> 334 | N20: =IFERROR(VLOOKUP(B20,'Факт продаж'!S:U,3,0),"нет продаж") -> 778664.4 | O20: =IFERROR(VLOOKUP(B20,'Факт продаж'!S:W,5,0),"нет продаж") -> 363391.75 | P20: =IFERROR(VLOOKUP(B20,'Факт продаж'!S:U,3,0)/SUM('План Антонова'!$C$17:$C$19),0) -> 0.0047428841 | Q20: =IFERROR(VLOOKUP(B20,'Факт продаж'!S:X,6,0),"-") -> 32.683009 | R20: =IF(AND(J20=0,P20>0),5,IF(P20/J20>5,5,IF(P20/J20=0,0.0000001,P20/J20))) -> 5 | S20: =IFERROR(VLOOKUP(B20,'Факт продаж'!AB:AD,2,0),"нет продаж") -> нет продаж | T20: =IFERROR(VLOOKUP(B20,'Факт продаж'!AB:AD,3,0),"нет продаж") -> нет продаж | U20: =IFERROR(VLOOKUP(B20,'Факт продаж'!AB:AF,5,0),"нет продаж") -> нет продаж | V20: =IFERROR(VLOOKUP(B20,'Факт продаж'!AB:AD,3,0)/SUM('План Антонова'!$C$20:$C$22),0) -> 0 | W20: =IFERROR(VLOOKUP(B20,'Факт продаж'!AB:AG,6,0),"-") -> - | X20: =IF(AND(P20=0,V20>0),5,IF(V20/P20>5,5,IF(V20/P20=0,0.0000001,V20/P20))) -> 1e-07 | Y20: =IFERROR(VLOOKUP(B20,'Факт продаж'!AB:AH,7,0),"-") -> - | Z20: =IF(AND(F20=0,V20>0),5,IF(V20/F20>5,5,IF(V20/F20=0,0.0000001,V20/F20))) -> 1e-07 | AB20: =IFERROR(VLOOKUP(VALUE(IF(L20<1,1,0)&IF(J20<'Факт продаж'!$M$24,0,1)),$AB$1:$AC$4,2,FALSE),"НЕТ ПРОДАЖ") -> Собака | AC20: =IFERROR(VLOOKUP(VALUE(IF(R20<1,1,0)&IF(P20<'Факт продаж'!$V$24,0,1)),$AB$1:$AC$4,2,FALSE),"НЕТ ПРОДАЖ") -> Звезда | AD20: =IFERROR(VLOOKUP(VALUE(IF(X20<1,1,0)&IF(V20<'Факт продаж'!$AE$24,0,1)),$AB$1:$AC$4,2,FALSE),"НЕТ ПРОДАЖ") -> Собака | AE20: =IFERROR(VLOOKUP(VALUE(IF(Z20<1,1,0)&IF(V20<'Факт продаж'!$AE$24,0,1)),$AB$1:$AC$4,2,FALSE),"НЕТ ПРОДАЖ") -> Собака | AF20: =VLOOKUP(B20,'ABC расчет'!B:G,6,0) -> A | AG20: =VLOOKUP(B20,'ABC расчет'!K:P,6,0) -> C | AH20: =VLOOKUP(B20,'ABC расчет'!T:Y,6,0) -> A | AI20: =VLOOKUP(B20,'ABC расчет'!AC:AH,6,0) -> C
A21: ПАРТЫ УЧЕНИЧЕСКИЕ | B21: СТОЛ УЧЕН. E-177 | C21: =IFERROR(VLOOKUP(B21,'Факт продаж'!A:B,2,0),"нет продаж") -> нет продаж | D21: =IFERROR(VLOOKUP(B21,'Факт продаж'!A:C,3,0),"нет продаж") -> нет продаж | E21: =IFERROR(VLOOKUP(B21,'Факт продаж'!A:E,5,0),"нет продаж") -> нет продаж | F21: =IFERROR(VLOOKUP(B21,'Факт продаж'!A:C,3,0)/SUM('План Антонова'!$C$11:$C$13),0) -> 0 | G21: =IFERROR(VLOOKUP(B21,'Факт продаж'!J:K,2,0),"нет продаж") -> нет продаж | H21: =IFERROR(VLOOKUP(B21,'Факт продаж'!J:L,3,0),"нет продаж") -> нет продаж | I21: =IFERROR(VLOOKUP(B21,'Факт продаж'!J:N,5,0),"нет продаж") -> нет продаж | J21: =IFERROR(VLOOKUP(B21,'Факт продаж'!J:L,3,0)/SUM('План Антонова'!$C$14:$C$16),0) -> 0 | K21: =IFERROR(VLOOKUP(B21,'Факт продаж'!J:O,6,0),"-") -> - | L21: =IF(AND(F21=0,J21>0),5,IF(J21/F21>5,5,IF(J21/F21=0,0.0000001,J21/F21))) -> #DIV/0! | M21: =IFERROR(VLOOKUP(B21,'Факт продаж'!S:T,2,0),"нет продаж") -> нет продаж | N21: =IFERROR(VLOOKUP(B21,'Факт продаж'!S:U,3,0),"нет продаж") -> нет продаж | O21: =IFERROR(VLOOKUP(B21,'Факт продаж'!S:W,5,0),"нет продаж") -> нет продаж | P21: =IFERROR(VLOOKUP(B21,'Факт продаж'!S:U,3,0)/SUM('План Антонова'!$C$17:$C$19),0) -> 0 | Q21: =IFERROR(VLOOKUP(B21,'Факт продаж'!S:X,6,0),"-") -> - | R21: =IF(AND(J21=0,P21>0),5,IF(P21/J21>5,5,IF(P21/J21=0,0.0000001,P21/J21))) -> #DIV/0! | S21: =IFERROR(VLOOKUP(B21,'Факт продаж'!AB:AD,2,0),"нет продаж") -> нет продаж | T21: =IFERROR(VLOOKUP(B21,'Факт продаж'!AB:AD,3,0),"нет продаж") -> нет продаж | U21: =IFERROR(VLOOKUP(B21,'Факт продаж'!AB:AF,5,0),"нет продаж") -> нет продаж | V21: =IFERROR(VLOOKUP(B21,'Факт продаж'!AB:AD,3,0)/SUM('План Антонова'!$C$20:$C$22),0) -> 0 | W21: =IFERROR(VLOOKUP(B21,'Факт продаж'!AB:AG,6,0),"-") -> - | X21: =IF(AND(P21=0,V21>0),5,IF(V21/P21>5,5,IF(V21/P21=0,0.0000001,V21/P21))) -> #DIV/0! | Y21: =IFERROR(VLOOKUP(B21,'Факт продаж'!AB:AH,7,0),"-") -> - | Z21: =IF(AND(F21=0,V21>0),5,IF(V21/F21>5,5,IF(V21/F21=0,0.0000001,V21/F21))) -> #DIV/0! | AB21: =IFERROR(VLOOKUP(VALUE(IF(L21<1,1,0)&IF(J21<'Факт продаж'!$M$24,0,1)),$AB$1:$AC$4,2,FALSE),"НЕТ ПРОДАЖ") -> НЕТ ПРОДАЖ | AC21: =IFERROR(VLOOKUP(VALUE(IF(R21<1,1,0)&IF(P21<'Факт продаж'!$V$24,0,1)),$AB$1:$AC$4,2,FALSE),"НЕТ ПРОДАЖ") -> НЕТ ПРОДАЖ | AD21: =IFERROR(VLOOKUP(VALUE(IF(X21<1,1,0)&IF(V21<'Факт продаж'!$AE$24,0,1)),$AB$1:$AC$4,2,FALSE),"НЕТ ПРОДАЖ") -> НЕТ ПРОДАЖ | AE21: =IFERROR(VLOOKUP(VALUE(IF(Z21<1,1,0)&IF(V21<'Факт продаж'!$AE$24,0,1)),$AB$1:$AC$4,2,FALSE),"НЕТ ПРОДАЖ") -> НЕТ ПРОДАЖ | AF21: =VLOOKUP(B21,'ABC расчет'!B:G,6,0) -> C | AG21: =VLOOKUP(B21,'ABC расчет'!K:P,6,0) -> C | AH21: =VLOOKUP(B21,'ABC расчет'!T:Y,6,0) -> C | AI21: =VLOOKUP(B21,'ABC расчет'!AC:AH,6,0) -> C
A22: ПАРТЫ УЧЕНИЧЕСКИЕ | B22: СТОЛ УЧЕН. E-178 | C22: =IFERROR(VLOOKUP(B22,'Факт продаж'!A:B,2,0),"нет продаж") -> нет продаж | D22: =IFERROR(VLOOKUP(B22,'Факт продаж'!A:C,3,0),"нет продаж") -> нет продаж | E22: =IFERROR(VLOOKUP(B22,'Факт продаж'!A:E,5,0),"нет продаж") -> нет продаж | F22: =IFERROR(VLOOKUP(B22,'Факт продаж'!A:C,3,0)/SUM('План Антонова'!$C$11:$C$13),0) -> 0 | G22: =IFERROR(VLOOKUP(B22,'Факт продаж'!J:K,2,0),"нет продаж") -> нет продаж | H22: =IFERROR(VLOOKUP(B22,'Факт продаж'!J:L,3,0),"нет продаж") -> нет продаж | I22: =IFERROR(VLOOKUP(B22,'Факт продаж'!J:N,5,0),"нет продаж") -> нет продаж | J22: =IFERROR(VLOOKUP(B22,'Факт продаж'!J:L,3,0)/SUM('План Антонова'!$C$14:$C$16),0) -> 0 | K22: =IFERROR(VLOOKUP(B22,'Факт продаж'!J:O,6,0),"-") -> - | L22: =IF(AND(F22=0,J22>0),5,IF(J22/F22>5,5,IF(J22/F22=0,0.0000001,J22/F22))) -> #DIV/0! | M22: =IFERROR(VLOOKUP(B22,'Факт продаж'!S:T,2,0),"нет продаж") -> 145 | N22: =IFERROR(VLOOKUP(B22,'Факт продаж'!S:U,3,0),"нет продаж") -> 200391.25 | O22: =IFERROR(VLOOKUP(B22,'Факт продаж'!S:W,5,0),"нет продаж") -> 49569.549 | P22: =IFERROR(VLOOKUP(B22,'Факт продаж'!S:U,3,0)/SUM('План Антонова'!$C$17:$C$19),0) -> 0.0012205932 | Q22: =IFERROR(VLOOKUP(B22,'Факт продаж'!S:X,6,0),"-") -> 1 | R22: =IF(AND(J22=0,P22>0),5,IF(P22/J22>5,5,IF(P22/J22=0,0.0000001,P22/J22))) -> 5 | S22: =IFERROR(VLOOKUP(B22,'Факт продаж'!AB:AD,2,0),"нет продаж") -> нет продаж | T22: =IFERROR(VLOOKUP(B22,'Факт продаж'!AB:AD,3,0),"нет продаж") -> нет продаж | U22: =IFERROR(VLOOKUP(B22,'Факт продаж'!AB:AF,5,0),"нет продаж") -> нет продаж | V22: =IFERROR(VLOOKUP(B22,'Факт продаж'!AB:AD,3,0)/SUM('План Антонова'!$C$20:$C$22),0) -> 0 | W22: =IFERROR(VLOOKUP(B22,'Факт продаж'!AB:AG,6,0),"-") -> - | X22: =IF(AND(P22=0,V22>0),5,IF(V22/P22>5,5,IF(V22/P22=0,0.0000001,V22/P22))) -> 1e-07 | Y22: =IFERROR(VLOOKUP(B22,'Факт продаж'!AB:AH,7,0),"-") -> - | Z22: =IF(AND(F22=0,V22>0),5,IF(V22/F22>5,5,IF(V22/F22=0,0.0000001,V22/F22))) -> #DIV/0! | AB22: =IFERROR(VLOOKUP(VALUE(IF(L22<1,1,0)&IF(J22<'Факт продаж'!$M$24,0,1)),$AB$1:$AC$4,2,FALSE),"НЕТ ПРОДАЖ") -> НЕТ ПРОДАЖ | AC22: =IFERROR(VLOOKUP(VALUE(IF(R22<1,1,0)&IF(P22<'Факт продаж'!$V$24,0,1)),$AB$1:$AC$4,2,FALSE),"НЕТ ПРОДАЖ") -> Звезда | AD22: =IFERROR(VLOOKUP(VALUE(IF(X22<1,1,0)&IF(V22<'Факт продаж'!$AE$24,0,1)),$AB$1:$AC$4,2,FALSE),"НЕТ ПРОДАЖ") -> Собака | AE22: =IFERROR(VLOOKUP(VALUE(IF(Z22<1,1,0)&IF(V22<'Факт продаж'!$AE$24,0,1)),$AB$1:$AC$4,2,FALSE),"НЕТ ПРОДАЖ") -> НЕТ ПРОДАЖ | AF22: =VLOOKUP(B22,'ABC расчет'!B:G,6,0) -> C | AG22: =VLOOKUP(B22,'ABC расчет'!K:P,6,0) -> C | AH22: =VLOOKUP(B22,'ABC расчет'!T:Y,6,0) -> B | AI22: =VLOOKUP(B22,'ABC расчет'!AC:AH,6,0) -> C
A23: ПАРТЫ УЧЕНИЧЕСКИЕ | B23: СТОЛ УЧЕН. E-179 | C23: =IFERROR(VLOOKUP(B23,'Факт продаж'!A:B,2,0),"нет продаж") -> 31 | D23: =IFERROR(VLOOKUP(B23,'Факт продаж'!A:C,3,0),"нет продаж") -> 41384.414 | E23: =IFERROR(VLOOKUP(B23,'Факт продаж'!A:E,5,0),"нет продаж") -> 20005.833 | F23: =IFERROR(VLOOKUP(B23,'Факт продаж'!A:C,3,0)/SUM('План Антонова'!$C$11:$C$13),0) -> 0.00031423624 | G23: =IFERROR(VLOOKUP(B23,'Факт продаж'!J:K,2,0),"нет продаж") -> нет продаж | H23: =IFERROR(VLOOKUP(B23,'Факт продаж'!J:L,3,0),"нет продаж") -> нет продаж | I23: =IFERROR(VLOOKUP(B23,'Факт продаж'!J:N,5,0),"нет продаж") -> нет продаж | J23: =IFERROR(VLOOKUP(B23,'Факт продаж'!J:L,3,0)/SUM('План Антонова'!$C$14:$C$16),0) -> 0 | K23: =IFERROR(VLOOKUP(B23,'Факт продаж'!J:O,6,0),"-") -> - | L23: =IF(AND(F23=0,J23>0),5,IF(J23/F23>5,5,IF(J23/F23=0,0.0000001,J23/F23))) -> 1e-07 | M23: =IFERROR(VLOOKUP(B23,'Факт продаж'!S:T,2,0),"нет продаж") -> 7 | N23: =IFERROR(VLOOKUP(B23,'Факт продаж'!S:U,3,0),"нет продаж") -> 11445 | O23: =IFERROR(VLOOKUP(B23,'Факт продаж'!S:W,5,0),"нет продаж") -> 4391.2415 | P23: =IFERROR(VLOOKUP(B23,'Факт продаж'!S:U,3,0)/SUM('План Антонова'!$C$17:$C$19),0) -> 6.9712071e-05 | Q23: =IFERROR(VLOOKUP(B23,'Факт продаж'!S:X,6,0),"-") -> 1 | R23: =IF(AND(J23=0,P23>0),5,IF(P23/J23>5,5,IF(P23/J23=0,0.0000001,P23/J23))) -> 5 | S23: =IFERROR(VLOOKUP(B23,'Факт продаж'!AB:AD,2,0),"нет продаж") -> нет продаж | T23: =IFERROR(VLOOKUP(B23,'Факт продаж'!AB:AD,3,0),"нет продаж") -> нет продаж | U23: =IFERROR(VLOOKUP(B23,'Факт продаж'!AB:AF,5,0),"нет продаж") -> нет продаж | V23: =IFERROR(VLOOKUP(B23,'Факт продаж'!AB:AD,3,0)/SUM('План Антонова'!$C$20:$C$22),0) -> 0 | W23: =IFERROR(VLOOKUP(B23,'Факт продаж'!AB:AG,6,0),"-") -> - | X23: =IF(AND(P23=0,V23>0),5,IF(V23/P23>5,5,IF(V23/P23=0,0.0000001,V23/P23))) -> 1e-07 | Y23: =IFERROR(VLOOKUP(B23,'Факт продаж'!AB:AH,7,0),"-") -> - | Z23: =IF(AND(F23=0,V23>0),5,IF(V23/F23>5,5,IF(V23/F23=0,0.0000001,V23/F23))) -> 1e-07 | AB23: =IFERROR(VLOOKUP(VALUE(IF(L23<1,1,0)&IF(J23<'Факт продаж'!$M$24,0,1)),$AB$1:$AC$4,2,FALSE),"НЕТ ПРОДАЖ") -> Собака | AC23: =IFERROR(VLOOKUP(VALUE(IF(R23<1,1,0)&IF(P23<'Факт продаж'!$V$24,0,1)),$AB$1:$AC$4,2,FALSE),"НЕТ ПРОДАЖ") -> Темная лошадка | AD23: =IFERROR(VLOOKUP(VALUE(IF(X23<1,1,0)&IF(V23<'Факт продаж'!$AE$24,0,1)),$AB$1:$AC$4,2,FALSE),"НЕТ ПРОДАЖ") -> Собака | AE23: =IFERROR(VLOOKUP(VALUE(IF(Z23<1,1,0)&IF(V23<'Факт продаж'!$AE$24,0,1)),$AB$1:$AC$4,2,FALSE),"НЕТ ПРОДАЖ") -> Собака | AF23: =VLOOKUP(B23,'ABC расчет'!B:G,6,0) -> C | AG23: =VLOOKUP(B23,'ABC расчет'!K:P,6,0) -> C | AH23: =VLOOKUP(B23,'ABC расчет'!T:Y,6,0) -> C | AI23: =VLOOKUP(B23,'ABC расчет'!AC:AH,6,0) -> C
... A32: СТУЛЬЯ ПОСЕТИТЕЛЬСКИЕ | B32: SAMBA | C32: =IFERROR(VLOOKUP(B32,'Факт продаж'!A:B,2,0),"нет продаж") -> 785 | D32: =IFERROR(VLOOKUP(B32,'Факт продаж'!A:C,3,0),"нет продаж") -> 1160120.9 | E32: =IFERROR(VLOOKUP(B32,'Факт продаж'!A:E,5,0),"нет продаж") -> 562386.04 | F32: =IFERROR(VLOOKUP(B32,'Факт продаж'!A:C,3,0)/SUM('План Антонова'!$C$11:$C$13),0) -> 0.0088089208 | G32: =IFERROR(VLOOKUP(B32,'Факт продаж'!J:K,2,0),"нет продаж") -> 2213 | H32: =IFERROR(VLOOKUP(B32,'Факт продаж'!J:L,3,0),"нет продаж") -> 4340297.2 | I32: =IFERROR(VLOOKUP(B32,'Факт продаж'!J:N,5,0),"нет продаж") -> 2065394.2 | J32: =IFERROR(VLOOKUP(B32,'Факт продаж'!J:L,3,0)/SUM('План Антонова'!$C$14:$C$16),0) -> 0.029969146 | K32: =IFERROR(VLOOKUP(B32,'Факт продаж'!J:O,6,0),"-") -> 2.6725559 | L32: =IF(AND(F32=0,J32>0),5,IF(J32/F32>5,5,IF(J32/F32=0,0.0000001,J32/F32))) -> 3.4021359 | M32: =IFERROR(VLOOKUP(B32,'Факт продаж'!S:T,2,0),"нет продаж") -> 1850 | N32: =IFERROR(VLOOKUP(B32,'Факт продаж'!S:U,3,0),"нет продаж") -> 3479076.1 | O32: =IFERROR(VLOOKUP(B32,'Факт продаж'!S:W,5,0),"нет продаж") -> 1520770 | P32: =IFERROR(VLOOKUP(B32,'Факт продаж'!S:U,3,0)/SUM('План Антонова'!$C$17:$C$19),0) -> 0.021191228 | Q32: =IFERROR(VLOOKUP(B32,'Факт продаж'!S:X,6,0),"-") -> -0.26369017 | R32: =IF(AND(J32=0,P32>0),5,IF(P32/J32>5,5,IF(P32/J32=0,0.0000001,P32/J32))) -> 0.70710151 | S32: =IFERROR(VLOOKUP(B32,'Факт продаж'!AB:AD,2,0),"нет продаж") -> 2800 | T32: =IFERROR(VLOOKUP(B32,'Факт продаж'!AB:AD,3,0),"нет продаж") -> 5565556.8 | U32: =IFERROR(VLOOKUP(B32,'Факт продаж'!AB:AF,5,0),"нет продаж") -> 2595520.3 | V32: =IFERROR(VLOOKUP(B32,'Факт продаж'!AB:AD,3,0)/SUM('План Антонова'!$C$20:$C$22),0) -> 0.036168869 | W32: =IFERROR(VLOOKUP(B32,'Факт продаж'!AB:AG,6,0),"-") -> 0.70671452 | X32: =IF(AND(P32=0,V32>0),5,IF(V32/P32>5,5,IF(V32/P32=0,0.0000001,V32/P32))) -> 1.7067849 | Y32: =IFERROR(VLOOKUP(B32,'Факт продаж'!AB:AH,7,0),"-") -> 3.6151934 | Z32: =IF(AND(F32=0,V32>0),5,IF(V32/F32>5,5,IF(V32/F32=0,0.0000001,V32/F32))) -> 4.1059364 | AB32: =IFERROR(VLOOKUP(VALUE(IF(L32<1,1,0)&IF(J32<'Факт продаж'!$M$24,0,1)),$AB$1:$AC$4,2,FALSE),"НЕТ ПРОДАЖ") -> Звезда | AC32: =IFERROR(VLOOKUP(VALUE(IF(R32<1,1,0)&IF(P32<'Факт продаж'!$V$24,0,1)),$AB$1:$AC$4,2,FALSE),"НЕТ ПРОДАЖ") -> Корова | AD32: =IFERROR(VLOOKUP(VALUE(IF(X32<1,1,0)&IF(V32<'Факт продаж'!$AE$24,0,1)),$AB$1:$AC$4,2,FALSE),"НЕТ ПРОДАЖ") -> Звезда | AE32: =IFERROR(VLOOKUP(VALUE(IF(Z32<1,1,0)&IF(V32<'Факт продаж'!$AE$24,0,1)),$AB$1:$AC$4,2,FALSE),"НЕТ ПРОДАЖ") -> Звезда | AF32: =VLOOKUP(B32,'ABC расчет'!B:G,6,0) -> B | AG32: =VLOOKUP(B32,'ABC расчет'!K:P,6,0) -> A | AH32: =VLOOKUP(B32,'ABC расчет'!T:Y,6,0) -> A | AI32: =VLOOKUP(B32,'ABC расчет'!AC:AH,6,0) -> A
A33: КРЕСЛА РУКОВОДИТЕЛЯ | B33: YAPPI | C33: =IFERROR(VLOOKUP(B33,'Факт продаж'!A:B,2,0),"нет продаж") -> 8 | D33: =IFERROR(VLOOKUP(B33,'Факт продаж'!A:C,3,0),"нет продаж") -> 32340.921 | E33: =IFERROR(VLOOKUP(B33,'Факт продаж'!A:E,5,0),"нет продаж") -> 15388.983 | F33: =IFERROR(VLOOKUP(B33,'Факт продаж'!A:C,3,0)/SUM('План Антонова'!$C$11:$C$13),0) -> 0.00024556804 | G33: =IFERROR(VLOOKUP(B33,'Факт продаж'!J:K,2,0),"нет продаж") -> 2423 | H33: =IFERROR(VLOOKUP(B33,'Факт продаж'!J:L,3,0),"нет продаж") -> 12103476 | I33: =IFERROR(VLOOKUP(B33,'Факт продаж'!J:N,5,0),"нет продаж") -> 5599944 | J33: =IFERROR(VLOOKUP(B33,'Факт продаж'!J:L,3,0)/SUM('План Антонова'!$C$14:$C$16),0) -> 0.083572807 | K33: =IFERROR(VLOOKUP(B33,'Факт продаж'!J:O,6,0),"-") -> 362.89306 | L33: =IF(AND(F33=0,J33>0),5,IF(J33/F33>5,5,IF(J33/F33=0,0.0000001,J33/F33))) -> 5 | M33: =IFERROR(VLOOKUP(B33,'Факт продаж'!S:T,2,0),"нет продаж") -> 2329 | N33: =IFERROR(VLOOKUP(B33,'Факт продаж'!S:U,3,0),"нет продаж") -> 12088900 | O33: =IFERROR(VLOOKUP(B33,'Факт продаж'!S:W,5,0),"нет продаж") -> 4709634.7 | P33: =IFERROR(VLOOKUP(B33,'Факт продаж'!S:U,3,0)/SUM('План Антонова'!$C$17:$C$19),0) -> 0.073634101 | Q33: =IFERROR(VLOOKUP(B33,'Факт продаж'!S:X,6,0),"-") -> -0.15898539 | R33: =IF(AND(J33=0,P33>0),5,IF(P33/J33>5,5,IF(P33/J33=0,0.0000001,P33/J33))) -> 0.88107728 | S33: =IFERROR(VLOOKUP(B33,'Факт продаж'!AB:AD,2,0),"нет продаж") -> 1074 | T33: =IFERROR(VLOOKUP(B33,'Факт продаж'!AB:AD,3,0),"нет продаж") -> 5744080.2 | U33: =IFERROR(VLOOKUP(B33,'Факт продаж'!AB:AF,5,0),"нет продаж") -> 2375375.5 | V33: =IFERROR(VLOOKUP(B33,'Факт продаж'!AB:AD,3,0)/SUM('План Антонова'!$C$20:$C$22),0) -> 0.037329038 | W33: =IFERROR(VLOOKUP(B33,'Факт продаж'!AB:AG,6,0),"-") -> -0.49563487 | X33: =IF(AND(P33=0,V33>0),5,IF(V33/P33>5,5,IF(V33/P33=0,0.0000001,V33/P33))) -> 0.50695313 | Y33: =IFERROR(VLOOKUP(B33,'Факт продаж'!AB:AH,7,0),"-") -> 153.35559 | Z33: =IF(AND(F33=0,V33>0),5,IF(V33/F33>5,5,IF(V33/F33=0,0.0000001,V33/F33))) -> 5 | AB33: =IFERROR(VLOOKUP(VALUE(IF(L33<1,1,0)&IF(J33<'Факт продаж'!$M$24,0,1)),$AB$1:$AC$4,2,FALSE),"НЕТ ПРОДАЖ") -> Звезда | AC33: =IFERROR(VLOOKUP(VALUE(IF(R33<1,1,0)&IF(P33<'Факт продаж'!$V$24,0,1)),$AB$1:$AC$4,2,FALSE),"НЕТ ПРОДАЖ") -> Корова | AD33: =IFERROR(VLOOKUP(VALUE(IF(X33<1,1,0)&IF(V33<'Факт продаж'!$AE$24,0,1)),$AB$1:$AC$4,2,FALSE),"НЕТ ПРОДАЖ") -> Корова | AE33: =IFERROR(VLOOKUP(VALUE(IF(Z33<1,1,0)&IF(V33<'Факт продаж'!$AE$24,0,1)),$AB$1:$AC$4,2,FALSE),"НЕТ ПРОДАЖ") -> Звезда | AF33: =VLOOKUP(B33,'ABC расчет'!B:G,6,0) -> C | AG33: =VLOOKUP(B33,'ABC расчет'!K:P,6,0) -> A | AH33: =VLOOKUP(B33,'ABC расчет'!T:Y,6,0) -> A | AI33: =VLOOKUP(B33,'ABC расчет'!AC:AH,6,0) -> A | AJ33: PROMO
A34: КРЕСЛА РУКОВОДИТЕЛЯ | B34: MORFEO | C34: =IFERROR(VLOOKUP(B34,'Факт продаж'!A:B,2,0),"нет продаж") -> 61 | D34: =IFERROR(VLOOKUP(B34,'Факт продаж'!A:C,3,0),"нет продаж") -> 250167.28 | E34: =IFERROR(VLOOKUP(B34,'Факт продаж'!A:E,5,0),"нет продаж") -> 112450.42 | F34: =IFERROR(VLOOKUP(B34,'Факт продаж'!A:C,3,0)/SUM('План Антонова'!$C$11:$C$13),0) -> 0.0018995466 | G34: =IFERROR(VLOOKUP(B34,'Факт продаж'!J:K,2,0),"нет продаж") -> 954 | H34: =IFERROR(VLOOKUP(B34,'Факт продаж'!J:L,3,0),"нет продаж") -> 4916371.2 | I34: =IFERROR(VLOOKUP(B34,'Факт продаж'!J:N,5,0),"нет продаж") -> 2330055.1 | J34: =IFERROR(VLOOKUP(B34,'Факт продаж'!J:L,3,0)/SUM('План Антонова'!$C$14:$C$16),0) -> 0.033946856 | K34: =IFERROR(VLOOKUP(B34,'Факт продаж'!J:O,6,0),"-") -> 19.720734 | L34: =IF(AND(F34=0,J34>0),5,IF(J34/F34>5,5,IF(J34/F34=0,0.0000001,J34/F34))) -> 5 | M34: =IFERROR(VLOOKUP(B34,'Факт продаж'!S:T,2,0),"нет продаж") -> 1172 | N34: =IFERROR(VLOOKUP(B34,'Факт продаж'!S:U,3,0),"нет продаж") -> 6188129.3 | O34: =IFERROR(VLOOKUP(B34,'Факт продаж'!S:W,5,0),"нет продаж") -> 2519842.1 | P34: =IFERROR(VLOOKUP(B34,'Факт продаж'!S:U,3,0)/SUM('План Антонова'!$C$17:$C$19),0) -> 0.037692207 | Q34: =IFERROR(VLOOKUP(B34,'Факт продаж'!S:X,6,0),"-") -> 0.081451729 | R34: =IF(AND(J34=0,P34>0),5,IF(P34/J34>5,5,IF(P34/J34=0,0.0000001,P34/J34))) -> 1.1103299 | S34: =IFERROR(VLOOKUP(B34,'Факт продаж'!AB:AD,2,0),"нет продаж") -> 614 | T34: =IFERROR(VLOOKUP(B34,'Факт продаж'!AB:AD,3,0),"нет продаж") -> 3500784.6 | U34: =IFERROR(VLOOKUP(B34,'Факт продаж'!AB:AF,5,0),"нет продаж") -> 1566355.7 | V34: =IFERROR(VLOOKUP(B34,'Факт продаж'!AB:AD,3,0)/SUM('План Антонова'!$C$20:$C$22),0) -> 0.022750539 | W34: =IFERROR(VLOOKUP(B34,'Факт продаж'!AB:AG,6,0),"-") -> -0.37839132 | X34: =IF(AND(P34=0,V34>0),5,IF(V34/P34>5,5,IF(V34/P34=0,0.0000001,V34/P34))) -> 0.60358734 | Y34: =IFERROR(VLOOKUP(B34,'Факт продаж'!AB:AH,7,0),"-") -> 12.929301 | Z34: =IF(AND(F34=0,V34>0),5,IF(V34/F34>5,5,IF(V34/F34=0,0.0000001,V34/F34))) -> 5 | AB34: =IFERROR(VLOOKUP(VALUE(IF(L34<1,1,0)&IF(J34<'Факт продаж'!$M$24,0,1)),$AB$1:$AC$4,2,FALSE),"НЕТ ПРОДАЖ") -> Звезда | AC34: =IFERROR(VLOOKUP(VALUE(IF(R34<1,1,0)&IF(P34<'Факт продаж'!$V$24,0,1)),$AB$1:$AC$4,2,FALSE),"НЕТ ПРОДАЖ") -> Звезда | AD34: =IFERROR(VLOOKUP(VALUE(IF(X34<1,1,0)&IF(V34<'Факт продаж'!$AE$24,0,1)),$AB$1:$AC$4,2,FALSE),"НЕТ ПРОДАЖ") -> Корова | AE34: =IFERROR(VLOOKUP(VALUE(IF(Z34<1,1,0)&IF(V34<'Факт продаж'!$AE$24,0,1)),$AB$1:$AC$4,2,FALSE),"НЕТ ПРОДАЖ") -> Звезда | AF34: =VLOOKUP(B34,'ABC расчет'!B:G,6,0) -> B | AG34: =VLOOKUP(B34,'ABC расчет'!K:P,6,0) -> A | AH34: =VLOOKUP(B34,'ABC расчет'!T:Y,6,0) -> A | AI34: =VLOOKUP(B34,'ABC расчет'!AC:AH,6,0) -> A | AJ34: PROMO
A35: КРЕСЛА РУКОВОДИТЕЛЯ | B35: BOSS | C35: =IFERROR(VLOOKUP(B35,'Факт продаж'!A:B,2,0),"нет продаж") -> 173 | D35: =IFERROR(VLOOKUP(B35,'Факт продаж'!A:C,3,0),"нет продаж") -> 541713.02 | E35: =IFERROR(VLOOKUP(B35,'Факт продаж'!A:E,5,0),"нет продаж") -> 233417.77 | F35: =IFERROR(VLOOKUP(B35,'Факт продаж'!A:C,3,0)/SUM('План Антонова'!$C$11:$C$13),0) -> 0.0041132843 | G35: =IFERROR(VLOOKUP(B35,'Факт продаж'!J:K,2,0),"нет продаж") -> 2219 | H35: =IFERROR(VLOOKUP(B35,'Факт продаж'!J:L,3,0),"нет продаж") -> 7880496 | I35: =IFERROR(VLOOKUP(B35,'Факт продаж'!J:N,5,0),"нет продаж") -> 4059483.9 | J35: =IFERROR(VLOOKUP(B35,'Факт продаж'!J:L,3,0)/SUM('План Антонова'!$C$14:$C$16),0) -> 0.054413723 | K35: =IFERROR(VLOOKUP(B35,'Факт продаж'!J:O,6,0),"-") -> 16.391495 | L35: =IF(AND(F35=0,J35>0),5,IF(J35/F35>5,5,IF(J35/F35=0,0.0000001,J35/F35))) -> 5 | M35: =IFERROR(VLOOKUP(B35,'Факт продаж'!S:T,2,0),"нет продаж") -> 1229 | N35: =IFERROR(VLOOKUP(B35,'Факт продаж'!S:U,3,0),"нет продаж") -> 4610369.8 | O35: =IFERROR(VLOOKUP(B35,'Факт продаж'!S:W,5,0),"нет продаж") -> 2259960 | P35: =IFERROR(VLOOKUP(B35,'Факт продаж'!S:U,3,0)/SUM('План Антонова'!$C$17:$C$19),0) -> 0.028081994 | Q35: =IFERROR(VLOOKUP(B35,'Факт продаж'!S:X,6,0),"-") -> -0.44328885 | R35: =IF(AND(J35=0,P35>0),5,IF(P35/J35>5,5,IF(P35/J35=0,0.0000001,P35/J35))) -> 0.51608294 | S35: =IFERROR(VLOOKUP(B35,'Факт продаж'!AB:AD,2,0),"нет продаж") -> 821 | T35: =IFERROR(VLOOKUP(B35,'Факт продаж'!AB:AD,3,0),"нет продаж") -> 3134898.6 | U35: =IFERROR(VLOOKUP(B35,'Факт продаж'!AB:AF,5,0),"нет продаж") -> 1516602.3 | V35: =IFERROR(VLOOKUP(B35,'Факт продаж'!AB:AD,3,0)/SUM('План Антонова'!$C$20:$C$22),0) -> 0.020372757 | W35: =IFERROR(VLOOKUP(B35,'Факт продаж'!AB:AG,6,0),"-") -> -0.32892514 | X35: =IF(AND(P35=0,V35>0),5,IF(V35/P35>5,5,IF(V35/P35=0,0.0000001,V35/P35))) -> 0.72547401 | Y35: =IFERROR(VLOOKUP(B35,'Факт продаж'!AB:AH,7,0),"-") -> 5.4973731 | Z35: =IF(AND(F35=0,V35>0),5,IF(V35/F35>5,5,IF(V35/F35=0,0.0000001,V35/F35))) -> 4.9529173 | AB35: =IFERROR(VLOOKUP(VALUE(IF(L35<1,1,0)&IF(J35<'Факт продаж'!$M$24,0,1)),$AB$1:$AC$4,2,FALSE),"НЕТ ПРОДАЖ") -> Звезда | AC35: =IFERROR(VLOOKUP(VALUE(IF(R35<1,1,0)&IF(P35<'Факт продаж'!$V$24,0,1)),$AB$1:$AC$4,2,FALSE),"НЕТ ПРОДАЖ") -> Корова | AD35: =IFERROR(VLOOKUP(VALUE(IF(X35<1,1,0)&IF(V35<'Факт продаж'!$AE$24,0,1)),$AB$1:$AC$4,2,FALSE),"НЕТ ПРОДАЖ") -> Корова | AE35: =IFERROR(VLOOKUP(VALUE(IF(Z35<1,1,0)&IF(V35<'Факт продаж'!$AE$24,0,1)),$AB$1:$AC$4,2,FALSE),"НЕТ ПРОДАЖ") -> Звезда | AF35: =VLOOKUP(B35,'ABC расчет'!B:G,6,0) -> A | AG35: =VLOOKUP(B35,'ABC расчет'!K:P,6,0) -> A | AH35: =VLOOKUP(B35,'ABC расчет'!T:Y,6,0) -> A | AI35: =VLOOKUP(B35,'ABC расчет'!AC:AH,6,0) -> A
A36: КРЕСЛА ОПЕРАТОРСКИЕ | B36: ALFA | C36: =IFERROR(VLOOKUP(B36,'Факт продаж'!A:B,2,0),"нет продаж") -> 10 | D36: =IFERROR(VLOOKUP(B36,'Факт продаж'!A:C,3,0),"нет продаж") -> 15069.337 | E36: =IFERROR(VLOOKUP(B36,'Факт продаж'!A:E,5,0),"нет продаж") -> 6250.316 | F36: =IFERROR(VLOOKUP(B36,'Факт продаж'!A:C,3,0)/SUM('План Антонова'!$C$11:$C$13),0) -> 0.00011442307 | G36: =IFERROR(VLOOKUP(B36,'Факт продаж'!J:K,2,0),"нет продаж") -> 3029 | H36: =IFERROR(VLOOKUP(B36,'Факт продаж'!J:L,3,0),"нет продаж") -> 5214554.1 | I36: =IFERROR(VLOOKUP(B36,'Факт продаж'!J:N,5,0),"нет продаж") -> 2134677.4 | J36: =IFERROR(VLOOKUP(B36,'Факт продаж'!J:L,3,0)/SUM('План Антонова'!$C$14:$C$16),0) -> 0.036005767 | K36: =IFERROR(VLOOKUP(B36,'Факт продаж'!J:O,6,0),"-") -> 340.53111 | L36: =IF(AND(F36=0,J36>0),5,IF(J36/F36>5,5,IF(J36/F36=0,0.0000001,J36/F36))) -> 5 | M36: =IFERROR(VLOOKUP(B36,'Факт продаж'!S:T,2,0),"нет продаж") -> 2859 | N36: =IFERROR(VLOOKUP(B36,'Факт продаж'!S:U,3,0),"нет продаж") -> 4988954.6 | O36: =IFERROR(VLOOKUP(B36,'Факт продаж'!S:W,5,0),"нет продаж") -> 1860334.9 | P36: =IFERROR(VLOOKUP(B36,'Факт продаж'!S:U,3,0)/SUM('План Антонова'!$C$17:$C$19),0) -> 0.030387974 | Q36: =IFERROR(VLOOKUP(B36,'Факт продаж'!S:X,6,0),"-") -> -0.12851708 | R36: =IF(AND(J36=0,P36>0),5,IF(P36/J36>5,5,IF(P36/J36=0,0.0000001,P36/J36))) -> 0.84397518 | S36: =IFERROR(VLOOKUP(B36,'Факт продаж'!AB:AD,2,0),"нет продаж") -> 2218 | T36: =IFERROR(VLOOKUP(B36,'Факт продаж'!AB:AD,3,0),"нет продаж") -> 3916741.3 | U36: =IFERROR(VLOOKUP(B36,'Факт продаж'!AB:AF,5,0),"нет продаж") -> 1483325.7 | V36: =IFERROR(VLOOKUP(B36,'Факт продаж'!AB:AD,3,0)/SUM('План Антонова'!$C$20:$C$22),0) -> 0.025453716 | W36: =IFERROR(VLOOKUP(B36,'Факт продаж'!AB:AG,6,0),"-") -> -0.20265659 | X36: =IF(AND(P36=0,V36>0),5,IF(V36/P36>5,5,IF(V36/P36=0,0.0000001,V36/P36))) -> 0.83762466 | Y36: =IFERROR(VLOOKUP(B36,'Факт продаж'!AB:AH,7,0),"-") -> 236.32012 | Z36: =IF(AND(F36=0,V36>0),5,IF(V36/F36>5,5,IF(V36/F36=0,0.0000001,V36/F36))) -> 5 | AB36: =IFERROR(VLOOKUP(VALUE(IF(L36<1,1,0)&IF(J36<'Факт продаж'!$M$24,0,1)),$AB$1:$AC$4,2,FALSE),"НЕТ ПРОДАЖ") -> Звезда | AC36: =IFERROR(VLOOKUP(VALUE(IF(R36<1,1,0)&IF(P36<'Факт продаж'!$V$24,0,1)),$AB$1:$AC$4,2,FALSE),"НЕТ ПРОДАЖ") -> Корова | AD36: =IFERROR(VLOOKUP(VALUE(IF(X36<1,1,0)&IF(V36<'Факт продаж'!$AE$24,0,1)),$AB$1:$AC$4,2,FALSE),"НЕТ ПРОДАЖ") -> Корова | AE36: =IFERROR(VLOOKUP(VALUE(IF(Z36<1,1,0)&IF(V36<'Факт продаж'!$AE$24,0,1)),$AB$1:$AC$4,2,FALSE),"НЕТ ПРОДАЖ") -> Звезда | AF36: =VLOOKUP(B36,'ABC расчет'!B:G,6,0) -> C | AG36: =VLOOKUP(B36,'ABC расчет'!K:P,6,0) -> A | AH36: =VLOOKUP(B36,'ABC расчет'!T:Y,6,0) -> A | AI36: =VLOOKUP(B36,'ABC расчет'!AC:AH,6,0) -> A | AJ36: PROMO
A37: КРЕСЛА ОПЕРАТОРСКИЕ | B37: FLY | C37: =IFERROR(VLOOKUP(B37,'Факт продаж'!A:B,2,0),"нет продаж") -> 431 | D37: =IFERROR(VLOOKUP(B37,'Факт продаж'!A:C,3,0),"нет продаж") -> 796455.75 | E37: =IFERROR(VLOOKUP(B37,'Факт продаж'!A:E,5,0),"нет продаж") -> 337919.57 | F37: =IFERROR(VLOOKUP(B37,'Факт продаж'!A:C,3,0)/SUM('План Антонова'!$C$11:$C$13),0) -> 0.0060475729 | G37: =IFERROR(VLOOKUP(B37,'Факт продаж'!J:K,2,0),"нет продаж") -> 1369 | H37: =IFERROR(VLOOKUP(B37,'Факт продаж'!J:L,3,0),"нет продаж") -> 2767314.2 | I37: =IFERROR(VLOOKUP(B37,'Факт продаж'!J:N,5,0),"нет продаж") -> 1310939.9 | J37: =IFERROR(VLOOKUP(B37,'Факт продаж'!J:L,3,0)/SUM('План Антонова'!$C$14:$C$16),0) -> 0.019107918 | K37: =IFERROR(VLOOKUP(B37,'Факт продаж'!J:O,6,0),"-") -> 2.8794437 | L37: =IF(AND(F37=0,J37>0),5,IF(J37/F37>5,5,IF(J37/F37=0,0.0000001,J37/F37))) -> 3.159601 | M37: =IFERROR(VLOOKUP(B37,'Факт продаж'!S:T,2,0),"нет продаж") -> 1840 | N37: =IFERROR(VLOOKUP(B37,'Факт продаж'!S:U,3,0),"нет продаж") -> 3661447.4 | O37: =IFERROR(VLOOKUP(B37,'Факт продаж'!S:W,5,0),"нет продаж") -> 1459692.1 | P37: =IFERROR(VLOOKUP(B37,'Факт продаж'!S:U,3,0)/SUM('План Антонова'!$C$17:$C$19),0) -> 0.022302061 | Q37: =IFERROR(VLOOKUP(B37,'Факт продаж'!S:X,6,0),"-") -> 0.11346983 | R37: =IF(AND(J37=0,P37>0),5,IF(P37/J37>5,5,IF(P37/J37=0,0.0000001,P37/J37))) -> 1.1671633 | S37: =IFERROR(VLOOKUP(B37,'Факт продаж'!AB:AD,2,0),"нет продаж") -> 1568 | T37: =IFERROR(VLOOKUP(B37,'Факт продаж'!AB:AD,3,0),"нет продаж") -> 3420548 | U37: =IFERROR(VLOOKUP(B37,'Факт продаж'!AB:AF,5,0),"нет продаж") -> 1479995.7 | V37: =IFERROR(VLOOKUP(B37,'Факт продаж'!AB:AD,3,0)/SUM('План Антонова'!$C$20:$C$22),0) -> 0.022229106 | W37: =IFERROR(VLOOKUP(B37,'Факт продаж'!AB:AG,6,0),"-") -> 0.013909555 | X37: =IF(AND(P37=0,V37>0),5,IF(V37/P37>5,5,IF(V37/P37=0,0.0000001,V37/P37))) -> 0.99672878 | Y37: =IFERROR(VLOOKUP(B37,'Факт продаж'!AB:AH,7,0),"-") -> 3.3797278 | Z37: =IF(AND(F37=0,V37>0),5,IF(V37/F37>5,5,IF(V37/F37=0,0.0000001,V37/F37))) -> 3.6757069 | AB37: =IFERROR(VLOOKUP(VALUE(IF(L37<1,1,0)&IF(J37<'Факт продаж'!$M$24,0,1)),$AB$1:$AC$4,2,FALSE),"НЕТ ПРОДАЖ") -> Звезда | AC37: =IFERROR(VLOOKUP(VALUE(IF(R37<1,1,0)&IF(P37<'Факт продаж'!$V$24,0,1)),$AB$1:$AC$4,2,FALSE),"НЕТ ПРОДАЖ") -> Звезда | AD37: =IFERROR(VLOOKUP(VALUE(IF(X37<1,1,0)&IF(V37<'Факт продаж'!$AE$24,0,1)),$AB$1:$AC$4,2,FALSE),"НЕТ ПРОДАЖ") -> Корова | AE37: =IFERROR(VLOOKUP(VALUE(IF(Z37<1,1,0)&IF(V37<'Факт продаж'!$AE$24,0,1)),$AB$1:$AC$4,2,FALSE),"НЕТ ПРОДАЖ") -> Звезда | AF37: =VLOOKUP(B37,'ABC расчет'!B:G,6,0) -> A | AG37: =VLOOKUP(B37,'ABC расчет'!K:P,6,0) -> A | AH37: =VLOOKUP(B37,'ABC расчет'!T:Y,6,0) -> A | AI37: =VLOOKUP(B37,'ABC расчет'!AC:AH,6,0) -> A | AJ37: PROMO
A38: КРЕСЛА ОПЕРАТОРСКИЕ | B38: ULTRA | C38: =IFERROR(VLOOKUP(B38,'Факт продаж'!A:B,2,0),"нет продаж") -> 550 | D38: =IFERROR(VLOOKUP(B38,'Факт продаж'!A:C,3,0),"нет продаж") -> 1096549.1 | E38: =IFERROR(VLOOKUP(B38,'Факт продаж'!A:E,5,0),"нет продаж") -> 320642.46 | F38: =IFERROR(VLOOKUP(B38,'Факт продаж'!A:C,3,0)/SUM('План Антонова'!$C$11:$C$13),0) -> 0.0083262135 | G38: =IFERROR(VLOOKUP(B38,'Факт продаж'!J:K,2,0),"нет продаж") -> 422 | H38: =IFERROR(VLOOKUP(B38,'Факт продаж'!J:L,3,0),"нет продаж") -> 1065223.2 | I38: =IFERROR(VLOOKUP(B38,'Факт продаж'!J:N,5,0),"нет продаж") -> 430956.46 | J38: =IFERROR(VLOOKUP(B38,'Факт продаж'!J:L,3,0)/SUM('План Антонова'!$C$14:$C$16),0) -> 0.007355217 | K38: =IFERROR(VLOOKUP(B38,'Факт продаж'!J:O,6,0),"-") -> 0.34404053 | L38: =IF(AND(F38=0,J38>0),5,IF(J38/F38>5,5,IF(J38/F38=0,0.0000001,J38/F38))) -> 0.88338078 | M38: =IFERROR(VLOOKUP(B38,'Факт продаж'!S:T,2,0),"нет продаж") -> 485 | N38: =IFERROR(VLOOKUP(B38,'Факт продаж'!S:U,3,0),"нет продаж") -> 1293251.8 | O38: =IFERROR(VLOOKUP(B38,'Факт продаж'!S:W,5,0),"нет продаж") -> 533612.23 | P38: =IFERROR(VLOOKUP(B38,'Факт продаж'!S:U,3,0)/SUM('План Антонова'!$C$17:$C$19),0) -> 0.0078772616 | Q38: =IFERROR(VLOOKUP(B38,'Факт продаж'!S:X,6,0),"-") -> 0.23820451 | R38: =IF(AND(J38=0,P38>0),5,IF(P38/J38>5,5,IF(P38/J38=0,0.0000001,P38/J38))) -> 1.0709761 | S38: =IFERROR(VLOOKUP(B38,'Факт продаж'!AB:AD,2,0),"нет продаж") -> 1434 | T38: =IFERROR(VLOOKUP(B38,'Факт продаж'!AB:AD,3,0),"нет продаж") -> 3747192.2 | U38: =IFERROR(VLOOKUP(B38,'Факт продаж'!AB:AF,5,0),"нет продаж") -> 1416147.7 | V38: =IFERROR(VLOOKUP(B38,'Факт продаж'!AB:AD,3,0)/SUM('План Антонова'!$C$20:$C$22),0) -> 0.024351867 | W38: =IFERROR(VLOOKUP(B38,'Факт продаж'!AB:AG,6,0),"-") -> 1.6538892 | X38: =IF(AND(P38=0,V38>0),5,IF(V38/P38>5,5,IF(V38/P38=0,0.0000001,V38/P38))) -> 3.0914128 | Y38: =IFERROR(VLOOKUP(B38,'Факт продаж'!AB:AH,7,0),"-") -> 3.4165945 | Z38: =IF(AND(F38=0,V38>0),5,IF(V38/F38>5,5,IF(V38/F38=0,0.0000001,V38/F38))) -> 2.9247229 | AB38: =IFERROR(VLOOKUP(VALUE(IF(L38<1,1,0)&IF(J38<'Факт продаж'!$M$24,0,1)),$AB$1:$AC$4,2,FALSE),"НЕТ ПРОДАЖ") -> Корова | AC38: =IFERROR(VLOOKUP(VALUE(IF(R38<1,1,0)&IF(P38<'Факт продаж'!$V$24,0,1)),$AB$1:$AC$4,2,FALSE),"НЕТ ПРОДАЖ") -> Звезда | AD38: =IFERROR(VLOOKUP(VALUE(IF(X38<1,1,0)&IF(V38<'Факт продаж'!$AE$24,0,1)),$AB$1:$AC$4,2,FALSE),"НЕТ ПРОДАЖ") -> Звезда | AE38: =IFERROR(VLOOKUP(VALUE(IF(Z38<1,1,0)&IF(V38<'Факт продаж'!$AE$24,0,1)),$AB$1:$AC$4,2,FALSE),"НЕТ ПРОДАЖ") -> Звезда | AF38: =VLOOKUP(B38,'ABC расчет'!B:G,6,0) -> A | AG38: =VLOOKUP(B38,'ABC расчет'!K:P,6,0) -> A | AH38: =VLOOKUP(B38,'ABC расчет'!T:Y,6,0) -> A | AI38: =VLOOKUP(B38,'ABC расчет'!AC:AH,6,0) -> A | AJ38: PROMO
A39: СТУЛЬЯ ПОСЕТИТЕЛЬСКИЕ | B39: VISITOR | C39: =IFERROR(VLOOKUP(B39,'Факт продаж'!A:B,2,0),"нет продаж") -> 34 | D39: =IFERROR(VLOOKUP(B39,'Факт продаж'!A:C,3,0),"нет продаж") -> 17950.15 | E39: =IFERROR(VLOOKUP(B39,'Факт продаж'!A:E,5,0),"нет продаж") -> 8658.2005 | F39: =IFERROR(VLOOKUP(B39,'Факт продаж'!A:C,3,0)/SUM('План Антонова'!$C$11:$C$13),0) -> 0.00013629739 | G39: =IFERROR(VLOOKUP(B39,'Факт продаж'!J:K,2,0),"нет продаж") -> 4694 | H39: =IFERROR(VLOOKUP(B39,'Факт продаж'!J:L,3,0),"нет продаж") -> 3162364.3 | I39: =IFERROR(VLOOKUP(B39,'Факт продаж'!J:N,5,0),"нет продаж") -> 1596204.2 | J39: =IFERROR(VLOOKUP(B39,'Факт продаж'!J:L,3,0)/SUM('План Антонова'!$C$14:$C$16),0) -> 0.021835683 | K39: =IFERROR(VLOOKUP(B39,'Факт продаж'!J:O,6,0),"-") -> 183.3575 | L39: =IF(AND(F39=0,J39>0),5,IF(J39/F39>5,5,IF(J39/F39=0,0.0000001,J39/F39))) -> 5 | M39: =IFERROR(VLOOKUP(B39,'Факт продаж'!S:T,2,0),"нет продаж") -> 5569 | N39: =IFERROR(VLOOKUP(B39,'Факт продаж'!S:U,3,0),"нет продаж") -> 3557262.6 | O39: =IFERROR(VLOOKUP(B39,'Факт продаж'!S:W,5,0),"нет продаж") -> 1613369.4 | P39: =IFERROR(VLOOKUP(B39,'Факт продаж'!S:U,3,0)/SUM('План Антонова'!$C$17:$C$19),0) -> 0.021667466 | Q39: =IFERROR(VLOOKUP(B39,'Факт продаж'!S:X,6,0),"-") -> 0.010753751 | R39: =IF(AND(J39=0,P39>0),5,IF(P39/J39>5,5,IF(P39/J39=0,0.0000001,P39/J39))) -> 0.99229621 | S39: =IFERROR(VLOOKUP(B39,'Факт продаж'!AB:AD,2,0),"нет продаж") -> 4245 | T39: =IFERROR(VLOOKUP(B39,'Факт продаж'!AB:AD,3,0),"нет продаж") -> 2859336.4 | U39: =IFERROR(VLOOKUP(B39,'Факт продаж'!AB:AF,5,0),"нет продаж") -> 1313437.6 | V39: =IFERROR(VLOOKUP(B39,'Факт продаж'!AB:AD,3,0)/SUM('План Антонова'!$C$20:$C$22),0) -> 0.018581961 | W39: =IFERROR(VLOOKUP(B39,'Факт продаж'!AB:AG,6,0),"-") -> -0.18590395 | X39: =IF(AND(P39=0,V39>0),5,IF(V39/P39>5,5,IF(V39/P39=0,0.0000001,V39/P39))) -> 0.85759734 | Y39: =IFERROR(VLOOKUP(B39,'Факт продаж'!AB:AH,7,0),"-") -> 150.69869 | Z39: =IF(AND(F39=0,V39>0),5,IF(V39/F39>5,5,IF(V39/F39=0,0.0000001,V39/F39))) -> 5 | AB39: =IFERROR(VLOOKUP(VALUE(IF(L39<1,1,0)&IF(J39<'Факт продаж'!$M$24,0,1)),$AB$1:$AC$4,2,FALSE),"НЕТ ПРОДАЖ") -> Звезда | AC39: =IFERROR(VLOOKUP(VALUE(IF(R39<1,1,0)&IF(P39<'Факт продаж'!$V$24,0,1)),$AB$1:$AC$4,2,FALSE),"НЕТ ПРОДАЖ") -> Корова | AD39: =IFERROR(VLOOKUP(VALUE(IF(X39<1,1,0)&IF(V39<'Факт продаж'!$AE$24,0,1)),$AB$1:$AC$4,2,FALSE),"НЕТ ПРОДАЖ") -> Корова | AE39: =IFERROR(VLOOKUP(VALUE(IF(Z39<1,1,0)&IF(V39<'Факт продаж'!$AE$24,0,1)),$AB$1:$AC$4,2,FALSE),"НЕТ ПРОДАЖ") -> Звезда | AF39: =VLOOKUP(B39,'ABC расчет'!B:G,6,0) -> C | AG39: =VLOOKUP(B39,'ABC расчет'!K:P,6,0) -> A | AH39: =VLOOKUP(B39,'ABC расчет'!T:Y,6,0) -> A | AI39: =VLOOKUP(B39,'ABC расчет'!AC:AH,6,0) -> A
A40: СТУЛЬЯ ПОСЕТИТЕЛЬСКИЕ | B40: ERA | C40: =IFERROR(VLOOKUP(B40,'Факт продаж'!A:B,2,0),"нет продаж") -> 205 | D40: =IFERROR(VLOOKUP(B40,'Факт продаж'!A:C,3,0),"нет продаж") -> 119001.04 | E40: =IFERROR(VLOOKUP(B40,'Факт продаж'!A:E,5,0),"нет продаж") -> 45805.292 | F40: =IFERROR(VLOOKUP(B40,'Факт продаж'!A:C,3,0)/SUM('План Антонова'!$C$11:$C$13),0) -> 0.00090358751 | G40: =IFERROR(VLOOKUP(B40,'Факт продаж'!J:K,2,0),"нет продаж") -> 2069 | H40: =IFERROR(VLOOKUP(B40,'Факт продаж'!J:L,3,0),"нет продаж") -> 1826940.4 | I40: =IFERROR(VLOOKUP(B40,'Факт продаж'!J:N,5,0),"нет продаж") -> 876174.87 | J40: =IFERROR(VLOOKUP(B40,'Факт продаж'!J:L,3,0)/SUM('План Антонова'!$C$14:$C$16),0) -> 0.012614768 | K40: =IFERROR(VLOOKUP(B40,'Факт продаж'!J:O,6,0),"-") -> 18.128245 | L40: =IF(AND(F40=0,J40>0),5,IF(J40/F40>5,5,IF(J40/F40=0,0.0000001,J40/F40))) -> 5 | M40: =IFERROR(VLOOKUP(B40,'Факт продаж'!S:T,2,0),"нет продаж") -> 2112 | N40: =IFERROR(VLOOKUP(B40,'Факт продаж'!S:U,3,0),"нет продаж") -> 2027871.6 | O40: =IFERROR(VLOOKUP(B40,'Факт продаж'!S:W,5,0),"нет продаж") -> 958623.55 | P40: =IFERROR(VLOOKUP(B40,'Факт продаж'!S:U,3,0)/SUM('План Антонова'!$C$17:$C$19),0) -> 0.012351868 | Q40: =IFERROR(VLOOKUP(B40,'Факт продаж'!S:X,6,0),"-") -> 0.094100706 | R40: =IF(AND(J40=0,P40>0),5,IF(P40/J40>5,5,IF(P40/J40=0,0.0000001,P40/J40))) -> 0.97915935 | S40: =IFERROR(VLOOKUP(B40,'Факт продаж'!AB:AD,2,0),"нет продаж") -> 3105 | T40: =IFERROR(VLOOKUP(B40,'Факт продаж'!AB:AD,3,0),"нет продаж") -> 2568570.8 | U40: =IFERROR(VLOOKUP(B40,'Факт продаж'!AB:AF,5,0),"нет продаж") -> 1217757.4 | V40: =IFERROR(VLOOKUP(B40,'Факт продаж'!AB:AD,3,0)/SUM('План Антонова'!$C$20:$C$22),0) -> 0.016692364 | W40: =IFERROR(VLOOKUP(B40,'Факт продаж'!AB:AG,6,0),"-") -> 0.27031867 | X40: =IF(AND(P40=0,V40>0),5,IF(V40/P40>5,5,IF(V40/P40=0,0.0000001,V40/P40))) -> 1.351404 | Y40: =IFERROR(VLOOKUP(B40,'Факт продаж'!AB:AH,7,0),"-") -> 25.585517 | Z40: =IF(AND(F40=0,V40>0),5,IF(V40/F40>5,5,IF(V40/F40=0,0.0000001,V40/F40))) -> 5 | AB40: =IFERROR(VLOOKUP(VALUE(IF(L40<1,1,0)&IF(J40<'Факт продаж'!$M$24,0,1)),$AB$1:$AC$4,2,FALSE),"НЕТ ПРОДАЖ") -> Звезда | AC40: =IFERROR(VLOOKUP(VALUE(IF(R40<1,1,0)&IF(P40<'Факт продаж'!$V$24,0,1)),$AB$1:$AC$4,2,FALSE),"НЕТ ПРОДАЖ") -> Корова | AD40: =IFERROR(VLOOKUP(VALUE(IF(X40<1,1,0)&IF(V40<'Факт продаж'!$AE$24,0,1)),$AB$1:$AC$4,2,FALSE),"НЕТ ПРОДАЖ") -> Звезда | AE40: =IFERROR(VLOOKUP(VALUE(IF(Z40<1,1,0)&IF(V40<'Факт продаж'!$AE$24,0,1)),$AB$1:$AC$4,2,FALSE),"НЕТ ПРОДАЖ") -> Звезда | AF40: =VLOOKUP(B40,'ABC расчет'!B:G,6,0) -> C | AG40: =VLOOKUP(B40,'ABC расчет'!K:P,6,0) -> A | AH40: =VLOOKUP(B40,'ABC расчет'!T:Y,6,0) -> B | AI40: =VLOOKUP(B40,'ABC расчет'!AC:AH,6,0) -> A
A41: КРЕСЛА ОПЕРАТОРСКИЕ | B41: BETTA | C41: =IFERROR(VLOOKUP(B41,'Факт продаж'!A:B,2,0),"нет продаж") -> 70 | D41: =IFERROR(VLOOKUP(B41,'Факт продаж'!A:C,3,0),"нет продаж") -> 120233.89 | E41: =IFERROR(VLOOKUP(B41,'Факт продаж'!A:E,5,0),"нет продаж") -> 56980.367 | F41: =IFERROR(VLOOKUP(B41,'Факт продаж'!A:C,3,0)/SUM('План Антонова'!$C$11:$C$13),0) -> 0.00091294867 | G41: =IFERROR(VLOOKUP(B41,'Факт продаж'!J:K,2,0),"нет продаж") -> 865 | H41: =IFERROR(VLOOKUP(B41,'Факт продаж'!J:L,3,0),"нет продаж") -> 1645151.5 | I41: =IFERROR(VLOOKUP(B41,'Факт продаж'!J:N,5,0),"нет продаж") -> 707699.69 | J41: =IFERROR(VLOOKUP(B41,'Факт продаж'!J:L,3,0)/SUM('План Антонова'!$C$14:$C$16),0) -> 0.011359541 | K41: =IFERROR(VLOOKUP(B41,'Факт продаж'!J:O,6,0),"-") -> 11.420062 | L41: =IF(AND(F41=0,J41>0),5,IF(J41/F41>5,5,IF(J41/F41=0,0.0000001,J41/F41))) -> 5 | M41: =IFERROR(VLOOKUP(B41,'Факт продаж'!S:T,2,0),"нет продаж") -> 1545 | N41: =IFERROR(VLOOKUP(B41,'Факт продаж'!S:U,3,0),"нет продаж") -> 3011351.6 | O41: =IFERROR(VLOOKUP(B41,'Факт продаж'!S:W,5,0),"нет продаж") -> 1265452.5 | P41: =IFERROR(VLOOKUP(B41,'Факт продаж'!S:U,3,0)/SUM('План Антонова'!$C$17:$C$19),0) -> 0.018342294 | Q41: =IFERROR(VLOOKUP(B41,'Факт продаж'!S:X,6,0),"-") -> 0.7881208 | R41: =IF(AND(J41=0,P41>0),5,IF(P41/J41>5,5,IF(P41/J41=0,0.0000001,P41/J41))) -> 1.6147038 | S41: =IFERROR(VLOOKUP(B41,'Факт продаж'!AB:AD,2,0),"нет продаж") -> 1393 | T41: =IFERROR(VLOOKUP(B41,'Факт продаж'!AB:AD,3,0),"нет продаж") -> 2729452.9 | U41: =IFERROR(VLOOKUP(B41,'Факт продаж'!AB:AF,5,0),"нет продаж") -> 1189745.7 | V41: =IFERROR(VLOOKUP(B41,'Факт продаж'!AB:AD,3,0)/SUM('План Антонова'!$C$20:$C$22),0) -> 0.017737888 | W41: =IFERROR(VLOOKUP(B41,'Факт продаж'!AB:AG,6,0),"-") -> -0.059825923 | X41: =IF(AND(P41=0,V41>0),5,IF(V41/P41>5,5,IF(V41/P41=0,0.0000001,V41/P41))) -> 0.9670485 | Y41: =IFERROR(VLOOKUP(B41,'Факт продаж'!AB:AH,7,0),"-") -> 19.879923 | Z41: =IF(AND(F41=0,V41>0),5,IF(V41/F41>5,5,IF(V41/F41=0,0.0000001,V41/F41))) -> 5 | AB41: =IFERROR(VLOOKUP(VALUE(IF(L41<1,1,0)&IF(J41<'Факт продаж'!$M$24,0,1)),$AB$1:$AC$4,2,FALSE),"НЕТ ПРОДАЖ") -> Звезда | AC41: =IFERROR(VLOOKUP(VALUE(IF(R41<1,1,0)&IF(P41<'Факт продаж'!$V$24,0,1)),$AB$1:$AC$4,2,FALSE),"НЕТ ПРОДАЖ") -> Звезда | AD41: =IFERROR(VLOOKUP(VALUE(IF(X41<1,1,0)&IF(V41<'Факт продаж'!$AE$24,0,1)),$AB$1:$AC$4,2,FALSE),"НЕТ ПРОДАЖ") -> Корова | AE41: =IFERROR(VLOOKUP(VALUE(IF(Z41<1,1,0)&IF(V41<'Факт продаж'!$AE$24,0,1)),$AB$1:$AC$4,2,FALSE),"НЕТ ПРОДАЖ") -> Звезда | AF41: =VLOOKUP(B41,'ABC расчет'!B:G,6,0) -> B | AG41: =VLOOKUP(B41,'ABC расчет'!K:P,6,0) -> A | AH41: =VLOOKUP(B41,'ABC расчет'!T:Y,6,0) -> A | AI41: =VLOOKUP(B41,'ABC расчет'!AC:AH,6,0) -> A | AJ41: PROMO
A42: КРЕСЛА/СТУЛЬЯ ОБЕДЕННЫЕ | B42: NICOLE | C42: =IFERROR(VLOOKUP(B42,'Факт продаж'!A:B,2,0),"нет продаж") -> 342 | D42: =IFERROR(VLOOKUP(B42,'Факт продаж'!A:C,3,0),"нет продаж") -> 449754.67 | E42: =IFERROR(VLOOKUP(B42,'Факт продаж'!A:E,5,0),"нет продаж") -> 197991.06 | F42: =IFERROR(VLOOKUP(B42,'Факт продаж'!A:C,3,0)/SUM('План Антонова'!$C$11:$C$13),0) -> 0.0034150349 | G42: =IFERROR(VLOOKUP(B42,'Факт продаж'!J:K,2,0),"нет продаж") -> 1574 | H42: =IFERROR(VLOOKUP(B42,'Факт продаж'!J:L,3,0),"нет продаж") -> 2846342.7 | I42: =IFERROR(VLOOKUP(B42,'Факт продаж'!J:N,5,0),"нет продаж") -> 1179630.2 | J42: =IFERROR(VLOOKUP(B42,'Факт продаж'!J:L,3,0)/SUM('План Антонова'!$C$14:$C$16),0) -> 0.019653599 | K42: =IFERROR(VLOOKUP(B42,'Факт продаж'!J:O,6,0),"-") -> 4.9579971 | L42: =IF(AND(F42=0,J42>0),5,IF(J42/F42>5,5,IF(J42/F42=0,0.0000001,J42/F42))) -> 5 | M42: =IFERROR(VLOOKUP(B42,'Факт продаж'!S:T,2,0),"нет продаж") -> 1537 | N42: =IFERROR(VLOOKUP(B42,'Факт продаж'!S:U,3,0),"нет продаж") -> 2920717.6 | O42: =IFERROR(VLOOKUP(B42,'Факт продаж'!S:W,5,0),"нет продаж") -> 994112.92 | P42: =IFERROR(VLOOKUP(B42,'Факт продаж'!S:U,3,0)/SUM('План Антонова'!$C$17:$C$19),0) -> 0.017790238 | Q42: =IFERROR(VLOOKUP(B42,'Факт продаж'!S:X,6,0),"-") -> -0.15726732 | R42: =IF(AND(J42=0,P42>0),5,IF(P42/J42>5,5,IF(P42/J42=0,0.0000001,P42/J42))) -> 0.90518986 | S42: =IFERROR(VLOOKUP(B42,'Факт продаж'!AB:AD,2,0),"нет продаж") -> 1535 | T42: =IFERROR(VLOOKUP(B42,'Факт продаж'!AB:AD,3,0),"нет продаж") -> 2986525.1 | U42: =IFERROR(VLOOKUP(B42,'Факт продаж'!AB:AF,5,0),"нет продаж") -> 1112021 | V42: =IFERROR(VLOOKUP(B42,'Факт продаж'!AB:AD,3,0)/SUM('План Антонова'!$C$20:$C$22),0) -> 0.019408522 | W42: =IFERROR(VLOOKUP(B42,'Факт продаж'!AB:AG,6,0),"-") -> 0.11860632 | X42: =IF(AND(P42=0,V42>0),5,IF(V42/P42>5,5,IF(V42/P42=0,0.0000001,V42/P42))) -> 1.0909647 | Y42: =IFERROR(VLOOKUP(B42,'Факт продаж'!AB:AH,7,0),"-") -> 4.6165211 | Z42: =IF(AND(F42=0,V42>0),5,IF(V42/F42>5,5,IF(V42/F42=0,0.0000001,V42/F42))) -> 5 | AB42: =IFERROR(VLOOKUP(VALUE(IF(L42<1,1,0)&IF(J42<'Факт продаж'!$M$24,0,1)),$AB$1:$AC$4,2,FALSE),"НЕТ ПРОДАЖ") -> Звезда | AC42: =IFERROR(VLOOKUP(VALUE(IF(R42<1,1,0)&IF(P42<'Факт продаж'!$V$24,0,1)),$AB$1:$AC$4,2,FALSE),"НЕТ ПРОДАЖ") -> Корова | AD42: =IFERROR(VLOOKUP(VALUE(IF(X42<1,1,0)&IF(V42<'Факт продаж'!$AE$24,0,1)),$AB$1:$AC$4,2,FALSE),"НЕТ ПРОДАЖ") -> Звезда | AE42: =IFERROR(VLOOKUP(VALUE(IF(Z42<1,1,0)&IF(V42<'Факт продаж'!$AE$24,0,1)),$AB$1:$AC$4,2,FALSE),"НЕТ ПРОДАЖ") -> Звезда | AF42: =VLOOKUP(B42,'ABC расчет'!B:G,6,0) -> A | AG42: =VLOOKUP(B42,'ABC расчет'!K:P,6,0) -> A | AH42: =VLOOKUP(B42,'ABC расчет'!T:Y,6,0) -> A | AI42: =VLOOKUP(B42,'ABC расчет'!AC:AH,6,0) -> A | AJ42: PROMO
A43: СТУЛЬЯ ПОСЕТИТЕЛЬСКИЕ | B43: SYLWIA | C43: =IFERROR(VLOOKUP(B43,'Факт продаж'!A:B,2,0),"нет продаж") -> 294 | D43: =IFERROR(VLOOKUP(B43,'Факт продаж'!A:C,3,0),"нет продаж") -> 310236.71 | E43: =IFERROR(VLOOKUP(B43,'Факт продаж'!A:E,5,0),"нет продаж") -> 173625.51 | F43: =IFERROR(VLOOKUP(B43,'Факт продаж'!A:C,3,0)/SUM('План Антонова'!$C$11:$C$13),0) -> 0.0023556602 | G43: =IFERROR(VLOOKUP(B43,'Факт продаж'!J:K,2,0),"нет продаж") -> 1395 | H43: =IFERROR(VLOOKUP(B43,'Факт продаж'!J:L,3,0),"нет продаж") -> 1584040 | I43: =IFERROR(VLOOKUP(B43,'Факт продаж'!J:N,5,0),"нет продаж") -> 759921.56 | J43: =IFERROR(VLOOKUP(B43,'Факт продаж'!J:L,3,0)/SUM('План Антонова'!$C$14:$C$16),0) -> 0.010937575 | K43: =IFERROR(VLOOKUP(B43,'Факт продаж'!J:O,6,0),"-") -> 3.3767853 | L43: =IF(AND(F43=0,J43>0),5,IF(J43/F43>5,5,IF(J43/F43=0,0.0000001,J43/F43))) -> 4.6431038 | M43: =IFERROR(VLOOKUP(B43,'Факт продаж'!S:T,2,0),"нет продаж") -> 1361 | N43: =IFERROR(VLOOKUP(B43,'Факт продаж'!S:U,3,0),"нет продаж") -> 1590186.2 | O43: =IFERROR(VLOOKUP(B43,'Факт продаж'!S:W,5,0),"нет продаж") -> 775622.7 | P43: =IFERROR(VLOOKUP(B43,'Факт продаж'!S:U,3,0)/SUM('План Антонова'!$C$17:$C$19),0) -> 0.0096859039 | Q43: =IFERROR(VLOOKUP(B43,'Факт продаж'!S:X,6,0),"-") -> 0.020661527 | R43: =IF(AND(J43=0,P43>0),5,IF(P43/J43>5,5,IF(P43/J43=0,0.0000001,P43/J43))) -> 0.8855623 | S43: =IFERROR(VLOOKUP(B43,'Факт продаж'!AB:AD,2,0),"нет продаж") -> 2082 | T43: =IFERROR(VLOOKUP(B43,'Факт продаж'!AB:AD,3,0),"нет продаж") -> 2351484 | U43: =IFERROR(VLOOKUP(B43,'Факт продаж'!AB:AF,5,0),"нет продаж") -> 1067778.9 | V43: =IFERROR(VLOOKUP(B43,'Факт продаж'!AB:AD,3,0)/SUM('План Антонова'!$C$20:$C$22),0) -> 0.015281582 | W43: =IFERROR(VLOOKUP(B43,'Факт продаж'!AB:AG,6,0),"-") -> 0.3766731 | X43: =IF(AND(P43=0,V43>0),5,IF(V43/P43>5,5,IF(V43/P43=0,0.0000001,V43/P43))) -> 1.5777136 | Y43: =IFERROR(VLOOKUP(B43,'Факт продаж'!AB:AH,7,0),"-") -> 5.1498966 | Z43: =IF(AND(F43=0,V43>0),5,IF(V43/F43>5,5,IF(V43/F43=0,0.0000001,V43/F43))) -> 5 | AB43: =IFERROR(VLOOKUP(VALUE(IF(L43<1,1,0)&IF(J43<'Факт продаж'!$M$24,0,1)),$AB$1:$AC$4,2,FALSE),"НЕТ ПРОДАЖ") -> Звезда | AC43: =IFERROR(VLOOKUP(VALUE(IF(R43<1,1,0)&IF(P43<'Факт продаж'!$V$24,0,1)),$AB$1:$AC$4,2,FALSE),"НЕТ ПРОДАЖ") -> Корова | AD43: =IFERROR(VLOOKUP(VALUE(IF(X43<1,1,0)&IF(V43<'Факт продаж'!$AE$24,0,1)),$AB$1:$AC$4,2,FALSE),"НЕТ ПРОДАЖ") -> Звезда | AE43: =IFERROR(VLOOKUP(VALUE(IF(Z43<1,1,0)&IF(V43<'Факт продаж'!$AE$24,0,1)),$AB$1:$AC$4,2,FALSE),"НЕТ ПРОДАЖ") -> Звезда | AF43: =VLOOKUP(B43,'ABC расчет'!B:G,6,0) -> C | AG43: =VLOOKUP(B43,'ABC расчет'!K:P,6,0) -> B | AH43: =VLOOKUP(B43,'ABC расчет'!T:Y,6,0) -> B | AI43: =VLOOKUP(B43,'ABC расчет'!AC:AH,6,0) -> B
A44: КРЕСЛА РУКОВОДИТЕЛЯ | B44: ATLANT | C44: =IFERROR(VLOOKUP(B44,'Факт продаж'!A:B,2,0),"нет продаж") -> 175 | D44: =IFERROR(VLOOKUP(B44,'Факт продаж'!A:C,3,0),"нет продаж") -> 725708.48 | E44: =IFERROR(VLOOKUP(B44,'Факт продаж'!A:E,5,0),"нет продаж") -> 400858.72 | F44: =IFERROR(VLOOKUP(B44,'Факт продаж'!A:C,3,0)/SUM('План Антонова'!$C$11:$C$13),0) -> 0.0055103814 | G44: =IFERROR(VLOOKUP(B44,'Факт продаж'!J:K,2,0),"нет продаж") -> 278 | H44: =IFERROR(VLOOKUP(B44,'Факт продаж'!J:L,3,0),"нет продаж") -> 1453913.8 | I44: =IFERROR(VLOOKUP(B44,'Факт продаж'!J:N,5,0),"нет продаж") -> 623946.88 | J44: =IFERROR(VLOOKUP(B44,'Факт продаж'!J:L,3,0)/SUM('План Антонова'!$C$14:$C$16),0) -> 0.010039072 | K44: =IFERROR(VLOOKUP(B44,'Факт продаж'!J:O,6,0),"-") -> 0.55652566 | L44: =IF(AND(F44=0,J44>0),5,IF(J44/F44>5,5,IF(J44/F44=0,0.0000001,J44/F44))) -> 1.821847 | M44: =IFERROR(VLOOKUP(B44,'Факт продаж'!S:T,2,0),"нет продаж") -> 474 | N44: =IFERROR(VLOOKUP(B44,'Факт продаж'!S:U,3,0),"нет продаж") -> 2363565.5 | O44: =IFERROR(VLOOKUP(B44,'Факт продаж'!S:W,5,0),"нет продаж") -> 997420.85 | P44: =IFERROR(VLOOKUP(B44,'Факт продаж'!S:U,3,0)/SUM('План Антонова'!$C$17:$C$19),0) -> 0.014396597 | Q44: =IFERROR(VLOOKUP(B44,'Факт продаж'!S:X,6,0),"-") -> 0.59856694 | R44: =IF(AND(J44=0,P44>0),5,IF(P44/J44>5,5,IF(P44/J44=0,0.0000001,P44/J44))) -> 1.4340566 | S44: =IFERROR(VLOOKUP(B44,'Факт продаж'!AB:AD,2,0),"нет продаж") -> 350 | T44: =IFERROR(VLOOKUP(B44,'Факт продаж'!AB:AD,3,0),"нет продаж") -> 2130112.3 | U44: =IFERROR(VLOOKUP(B44,'Факт продаж'!AB:AF,5,0),"нет продаж") -> 1036381 | V44: =IFERROR(VLOOKUP(B44,'Факт продаж'!AB:AD,3,0)/SUM('План Антонова'!$C$20:$C$22),0) -> 0.013842955 | W44: =IFERROR(VLOOKUP(B44,'Факт продаж'!AB:AG,6,0),"-") -> 0.039060924 | X44: =IF(AND(P44=0,V44>0),5,IF(V44/P44>5,5,IF(V44/P44=0,0.0000001,V44/P44))) -> 0.96154357 | Y44: =IFERROR(VLOOKUP(B44,'Факт продаж'!AB:AH,7,0),"-") -> 1.5854023 | Z44: =IF(AND(F44=0,V44>0),5,IF(V44/F44>5,5,IF(V44/F44=0,0.0000001,V44/F44))) -> 2.5121591 | AB44: =IFERROR(VLOOKUP(VALUE(IF(L44<1,1,0)&IF(J44<'Факт продаж'!$M$24,0,1)),$AB$1:$AC$4,2,FALSE),"НЕТ ПРОДАЖ") -> Звезда | AC44: =IFERROR(VLOOKUP(VALUE(IF(R44<1,1,0)&IF(P44<'Факт продаж'!$V$24,0,1)),$AB$1:$AC$4,2,FALSE),"НЕТ ПРОДАЖ") -> Звезда | AD44: =IFERROR(VLOOKUP(VALUE(IF(X44<1,1,0)&IF(V44<'Факт продаж'!$AE$24,0,1)),$AB$1:$AC$4,2,FALSE),"НЕТ ПРОДАЖ") -> Корова | AE44: =IFERROR(VLOOKUP(VALUE(IF(Z44<1,1,0)&IF(V44<'Факт продаж'!$AE$24,0,1)),$AB$1:$AC$4,2,FALSE),"НЕТ ПРОДАЖ") -> Звезда | AF44: =VLOOKUP(B44,'ABC расчет'!B:G,6,0) -> A | AG44: =VLOOKUP(B44,'ABC расчет'!K:P,6,0) -> A | AH44: =VLOOKUP(B44,'ABC расчет'!T:Y,6,0) -> A | AI44: =VLOOKUP(B44,'ABC расчет'!AC:AH,6,0) -> A
A45: КРЕСЛА ОПЕРАТОРСКИЕ | B45: WEBSTAR | C45: =IFERROR(VLOOKUP(B45,'Факт продаж'!A:B,2,0),"нет продаж") -> 112 | D45: =IFERROR(VLOOKUP(B45,'Факт продаж'!A:C,3,0),"нет продаж") -> 186479.64 | E45: =IFERROR(VLOOKUP(B45,'Факт продаж'!A:E,5,0),"нет продаж") -> 81569.817 | F45: =IFERROR(VLOOKUP(B45,'Факт продаж'!A:C,3,0)/SUM('План Антонова'!$C$11:$C$13),0) -> 0.0014159597 | G45: =IFERROR(VLOOKUP(B45,'Факт продаж'!J:K,2,0),"нет продаж") -> 744 | H45: =IFERROR(VLOOKUP(B45,'Факт продаж'!J:L,3,0),"нет продаж") -> 1808075 | I45: =IFERROR(VLOOKUP(B45,'Факт продаж'!J:N,5,0),"нет продаж") -> 844152.33 | J45: =IFERROR(VLOOKUP(B45,'Факт продаж'!J:L,3,0)/SUM('План Антонова'!$C$14:$C$16),0) -> 0.012484505 | K45: =IFERROR(VLOOKUP(B45,'Факт продаж'!J:O,6,0),"-") -> 9.348832 | L45: =IF(AND(F45=0,J45>0),5,IF(J45/F45>5,5,IF(J45/F45=0,0.0000001,J45/F45))) -> 5 | M45: =IFERROR(VLOOKUP(B45,'Факт продаж'!S:T,2,0),"нет продаж") -> 999 | N45: =IFERROR(VLOOKUP(B45,'Факт продаж'!S:U,3,0),"нет продаж") -> 2273770.2 | O45: =IFERROR(VLOOKUP(B45,'Факт продаж'!S:W,5,0),"нет продаж") -> 960884.87 | P45: =IFERROR(VLOOKUP(B45,'Факт продаж'!S:U,3,0)/SUM('План Антонова'!$C$17:$C$19),0) -> 0.013849649 | Q45: =IFERROR(VLOOKUP(B45,'Факт продаж'!S:X,6,0),"-") -> 0.13828374 | R45: =IF(AND(J45=0,P45>0),5,IF(P45/J45>5,5,IF(P45/J45=0,0.0000001,P45/J45))) -> 1.1093471 | S45: =IFERROR(VLOOKUP(B45,'Факт продаж'!AB:AD,2,0),"нет продаж") -> 947 | T45: =IFERROR(VLOOKUP(B45,'Факт продаж'!AB:AD,3,0),"нет продаж") -> 2134168.4 | U45: =IFERROR(VLOOKUP(B45,'Факт продаж'!AB:AF,5,0),"нет продаж") -> 868272.04 | V45: =IFERROR(VLOOKUP(B45,'Факт продаж'!AB:AD,3,0)/SUM('План Антонова'!$C$20:$C$22),0) -> 0.013869314 | W45: =IFERROR(VLOOKUP(B45,'Факт продаж'!AB:AG,6,0),"-") -> -0.096382864 | X45: =IF(AND(P45=0,V45>0),5,IF(V45/P45>5,5,IF(V45/P45=0,0.0000001,V45/P45))) -> 1.0014199 | Y45: =IFERROR(VLOOKUP(B45,'Факт продаж'!AB:AH,7,0),"-") -> 9.644526 | Z45: =IF(AND(F45=0,V45>0),5,IF(V45/F45>5,5,IF(V45/F45=0,0.0000001,V45/F45))) -> 5 | AB45: =IFERROR(VLOOKUP(VALUE(IF(L45<1,1,0)&IF(J45<'Факт продаж'!$M$24,0,1)),$AB$1:$AC$4,2,FALSE),"НЕТ ПРОДАЖ") -> Звезда | AC45: =IFERROR(VLOOKUP(VALUE(IF(R45<1,1,0)&IF(P45<'Факт продаж'!$V$24,0,1)),$AB$1:$AC$4,2,FALSE),"НЕТ ПРОДАЖ") -> Звезда | AD45: =IFERROR(VLOOKUP(VALUE(IF(X45<1,1,0)&IF(V45<'Факт продаж'!$AE$24,0,1)),$AB$1:$AC$4,2,FALSE),"НЕТ ПРОДАЖ") -> Звезда | AE45: =IFERROR(VLOOKUP(VALUE(IF(Z45<1,1,0)&IF(V45<'Факт продаж'!$AE$24,0,1)),$AB$1:$AC$4,2,FALSE),"НЕТ ПРОДАЖ") -> Звезда | AF45: =VLOOKUP(B45,'ABC расчет'!B:G,6,0) -> B | AG45: =VLOOKUP(B45,'ABC расчет'!K:P,6,0) -> A | AH45: =VLOOKUP(B45,'ABC расчет'!T:Y,6,0) -> A | AI45: =VLOOKUP(B45,'ABC расчет'!AC:AH,6,0) -> A | AJ45: PROMO
A46: МАТРАСЫ | B46: STANDART | C46: =IFERROR(VLOOKUP(B46,'Факт продаж'!A:B,2,0),"нет продаж") -> нет продаж | D46: =IFERROR(VLOOKUP(B46,'Факт продаж'!A:C,3,0),"нет продаж") -> нет продаж | E46: =IFERROR(VLOOKUP(B46,'Факт продаж'!A:E,5,0),"нет продаж") -> нет продаж | F46: =IFERROR(VLOOKUP(B46,'Факт продаж'!A:C,3,0)/SUM('План Антонова'!$C$11:$C$13),0) -> 0 | G46: =IFERROR(VLOOKUP(B46,'Факт продаж'!J:K,2,0),"нет продаж") -> 472 | H46: =IFERROR(VLOOKUP(B46,'Факт продаж'!J:L,3,0),"нет продаж") -> 720263.85 | I46: =IFERROR(VLOOKUP(B46,'Факт продаж'!J:N,5,0),"нет продаж") -> 332301.33 | J46: =IFERROR(VLOOKUP(B46,'Факт продаж'!J:L,3,0)/SUM('План Антонова'!$C$14:$C$16),0) -> 0.0049733212 | K46: =IFERROR(VLOOKUP(B46,'Факт продаж'!J:O,6,0),"-") -> 1 | L46: =IF(AND(F46=0,J46>0),5,IF(J46/F46>5,5,IF(J46/F46=0,0.0000001,J46/F46))) -> 5 | M46: =IFERROR(VLOOKUP(B46,'Факт продаж'!S:T,2,0),"нет продаж") -> 1261 | N46: =IFERROR(VLOOKUP(B46,'Факт продаж'!S:U,3,0),"нет продаж") -> 1817241.9 | O46: =IFERROR(VLOOKUP(B46,'Факт продаж'!S:W,5,0),"нет продаж") -> 761525.35 | P46: =IFERROR(VLOOKUP(B46,'Факт продаж'!S:U,3,0)/SUM('План Антонова'!$C$17:$C$19),0) -> 0.011068912 | Q46: =IFERROR(VLOOKUP(B46,'Факт продаж'!S:X,6,0),"-") -> 1.2916711 | R46: =IF(AND(J46=0,P46>0),5,IF(P46/J46>5,5,IF(P46/J46=0,0.0000001,P46/J46))) -> 2.2256579 | S46: =IFERROR(VLOOKUP(B46,'Факт продаж'!AB:AD,2,0),"нет продаж") -> 1717 | T46: =IFERROR(VLOOKUP(B46,'Факт продаж'!AB:AD,3,0),"нет продаж") -> 2809770.4 | U46: =IFERROR(VLOOKUP(B46,'Факт продаж'!AB:AF,5,0),"нет продаж") -> 857147.6 | V46: =IFERROR(VLOOKUP(B46,'Факт продаж'!AB:AD,3,0)/SUM('План Антонова'!$C$20:$C$22),0) -> 0.018259847 | W46: =IFERROR(VLOOKUP(B46,'Факт продаж'!AB:AG,6,0),"-") -> 0.12556674 | X46: =IF(AND(P46=0,V46>0),5,IF(V46/P46>5,5,IF(V46/P46=0,0.0000001,V46/P46))) -> 1.6496515 | Y46: =IFERROR(VLOOKUP(B46,'Факт продаж'!AB:AH,7,0),"-") -> 1 | Z46: =IF(AND(F46=0,V46>0),5,IF(V46/F46>5,5,IF(V46/F46=0,0.0000001,V46/F46))) -> 5 | AB46: =IFERROR(VLOOKUP(VALUE(IF(L46<1,1,0)&IF(J46<'Факт продаж'!$M$24,0,1)),$AB$1:$AC$4,2,FALSE),"НЕТ ПРОДАЖ") -> Звезда | AC46: =IFERROR(VLOOKUP(VALUE(IF(R46<1,1,0)&IF(P46<'Факт продаж'!$V$24,0,1)),$AB$1:$AC$4,2,FALSE),"НЕТ ПРОДАЖ") -> Звезда | AD46: =IFERROR(VLOOKUP(VALUE(IF(X46<1,1,0)&IF(V46<'Факт продаж'!$AE$24,0,1)),$AB$1:$AC$4,2,FALSE),"НЕТ ПРОДАЖ") -> Звезда | AE46: =IFERROR(VLOOKUP(VALUE(IF(Z46<1,1,0)&IF(V46<'Факт продаж'!$AE$24,0,1)),$AB$1:$AC$4,2,FALSE),"НЕТ ПРОДАЖ") -> Звезда | AF46: =VLOOKUP(B46,'ABC расчет'!B:G,6,0) -> A | AG46: =VLOOKUP(B46,'ABC расчет'!K:P,6,0) -> A | AH46: =VLOOKUP(B46,'ABC расчет'!T:Y,6,0) -> A | AI46: =VLOOKUP(B46,'ABC расчет'!AC:AH,6,0) -> A
A47: КРЕСЛА РУКОВОДИТЕЛЯ | B47: SLIM | C47: =IFERROR(VLOOKUP(B47,'Факт продаж'!A:B,2,0),"нет продаж") -> 181 | D47: =IFERROR(VLOOKUP(B47,'Факт продаж'!A:C,3,0),"нет продаж") -> 525021.34 | E47: =IFERROR(VLOOKUP(B47,'Факт продаж'!A:E,5,0),"нет продаж") -> 190891.92 | F47: =IFERROR(VLOOKUP(B47,'Факт продаж'!A:C,3,0)/SUM('План Антонова'!$C$11:$C$13),0) -> 0.0039865427 | G47: =IFERROR(VLOOKUP(B47,'Факт продаж'!J:K,2,0),"нет продаж") -> 874 | H47: =IFERROR(VLOOKUP(B47,'Факт продаж'!J:L,3,0),"нет продаж") -> 3239244 | I47: =IFERROR(VLOOKUP(B47,'Факт продаж'!J:N,5,0),"нет продаж") -> 1211909.5 | J47: =IFERROR(VLOOKUP(B47,'Факт продаж'!J:L,3,0)/SUM('План Антонова'!$C$14:$C$16),0) -> 0.022366527 | K47: =IFERROR(VLOOKUP(B47,'Факт продаж'!J:O,6,0),"-") -> 5.348668 | L47: =IF(AND(F47=0,J47>0),5,IF(J47/F47>5,5,IF(J47/F47=0,0.0000001,J47/F47))) -> 5 | M47: =IFERROR(VLOOKUP(B47,'Факт продаж'!S:T,2,0),"нет продаж") -> 766 | N47: =IFERROR(VLOOKUP(B47,'Факт продаж'!S:U,3,0),"нет продаж") -> 3015084.9 | O47: =IFERROR(VLOOKUP(B47,'Факт продаж'!S:W,5,0),"нет продаж") -> 996852.63 | P47: =IFERROR(VLOOKUP(B47,'Факт продаж'!S:U,3,0)/SUM('План Антонова'!$C$17:$C$19),0) -> 0.018365034 | Q47: =IFERROR(VLOOKUP(B47,'Факт продаж'!S:X,6,0),"-") -> -0.17745288 | R47: =IF(AND(J47=0,P47>0),5,IF(P47/J47>5,5,IF(P47/J47=0,0.0000001,P47/J47))) -> 0.82109455 | S47: =IFERROR(VLOOKUP(B47,'Факт продаж'!AB:AD,2,0),"нет продаж") -> 560 | T47: =IFERROR(VLOOKUP(B47,'Факт продаж'!AB:AD,3,0),"нет продаж") -> 2235986.6 | U47: =IFERROR(VLOOKUP(B47,'Факт продаж'!AB:AF,5,0),"нет продаж") -> 822153.66 | V47: =IFERROR(VLOOKUP(B47,'Факт продаж'!AB:AD,3,0)/SUM('План Антонова'!$C$20:$C$22),0) -> 0.014531 | W47: =IFERROR(VLOOKUP(B47,'Факт продаж'!AB:AG,6,0),"-") -> -0.17525055 | X47: =IF(AND(P47=0,V47>0),5,IF(V47/P47>5,5,IF(V47/P47=0,0.0000001,V47/P47))) -> 0.79123188 | Y47: =IFERROR(VLOOKUP(B47,'Факт продаж'!AB:AH,7,0),"-") -> 3.3069065 | Z47: =IF(AND(F47=0,V47>0),5,IF(V47/F47>5,5,IF(V47/F47=0,0.0000001,V47/F47))) -> 3.6450131 | AB47: =IFERROR(VLOOKUP(VALUE(IF(L47<1,1,0)&IF(J47<'Факт продаж'!$M$24,0,1)),$AB$1:$AC$4,2,FALSE),"НЕТ ПРОДАЖ") -> Звезда | AC47: =IFERROR(VLOOKUP(VALUE(IF(R47<1,1,0)&IF(P47<'Факт продаж'!$V$24,0,1)),$AB$1:$AC$4,2,FALSE),"НЕТ ПРОДАЖ") -> Корова | AD47: =IFERROR(VLOOKUP(VALUE(IF(X47<1,1,0)&IF(V47<'Факт продаж'!$AE$24,0,1)),$AB$1:$AC$4,2,FALSE),"НЕТ ПРОДАЖ") -> Корова | AE47: =IFERROR(VLOOKUP(VALUE(IF(Z47<1,1,0)&IF(V47<'Факт продаж'!$AE$24,0,1)),$AB$1:$AC$4,2,FALSE),"НЕТ ПРОДАЖ") -> Звезда | AF47: =VLOOKUP(B47,'ABC расчет'!B:G,6,0) -> A | AG47: =VLOOKUP(B47,'ABC расчет'!K:P,6,0) -> A | AH47: =VLOOKUP(B47,'ABC расчет'!T:Y,6,0) -> A | AI47: =VLOOKUP(B47,'ABC расчет'!AC:AH,6,0) -> A | AJ47: PROMO
A48: КРЕСЛА ОПЕРАТОРСКИЕ | B48: PRESTIGE | C48: =IFERROR(VLOOKUP(B48,'Факт продаж'!A:B,2,0),"нет продаж") -> 783 | D48: =IFERROR(VLOOKUP(B48,'Факт продаж'!A:C,3,0),"нет продаж") -> 916268.18 | E48: =IFERROR(VLOOKUP(B48,'Факт продаж'!A:E,5,0),"нет продаж") -> 327904.71 | F48: =IFERROR(VLOOKUP(B48,'Факт продаж'!A:C,3,0)/SUM('План Антонова'!$C$11:$C$13),0) -> 0.0069573214 | G48: =IFERROR(VLOOKUP(B48,'Факт продаж'!J:K,2,0),"нет продаж") -> 316 | H48: =IFERROR(VLOOKUP(B48,'Факт продаж'!J:L,3,0),"нет продаж") -> 519873.7 | I48: =IFERROR(VLOOKUP(B48,'Факт продаж'!J:N,5,0),"нет продаж") -> 236045.19 | J48: =IFERROR(VLOOKUP(B48,'Факт продаж'!J:L,3,0)/SUM('План Антонова'!$C$14:$C$16),0) -> 0.0035896552 | K48: =IFERROR(VLOOKUP(B48,'Факт продаж'!J:O,6,0),"-") -> -0.28014087 | L48: =IF(AND(F48=0,J48>0),5,IF(J48/F48>5,5,IF(J48/F48=0,0.0000001,J48/F48))) -> 0.51595363 | M48: =IFERROR(VLOOKUP(B48,'Факт продаж'!S:T,2,0),"нет продаж") -> 490 | N48: =IFERROR(VLOOKUP(B48,'Факт продаж'!S:U,3,0),"нет продаж") -> 814034.05 | O48: =IFERROR(VLOOKUP(B48,'Факт продаж'!S:W,5,0),"нет продаж") -> 380530.86 | P48: =IFERROR(VLOOKUP(B48,'Факт продаж'!S:U,3,0)/SUM('План Антонова'!$C$17:$C$19),0) -> 0.0049583224 | Q48: =IFERROR(VLOOKUP(B48,'Факт продаж'!S:X,6,0),"-") -> 0.61211016 | R48: =IF(AND(J48=0,P48>0),5,IF(P48/J48>5,5,IF(P48/J48=0,0.0000001,P48/J48))) -> 1.381281 | S48: =IFERROR(VLOOKUP(B48,'Факт продаж'!AB:AD,2,0),"нет продаж") -> 935 | T48: =IFERROR(VLOOKUP(B48,'Факт продаж'!AB:AD,3,0),"нет продаж") -> 1581229.5 | U48: =IFERROR(VLOOKUP(B48,'Факт продаж'!AB:AF,5,0),"нет продаж") -> 739746.67 | V48: =IFERROR(VLOOKUP(B48,'Факт продаж'!AB:AD,3,0)/SUM('План Антонова'!$C$20:$C$22),0) -> 0.010275932 | W48: =IFERROR(VLOOKUP(B48,'Факт продаж'!AB:AG,6,0),"-") -> 0.94398603 | X48: =IF(AND(P48=0,V48>0),5,IF(V48/P48>5,5,IF(V48/P48=0,0.0000001,V48/P48))) -> 2.0724614 | Y48: =IFERROR(VLOOKUP(B48,'Факт продаж'!AB:AH,7,0),"-") -> 1.2559806 | Z48: =IF(AND(F48=0,V48>0),5,IF(V48/F48>5,5,IF(V48/F48=0,0.0000001,V48/F48))) -> 1.4769954 | AB48: =IFERROR(VLOOKUP(VALUE(IF(L48<1,1,0)&IF(J48<'Факт продаж'!$M$24,0,1)),$AB$1:$AC$4,2,FALSE),"НЕТ ПРОДАЖ") -> Корова | AC48: =IFERROR(VLOOKUP(VALUE(IF(R48<1,1,0)&IF(P48<'Факт продаж'!$V$24,0,1)),$AB$1:$AC$4,2,FALSE),"НЕТ ПРОДАЖ") -> Звезда | AD48: =IFERROR(VLOOKUP(VALUE(IF(X48<1,1,0)&IF(V48<'Факт продаж'!$AE$24,0,1)),$AB$1:$AC$4,2,FALSE),"НЕТ ПРОДАЖ") -> Звезда | AE48: =IFERROR(VLOOKUP(VALUE(IF(Z48<1,1,0)&IF(V48<'Факт продаж'!$AE$24,0,1)),$AB$1:$AC$4,2,FALSE),"НЕТ ПРОДАЖ") -> Звезда | AF48: =VLOOKUP(B48,'ABC расчет'!B:G,6,0) -> A | AG48: =VLOOKUP(B48,'ABC расчет'!K:P,6,0) -> B | AH48: =VLOOKUP(B48,'ABC расчет'!T:Y,6,0) -> A | AI48: =VLOOKUP(B48,'ABC расчет'!AC:AH,6,0) -> A
A49: КРЕСЛА ОПЕРАТОРСКИЕ | B49: SAMBA GTP | C49: =IFERROR(VLOOKUP(B49,'Факт продаж'!A:B,2,0),"нет продаж") -> 2 | D49: =IFERROR(VLOOKUP(B49,'Факт продаж'!A:C,3,0),"нет продаж") -> 4923.3993 | E49: =IFERROR(VLOOKUP(B49,'Факт продаж'!A:E,5,0),"нет продаж") -> 2359.2048 | F49: =IFERROR(VLOOKUP(B49,'Факт продаж'!A:C,3,0)/SUM('План Антонова'!$C$11:$C$13),0) -> 3.7383892e-05 | G49: =IFERROR(VLOOKUP(B49,'Факт продаж'!J:K,2,0),"нет продаж") -> 461 | H49: =IFERROR(VLOOKUP(B49,'Факт продаж'!J:L,3,0),"нет продаж") -> 1280554.7 | I49: =IFERROR(VLOOKUP(B49,'Факт продаж'!J:N,5,0),"нет продаж") -> 573760.21 | J49: =IFERROR(VLOOKUP(B49,'Факт продаж'!J:L,3,0)/SUM('План Антонова'!$C$14:$C$16),0) -> 0.0088420512 | K49: =IFERROR(VLOOKUP(B49,'Факт продаж'!J:O,6,0),"-") -> 242.20068 | L49: =IF(AND(F49=0,J49>0),5,IF(J49/F49>5,5,IF(J49/F49=0,0.0000001,J49/F49))) -> 5 | M49: =IFERROR(VLOOKUP(B49,'Факт продаж'!S:T,2,0),"нет продаж") -> 717 | N49: =IFERROR(VLOOKUP(B49,'Факт продаж'!S:U,3,0),"нет продаж") -> 1963688.3 | O49: =IFERROR(VLOOKUP(B49,'Факт продаж'!S:W,5,0),"нет продаж") -> 813674.85 | P49: =IFERROR(VLOOKUP(B49,'Факт продаж'!S:U,3,0)/SUM('План Антонова'!$C$17:$C$19),0) -> 0.011960924 | Q49: =IFERROR(VLOOKUP(B49,'Факт продаж'!S:X,6,0),"-") -> 0.41814443 | R49: =IF(AND(J49=0,P49>0),5,IF(P49/J49>5,5,IF(P49/J49=0,0.0000001,P49/J49))) -> 1.3527319 | S49: =IFERROR(VLOOKUP(B49,'Факт продаж'!AB:AD,2,0),"нет продаж") -> 550 | T49: =IFERROR(VLOOKUP(B49,'Факт продаж'!AB:AD,3,0),"нет продаж") -> 1559975.2 | U49: =IFERROR(VLOOKUP(B49,'Факт продаж'!AB:AF,5,0),"нет продаж") -> 666581.76 | V49: =IFERROR(VLOOKUP(B49,'Факт продаж'!AB:AD,3,0)/SUM('План Антонова'!$C$20:$C$22),0) -> 0.010137806 | W49: =IFERROR(VLOOKUP(B49,'Факт продаж'!AB:AG,6,0),"-") -> -0.18077625 | X49: =IF(AND(P49=0,V49>0),5,IF(V49/P49>5,5,IF(V49/P49=0,0.0000001,V49/P49))) -> 0.84757718 | Y49: =IFERROR(VLOOKUP(B49,'Факт продаж'!AB:AH,7,0),"-") -> 281.54511 | Z49: =IF(AND(F49=0,V49>0),5,IF(V49/F49>5,5,IF(V49/F49=0,0.0000001,V49/F49))) -> 5 | AB49: =IFERROR(VLOOKUP(VALUE(IF(L49<1,1,0)&IF(J49<'Факт продаж'!$M$24,0,1)),$AB$1:$AC$4,2,FALSE),"НЕТ ПРОДАЖ") -> Звезда | AC49: =IFERROR(VLOOKUP(VALUE(IF(R49<1,1,0)&IF(P49<'Факт продаж'!$V$24,0,1)),$AB$1:$AC$4,2,FALSE),"НЕТ ПРОДАЖ") -> Звезда | AD49: =IFERROR(VLOOKUP(VALUE(IF(X49<1,1,0)&IF(V49<'Факт продаж'!$AE$24,0,1)),$AB$1:$AC$4,2,FALSE),"НЕТ ПРОДАЖ") -> Корова | AE49: =IFERROR(VLOOKUP(VALUE(IF(Z49<1,1,0)&IF(V49<'Факт продаж'!$AE$24,0,1)),$AB$1:$AC$4,2,FALSE),"НЕТ ПРОДАЖ") -> Звезда | AF49: =VLOOKUP(B49,'ABC расчет'!B:G,6,0) -> C | AG49: =VLOOKUP(B49,'ABC расчет'!K:P,6,0) -> A | AH49: =VLOOKUP(B49,'ABC расчет'!T:Y,6,0) -> A | AI49: =VLOOKUP(B49,'ABC расчет'!AC:AH,6,0) -> A
A50: КРЕСЛА/СТУЛЬЯ ОБЕДЕННЫЕ | B50: JACK | C50: =IFERROR(VLOOKUP(B50,'Факт продаж'!A:B,2,0),"нет продаж") -> 614 | D50: =IFERROR(VLOOKUP(B50,'Факт продаж'!A:C,3,0),"нет продаж") -> 317577.58 | E50: =IFERROR(VLOOKUP(B50,'Факт продаж'!A:E,5,0),"нет продаж") -> 135483.96 | F50: =IFERROR(VLOOKUP(B50,'Факт продаж'!A:C,3,0)/SUM('План Антонова'!$C$11:$C$13),0) -> 0.0024114002 | G50: =IFERROR(VLOOKUP(B50,'Факт продаж'!J:K,2,0),"нет продаж") -> 2566 | H50: =IFERROR(VLOOKUP(B50,'Факт продаж'!J:L,3,0),"нет продаж") -> 1393994.3 | I50: =IFERROR(VLOOKUP(B50,'Факт продаж'!J:N,5,0),"нет продаж") -> 458315.53 | J50: =IFERROR(VLOOKUP(B50,'Факт продаж'!J:L,3,0)/SUM('План Антонова'!$C$14:$C$16),0) -> 0.0096253358 | K50: =IFERROR(VLOOKUP(B50,'Факт продаж'!J:O,6,0),"-") -> 2.3828028 | L50: =IF(AND(F50=0,J50>0),5,IF(J50/F50>5,5,IF(J50/F50=0,0.0000001,J50/F50))) -> 3.9915961 | M50: =IFERROR(VLOOKUP(B50,'Факт продаж'!S:T,2,0),"нет продаж") -> 3233 | N50: =IFERROR(VLOOKUP(B50,'Факт продаж'!S:U,3,0),"нет продаж") -> 1771134.2 | O50: =IFERROR(VLOOKUP(B50,'Факт продаж'!S:W,5,0),"нет продаж") -> 568008.41 | P50: =IFERROR(VLOOKUP(B50,'Факт продаж'!S:U,3,0)/SUM('План Антонова'!$C$17:$C$19),0) -> 0.010788068 | Q50: =IFERROR(VLOOKUP(B50,'Факт продаж'!S:X,6,0),"-") -> 0.23933923 | R50: =IF(AND(J50=0,P50>0),5,IF(P50/J50>5,5,IF(P50/J50=0,0.0000001,P50/J50))) -> 1.1207991 | S50: =IFERROR(VLOOKUP(B50,'Факт продаж'!AB:AD,2,0),"нет продаж") -> 3796 | T50: =IFERROR(VLOOKUP(B50,'Факт продаж'!AB:AD,3,0),"нет продаж") -> 2126404.5 | U50: =IFERROR(VLOOKUP(B50,'Факт продаж'!AB:AF,5,0),"нет продаж") -> 663921.9 | V50: =IFERROR(VLOOKUP(B50,'Факт продаж'!AB:AD,3,0)/SUM('План Антонова'!$C$20:$C$22),0) -> 0.013818859 | W50: =IFERROR(VLOOKUP(B50,'Факт продаж'!AB:AG,6,0),"-") -> 0.16885928 | X50: =IF(AND(P50=0,V50>0),5,IF(V50/P50>5,5,IF(V50/P50=0,0.0000001,V50/P50))) -> 1.2809393 | Y50: =IFERROR(VLOOKUP(B50,'Факт продаж'!AB:AH,7,0),"-") -> 3.9003727 | Z50: =IF(AND(F50=0,V50>0),5,IF(V50/F50>5,5,IF(V50/F50=0,0.0000001,V50/F50))) -> 5 | AB50: =IFERROR(VLOOKUP(VALUE(IF(L50<1,1,0)&IF(J50<'Факт продаж'!$M$24,0,1)),$AB$1:$AC$4,2,FALSE),"НЕТ ПРОДАЖ") -> Звезда | AC50: =IFERROR(VLOOKUP(VALUE(IF(R50<1,1,0)&IF(P50<'Факт продаж'!$V$24,0,1)),$AB$1:$AC$4,2,FALSE),"НЕТ ПРОДАЖ") -> Звезда | AD50: =IFERROR(VLOOKUP(VALUE(IF(X50<1,1,0)&IF(V50<'Факт продаж'!$AE$24,0,1)),$AB$1:$AC$4,2,FALSE),"НЕТ ПРОДАЖ") -> Звезда | AE50: =IFERROR(VLOOKUP(VALUE(IF(Z50<1,1,0)&IF(V50<'Факт продаж'!$AE$24,0,1)),$AB$1:$AC$4,2,FALSE),"НЕТ ПРОДАЖ") -> Звезда | AF50: =VLOOKUP(B50,'ABC расчет'!B:G,6,0) -> A | AG50: =VLOOKUP(B50,'ABC расчет'!K:P,6,0) -> A | AH50: =VLOOKUP(B50,'ABC расчет'!T:Y,6,0) -> A | AI50: =VLOOKUP(B50,'ABC расчет'!AC:AH,6,0) -> A
A51: КРЕСЛА/СТУЛЬЯ ОБЕДЕННЫЕ | B51: TEDDY | C51: =IFERROR(VLOOKUP(B51,'Факт продаж'!A:B,2,0),"нет продаж") -> 428 | D51: =IFERROR(VLOOKUP(B51,'Факт продаж'!A:C,3,0),"нет продаж") -> 136076.88 | E51: =IFERROR(VLOOKUP(B51,'Факт продаж'!A:E,5,0),"нет продаж") -> 52789.886 | F51: =IFERROR(VLOOKUP(B51,'Факт продаж'!A:C,3,0)/SUM('План Антонова'!$C$11:$C$13),0) -> 0.0010332462 | G51: =IFERROR(VLOOKUP(B51,'Факт продаж'!J:K,2,0),"нет продаж") -> 3580 | H51: =IFERROR(VLOOKUP(B51,'Факт продаж'!J:L,3,0),"нет продаж") -> 1304067.7 | I51: =IFERROR(VLOOKUP(B51,'Факт продаж'!J:N,5,0),"нет продаж") -> 620170.09 | J51: =IFERROR(VLOOKUP(B51,'Факт продаж'!J:L,3,0)/SUM('План Антонова'!$C$14:$C$16),0) -> 0.0090044051 | K51: =IFERROR(VLOOKUP(B51,'Факт продаж'!J:O,6,0),"-") -> 10.747896 | L51: =IF(AND(F51=0,J51>0),5,IF(J51/F51>5,5,IF(J51/F51=0,0.0000001,J51/F51))) -> 5 | M51: =IFERROR(VLOOKUP(B51,'Факт продаж'!S:T,2,0),"нет продаж") -> 2538 | N51: =IFERROR(VLOOKUP(B51,'Факт продаж'!S:U,3,0),"нет продаж") -> 1012892 | O51: =IFERROR(VLOOKUP(B51,'Факт продаж'!S:W,5,0),"нет продаж") -> 495487.46 | P51: =IFERROR(VLOOKUP(B51,'Факт продаж'!S:U,3,0)/SUM('План Антонова'!$C$17:$C$19),0) -> 0.0061695761 | Q51: =IFERROR(VLOOKUP(B51,'Факт продаж'!S:X,6,0),"-") -> -0.20104586 | R51: =IF(AND(J51=0,P51>0),5,IF(P51/J51>5,5,IF(P51/J51=0,0.0000001,P51/J51))) -> 0.6851731 | S51: =IFERROR(VLOOKUP(B51,'Факт продаж'!AB:AD,2,0),"нет продаж") -> 3336 | T51: =IFERROR(VLOOKUP(B51,'Факт продаж'!AB:AD,3,0),"нет продаж") -> 1386535.2 | U51: =IFERROR(VLOOKUP(B51,'Факт продаж'!AB:AF,5,0),"нет продаж") -> 640505.29 | V51: =IFERROR(VLOOKUP(B51,'Факт продаж'!AB:AD,3,0)/SUM('План Антонова'!$C$20:$C$22),0) -> 0.0090106721 | W51: =IFERROR(VLOOKUP(B51,'Факт продаж'!AB:AG,6,0),"-") -> 0.2926771 | X51: =IF(AND(P51=0,V51>0),5,IF(V51/P51>5,5,IF(V51/P51=0,0.0000001,V51/P51))) -> 1.460501 | Y51: =IFERROR(VLOOKUP(B51,'Факт продаж'!AB:AH,7,0),"-") -> 11.133106 | Z51: =IF(AND(F51=0,V51>0),5,IF(V51/F51>5,5,IF(V51/F51=0,0.0000001,V51/F51))) -> 5 | AB51: =IFERROR(VLOOKUP(VALUE(IF(L51<1,1,0)&IF(J51<'Факт продаж'!$M$24,0,1)),$AB$1:$AC$4,2,FALSE),"НЕТ ПРОДАЖ") -> Звезда | AC51: =IFERROR(VLOOKUP(VALUE(IF(R51<1,1,0)&IF(P51<'Факт продаж'!$V$24,0,1)),$AB$1:$AC$4,2,FALSE),"НЕТ ПРОДАЖ") -> Корова | AD51: =IFERROR(VLOOKUP(VALUE(IF(X51<1,1,0)&IF(V51<'Факт продаж'!$AE$24,0,1)),$AB$1:$AC$4,2,FALSE),"НЕТ ПРОДАЖ") -> Звезда | AE51: =IFERROR(VLOOKUP(VALUE(IF(Z51<1,1,0)&IF(V51<'Факт продаж'!$AE$24,0,1)),$AB$1:$AC$4,2,FALSE),"НЕТ ПРОДАЖ") -> Звезда | AF51: =VLOOKUP(B51,'ABC расчет'!B:G,6,0) -> A | AG51: =VLOOKUP(B51,'ABC расчет'!K:P,6,0) -> A | AH51: =VLOOKUP(B51,'ABC расчет'!T:Y,6,0) -> A | AI51: =VLOOKUP(B51,'ABC расчет'!AC:AH,6,0) -> A
A52: КРЕСЛА И СТУЛЬЯ СПЕЦИАЛЬНЫЕ | B52: LABORANT | C52: =IFERROR(VLOOKUP(B52,'Факт продаж'!A:B,2,0),"нет продаж") -> 162 | D52: =IFERROR(VLOOKUP(B52,'Факт продаж'!A:C,3,0),"нет продаж") -> 467913.76 | E52: =IFERROR(VLOOKUP(B52,'Факт продаж'!A:E,5,0),"нет продаж") -> 108065.57 | F52: =IFERROR(VLOOKUP(B52,'Факт продаж'!A:C,3,0)/SUM('План Антонова'!$C$11:$C$13),0) -> 0.0035529187 | G52: =IFERROR(VLOOKUP(B52,'Факт продаж'!J:K,2,0),"нет продаж") -> 341 | H52: =IFERROR(VLOOKUP(B52,'Факт продаж'!J:L,3,0),"нет продаж") -> 1352925.1 | I52: =IFERROR(VLOOKUP(B52,'Факт продаж'!J:N,5,0),"нет продаж") -> 541662.72 | J52: =IFERROR(VLOOKUP(B52,'Факт продаж'!J:L,3,0)/SUM('План Антонова'!$C$14:$C$16),0) -> 0.0093417584 | K52: =IFERROR(VLOOKUP(B52,'Факт продаж'!J:O,6,0),"-") -> 4.0123526 | L52: =IF(AND(F52=0,J52>0),5,IF(J52/F52>5,5,IF(J52/F52=0,0.0000001,J52/F52))) -> 2.6293195 | M52: =IFERROR(VLOOKUP(B52,'Факт продаж'!S:T,2,0),"нет продаж") -> 245 | N52: =IFERROR(VLOOKUP(B52,'Факт продаж'!S:U,3,0),"нет продаж") -> 1034041.6 | O52: =IFERROR(VLOOKUP(B52,'Факт продаж'!S:W,5,0),"нет продаж") -> 421255.03 | P52: =IFERROR(VLOOKUP(B52,'Факт продаж'!S:U,3,0)/SUM('План Антонова'!$C$17:$C$19),0) -> 0.0062983993 | Q52: =IFERROR(VLOOKUP(B52,'Факт продаж'!S:X,6,0),"-") -> -0.22229274 | R52: =IF(AND(J52=0,P52>0),5,IF(P52/J52>5,5,IF(P52/J52=0,0.0000001,P52/J52))) -> 0.67421989 | S52: =IFERROR(VLOOKUP(B52,'Факт продаж'!AB:AD,2,0),"нет продаж") -> 316 | T52: =IFERROR(VLOOKUP(B52,'Факт продаж'!AB:AD,3,0),"нет продаж") -> 1356730.1 | U52: =IFERROR(VLOOKUP(B52,'Факт продаж'!AB:AF,5,0),"нет продаж") -> 636057.72 | V52: =IFERROR(VLOOKUP(B52,'Факт продаж'!AB:AD,3,0)/SUM('План Антонова'!$C$20:$C$22),0) -> 0.0088169778 | W52: =IFERROR(VLOOKUP(B52,'Факт продаж'!AB:AG,6,0),"-") -> 0.50991127 | X52: =IF(AND(P52=0,V52>0),5,IF(V52/P52>5,5,IF(V52/P52=0,0.0000001,V52/P52))) -> 1.399876 | Y52: =IFERROR(VLOOKUP(B52,'Факт продаж'!AB:AH,7,0),"-") -> 4.88585 | Z52: =IF(AND(F52=0,V52>0),5,IF(V52/F52>5,5,IF(V52/F52=0,0.0000001,V52/F52))) -> 2.4816154 | AB52: =IFERROR(VLOOKUP(VALUE(IF(L52<1,1,0)&IF(J52<'Факт продаж'!$M$24,0,1)),$AB$1:$AC$4,2,FALSE),"НЕТ ПРОДАЖ") -> Звезда | AC52: =IFERROR(VLOOKUP(VALUE(IF(R52<1,1,0)&IF(P52<'Факт продаж'!$V$24,0,1)),$AB$1:$AC$4,2,FALSE),"НЕТ ПРОДАЖ") -> Корова | AD52: =IFERROR(VLOOKUP(VALUE(IF(X52<1,1,0)&IF(V52<'Факт продаж'!$AE$24,0,1)),$AB$1:$AC$4,2,FALSE),"НЕТ ПРОДАЖ") -> Звезда | AE52: =IFERROR(VLOOKUP(VALUE(IF(Z52<1,1,0)&IF(V52<'Факт продаж'!$AE$24,0,1)),$AB$1:$AC$4,2,FALSE),"НЕТ ПРОДАЖ") -> Звезда | AF52: =VLOOKUP(B52,'ABC расчет'!B:G,6,0) -> A | AG52: =VLOOKUP(B52,'ABC расчет'!K:P,6,0) -> A | AH52: =VLOOKUP(B52,'ABC расчет'!T:Y,6,0) -> A | AI52: =VLOOKUP(B52,'ABC расчет'!AC:AH,6,0) -> A
A53: СТУЛЬЯ ПОСЕТИТЕЛЬСКИЕ | B53: TASK | C53: =IFERROR(VLOOKUP(B53,'Факт продаж'!A:B,2,0),"нет продаж") -> 359 | D53: =IFERROR(VLOOKUP(B53,'Факт продаж'!A:C,3,0),"нет продаж") -> 603712.93 | E53: =IFERROR(VLOOKUP(B53,'Факт продаж'!A:E,5,0),"нет продаж") -> 288008.46 | F53: =IFERROR(VLOOKUP(B53,'Факт продаж'!A:C,3,0)/SUM('План Антонова'!$C$11:$C$13),0) -> 0.0045840562 | G53: =IFERROR(VLOOKUP(B53,'Факт продаж'!J:K,2,0),"нет продаж") -> 662 | H53: =IFERROR(VLOOKUP(B53,'Факт продаж'!J:L,3,0),"нет продаж") -> 1439290.3 | I53: =IFERROR(VLOOKUP(B53,'Факт продаж'!J:N,5,0),"нет продаж") -> 682750.65 | J53: =IFERROR(VLOOKUP(B53,'Факт продаж'!J:L,3,0)/SUM('План Антонова'!$C$14:$C$16),0) -> 0.009938098 | K53: =IFERROR(VLOOKUP(B53,'Факт продаж'!J:O,6,0),"-") -> 1.3705924 | L53: =IF(AND(F53=0,J53>0),5,IF(J53/F53>5,5,IF(J53/F53=0,0.0000001,J53/F53))) -> 2.1679704 | M53: =IFERROR(VLOOKUP(B53,'Факт продаж'!S:T,2,0),"нет продаж") -> 346 | N53: =IFERROR(VLOOKUP(B53,'Факт продаж'!S:U,3,0),"нет продаж") -> 781166.05 | O53: =IFERROR(VLOOKUP(B53,'Факт продаж'!S:W,5,0),"нет продаж") -> 363617.36 | P53: =IFERROR(VLOOKUP(B53,'Факт продаж'!S:U,3,0)/SUM('План Антонова'!$C$17:$C$19),0) -> 0.0047581218 | Q53: =IFERROR(VLOOKUP(B53,'Факт продаж'!S:X,6,0),"-") -> -0.46742291 | R53: =IF(AND(J53=0,P53>0),5,IF(P53/J53>5,5,IF(P53/J53=0,0.0000001,P53/J53))) -> 0.47877589 | S53: =IFERROR(VLOOKUP(B53,'Факт продаж'!AB:AD,2,0),"нет продаж") -> 583 | T53: =IFERROR(VLOOKUP(B53,'Факт продаж'!AB:AD,3,0),"нет продаж") -> 1355705.1 | U53: =IFERROR(VLOOKUP(B53,'Факт продаж'!AB:AF,5,0),"нет продаж") -> 635269.88 | V53: =IFERROR(VLOOKUP(B53,'Факт продаж'!AB:AD,3,0)/SUM('План Антонова'!$C$20:$C$22),0) -> 0.0088103172 | W53: =IFERROR(VLOOKUP(B53,'Факт продаж'!AB:AG,6,0),"-") -> 0.74708346 | X53: =IF(AND(P53=0,V53>0),5,IF(V53/P53>5,5,IF(V53/P53=0,0.0000001,V53/P53))) -> 1.8516376 | Y53: =IFERROR(VLOOKUP(B53,'Факт продаж'!AB:AH,7,0),"-") -> 1.2057334 | Z53: =IF(AND(F53=0,V53>0),5,IF(V53/F53>5,5,IF(V53/F53=0,0.0000001,V53/F53))) -> 1.9219479 | AB53: =IFERROR(VLOOKUP(VALUE(IF(L53<1,1,0)&IF(J53<'Факт продаж'!$M$24,0,1)),$AB$1:$AC$4,2,FALSE),"НЕТ ПРОДАЖ") -> Звезда | AC53: =IFERROR(VLOOKUP(VALUE(IF(R53<1,1,0)&IF(P53<'Факт продаж'!$V$24,0,1)),$AB$1:$AC$4,2,FALSE),"НЕТ ПРОДАЖ") -> Корова | AD53: =IFERROR(VLOOKUP(VALUE(IF(X53<1,1,0)&IF(V53<'Факт продаж'!$AE$24,0,1)),$AB$1:$AC$4,2,FALSE),"НЕТ ПРОДАЖ") -> Звезда | AE53: =IFERROR(VLOOKUP(VALUE(IF(Z53<1,1,0)&IF(V53<'Факт продаж'!$AE$24,0,1)),$AB$1:$AC$4,2,FALSE),"НЕТ ПРОДАЖ") -> Звезда | AF53: =VLOOKUP(B53,'ABC расчет'!B:G,6,0) -> B | AG53: =VLOOKUP(B53,'ABC расчет'!K:P,6,0) -> B | AH53: =VLOOKUP(B53,'ABC расчет'!T:Y,6,0) -> B | AI53: =VLOOKUP(B53,'ABC расчет'!AC:AH,6,0) -> B
A54: КРЕСЛА РУКОВОДИТЕЛЯ | B54: DIPLOMAT | C54: =IFERROR(VLOOKUP(B54,'Факт продаж'!A:B,2,0),"нет продаж") -> 257 | D54: =IFERROR(VLOOKUP(B54,'Факт продаж'!A:C,3,0),"нет продаж") -> 519969.63 | E54: =IFERROR(VLOOKUP(B54,'Факт продаж'!A:E,5,0),"нет продаж") -> 221798.98 | F54: =IFERROR(VLOOKUP(B54,'Факт продаж'!A:C,3,0)/SUM('План Антонова'!$C$11:$C$13),0) -> 0.0039481845 | G54: =IFERROR(VLOOKUP(B54,'Факт продаж'!J:K,2,0),"нет продаж") -> 737 | H54: =IFERROR(VLOOKUP(B54,'Факт продаж'!J:L,3,0),"нет продаж") -> 1850810.9 | I54: =IFERROR(VLOOKUP(B54,'Факт продаж'!J:N,5,0),"нет продаж") -> 818359.36 | J54: =IFERROR(VLOOKUP(B54,'Факт продаж'!J:L,3,0)/SUM('План Антонова'!$C$14:$C$16),0) -> 0.012779591 | K54: =IFERROR(VLOOKUP(B54,'Факт продаж'!J:O,6,0),"-") -> 2.6896444 | L54: =IF(AND(F54=0,J54>0),5,IF(J54/F54>5,5,IF(J54/F54=0,0.0000001,J54/F54))) -> 3.2368271 | M54: =IFERROR(VLOOKUP(B54,'Факт продаж'!S:T,2,0),"нет продаж") -> 670 | N54: =IFERROR(VLOOKUP(B54,'Факт продаж'!S:U,3,0),"нет продаж") -> 1812266.2 | O54: =IFERROR(VLOOKUP(B54,'Факт продаж'!S:W,5,0),"нет продаж") -> 689501.83 | P54: =IFERROR(VLOOKUP(B54,'Факт продаж'!S:U,3,0)/SUM('План Антонова'!$C$17:$C$19),0) -> 0.011038604 | Q54: =IFERROR(VLOOKUP(B54,'Факт продаж'!S:X,6,0),"-") -> -0.15745837 | R54: =IF(AND(J54=0,P54>0),5,IF(P54/J54>5,5,IF(P54/J54=0,0.0000001,P54/J54))) -> 0.86376824 | S54: =IFERROR(VLOOKUP(B54,'Факт продаж'!AB:AD,2,0),"нет продаж") -> 509 | T54: =IFERROR(VLOOKUP(B54,'Факт продаж'!AB:AD,3,0),"нет продаж") -> 1469124.9 | U54: =IFERROR(VLOOKUP(B54,'Факт продаж'!AB:AF,5,0),"нет продаж") -> 624653.37 | V54: =IFERROR(VLOOKUP(B54,'Факт продаж'!AB:AD,3,0)/SUM('План Антонова'!$C$20:$C$22),0) -> 0.009547398 | W54: =IFERROR(VLOOKUP(B54,'Факт продаж'!AB:AG,6,0),"-") -> -0.094051177 | X54: =IF(AND(P54=0,V54>0),5,IF(V54/P54>5,5,IF(V54/P54=0,0.0000001,V54/P54))) -> 0.86490988 | Y54: =IFERROR(VLOOKUP(B54,'Факт продаж'!AB:AH,7,0),"-") -> 1.816304 | Z54: =IF(AND(F54=0,V54>0),5,IF(V54/F54>5,5,IF(V54/F54=0,0.0000001,V54/F54))) -> 2.4181743 | AB54: =IFERROR(VLOOKUP(VALUE(IF(L54<1,1,0)&IF(J54<'Факт продаж'!$M$24,0,1)),$AB$1:$AC$4,2,FALSE),"НЕТ ПРОДАЖ") -> Звезда | AC54: =IFERROR(VLOOKUP(VALUE(IF(R54<1,1,0)&IF(P54<'Факт продаж'!$V$24,0,1)),$AB$1:$AC$4,2,FALSE),"НЕТ ПРОДАЖ") -> Корова | AD54: =IFERROR(VLOOKUP(VALUE(IF(X54<1,1,0)&IF(V54<'Факт продаж'!$AE$24,0,1)),$AB$1:$AC$4,2,FALSE),"НЕТ ПРОДАЖ") -> Корова | AE54: =IFERROR(VLOOKUP(VALUE(IF(Z54<1,1,0)&IF(V54<'Факт продаж'!$AE$24,0,1)),$AB$1:$AC$4,2,FALSE),"НЕТ ПРОДАЖ") -> Звезда | AF54: =VLOOKUP(B54,'ABC расчет'!B:G,6,0) -> A | AG54: =VLOOKUP(B54,'ABC расчет'!K:P,6,0) -> A | AH54: =VLOOKUP(B54,'ABC расчет'!T:Y,6,0) -> A | AI54: =VLOOKUP(B54,'ABC расчет'!AC:AH,6,0) -> A
A55: ВЕШАЛКИ НАПОЛЬНЫЕ | B55: VENEZIA | C55: =IFERROR(VLOOKUP(B55,'Факт продаж'!A:B,2,0),"нет продаж") -> 270 | D55: =IFERROR(VLOOKUP(B55,'Факт продаж'!A:C,3,0),"нет продаж") -> 326781.97 | E55: =IFERROR(VLOOKUP(B55,'Факт продаж'!A:E,5,0),"нет продаж") -> 179145.26 | F55: =IFERROR(VLOOKUP(B55,'Факт продаж'!A:C,3,0)/SUM('План Антонова'!$C$11:$C$13),0) -> 0.0024812901 | G55: =IFERROR(VLOOKUP(B55,'Факт продаж'!J:K,2,0),"нет продаж") -> 222 | H55: =IFERROR(VLOOKUP(B55,'Факт продаж'!J:L,3,0),"нет продаж") -> 299870.45 | I55: =IFERROR(VLOOKUP(B55,'Факт продаж'!J:N,5,0),"нет продаж") -> 140528.35 | J55: =IFERROR(VLOOKUP(B55,'Факт продаж'!J:L,3,0)/SUM('План Антонова'!$C$14:$C$16),0) -> 0.0020705635 | K55: =IFERROR(VLOOKUP(B55,'Факт продаж'!J:O,6,0),"-") -> -0.21556199 | L55: =IF(AND(F55=0,J55>0),5,IF(J55/F55>5,5,IF(J55/F55=0,0.0000001,J55/F55))) -> 0.83447055 | M55: =IFERROR(VLOOKUP(B55,'Факт продаж'!S:T,2,0),"нет продаж") -> 374 | N55: =IFERROR(VLOOKUP(B55,'Факт продаж'!S:U,3,0),"нет продаж") -> 568407.57 | O55: =IFERROR(VLOOKUP(B55,'Факт продаж'!S:W,5,0),"нет продаж") -> 241582.89 | P55: =IFERROR(VLOOKUP(B55,'Факт продаж'!S:U,3,0)/SUM('План Антонова'!$C$17:$C$19),0) -> 0.0034621991 | Q55: =IFERROR(VLOOKUP(B55,'Факт продаж'!S:X,6,0),"-") -> 0.71910427 | R55: =IF(AND(J55=0,P55>0),5,IF(P55/J55>5,5,IF(P55/J55=0,0.0000001,P55/J55))) -> 1.6721048 | S55: =IFERROR(VLOOKUP(B55,'Факт продаж'!AB:AD,2,0),"нет продаж") -> 873 | T55: =IFERROR(VLOOKUP(B55,'Факт продаж'!AB:AD,3,0),"нет продаж") -> 1392798.6 | U55: =IFERROR(VLOOKUP(B55,'Факт продаж'!AB:AF,5,0),"нет продаж") -> 621386.01 | V55: =IFERROR(VLOOKUP(B55,'Факт продаж'!AB:AD,3,0)/SUM('План Антонова'!$C$20:$C$22),0) -> 0.0090513764 | W55: =IFERROR(VLOOKUP(B55,'Факт продаж'!AB:AG,6,0),"-") -> 1.5721441 | X55: =IF(AND(P55=0,V55>0),5,IF(V55/P55>5,5,IF(V55/P55=0,0.0000001,V55/P55))) -> 2.6143431 | Y55: =IFERROR(VLOOKUP(B55,'Факт продаж'!AB:AH,7,0),"-") -> 2.4686154 | Z55: =IF(AND(F55=0,V55>0),5,IF(V55/F55>5,5,IF(V55/F55=0,0.0000001,V55/F55))) -> 3.6478509 | AB55: =IFERROR(VLOOKUP(VALUE(IF(L55<1,1,0)&IF(J55<'Факт продаж'!$M$24,0,1)),$AB$1:$AC$4,2,FALSE),"НЕТ ПРОДАЖ") -> Корова | AC55: =IFERROR(VLOOKUP(VALUE(IF(R55<1,1,0)&IF(P55<'Факт продаж'!$V$24,0,1)),$AB$1:$AC$4,2,FALSE),"НЕТ ПРОДАЖ") -> Звезда | AD55: =IFERROR(VLOOKUP(VALUE(IF(X55<1,1,0)&IF(V55<'Факт продаж'!$AE$24,0,1)),$AB$1:$AC$4,2,FALSE),"НЕТ ПРОДАЖ") -> Звезда | AE55: =IFERROR(VLOOKUP(VALUE(IF(Z55<1,1,0)&IF(V55<'Факт продаж'!$AE$24,0,1)),$AB$1:$AC$4,2,FALSE),"НЕТ ПРОДАЖ") -> Звезда | AF55: =VLOOKUP(B55,'ABC расчет'!B:G,6,0) -> A | AG55: =VLOOKUP(B55,'ABC расчет'!K:P,6,0) -> A | AH55: =VLOOKUP(B55,'ABC расчет'!T:Y,6,0) -> A | AI55: =VLOOKUP(B55,'ABC расчет'!AC:AH,6,0) -> A
A56: КРЕСЛА/СТУЛЬЯ ОБЕДЕННЫЕ | B56: MARCO | C56: =IFERROR(VLOOKUP(B56,'Факт продаж'!A:B,2,0),"нет продаж") -> 575 | D56: =IFERROR(VLOOKUP(B56,'Факт продаж'!A:C,3,0),"нет продаж") -> 387600.87 | E56: =IFERROR(VLOOKUP(B56,'Факт продаж'!A:E,5,0),"нет продаж") -> 191890.02 | F56: =IFERROR(VLOOKUP(B56,'Факт продаж'!A:C,3,0)/SUM('План Антонова'!$C$11:$C$13),0) -> 0.0029430944 | G56: =IFERROR(VLOOKUP(B56,'Факт продаж'!J:K,2,0),"нет продаж") -> 1935 | H56: =IFERROR(VLOOKUP(B56,'Факт продаж'!J:L,3,0),"нет продаж") -> 1332860.5 | I56: =IFERROR(VLOOKUP(B56,'Факт продаж'!J:N,5,0),"нет продаж") -> 628428.96 | J56: =IFERROR(VLOOKUP(B56,'Факт продаж'!J:L,3,0)/SUM('План Антонова'!$C$14:$C$16),0) -> 0.0092032156 | K56: =IFERROR(VLOOKUP(B56,'Факт продаж'!J:O,6,0),"-") -> 2.2749434 | L56: =IF(AND(F56=0,J56>0),5,IF(J56/F56>5,5,IF(J56/F56=0,0.0000001,J56/F56))) -> 3.1270541 | M56: =IFERROR(VLOOKUP(B56,'Факт продаж'!S:T,2,0),"нет продаж") -> 2571 | N56: =IFERROR(VLOOKUP(B56,'Факт продаж'!S:U,3,0),"нет продаж") -> 1749246.8 | O56: =IFERROR(VLOOKUP(B56,'Факт продаж'!S:W,5,0),"нет продаж") -> 790631.7 | P56: =IFERROR(VLOOKUP(B56,'Факт продаж'!S:U,3,0)/SUM('План Антонова'!$C$17:$C$19),0) -> 0.010654751 | Q56: =IFERROR(VLOOKUP(B56,'Факт продаж'!S:X,6,0),"-") -> 0.25810831 | R56: =IF(AND(J56=0,P56>0),5,IF(P56/J56>5,5,IF(P56/J56=0,0.0000001,P56/J56))) -> 1.1577204 | S56: =IFERROR(VLOOKUP(B56,'Факт продаж'!AB:AD,2,0),"нет продаж") -> 1773 | T56: =IFERROR(VLOOKUP(B56,'Факт продаж'!AB:AD,3,0),"нет продаж") -> 1303100.4 | U56: =IFERROR(VLOOKUP(B56,'Факт продаж'!AB:AF,5,0),"нет продаж") -> 590609.34 | V56: =IFERROR(VLOOKUP(B56,'Факт продаж'!AB:AD,3,0)/SUM('План Антонова'!$C$20:$C$22),0) -> 0.0084684552 | W56: =IFERROR(VLOOKUP(B56,'Факт продаж'!AB:AG,6,0),"-") -> -0.25299057 | X56: =IF(AND(P56=0,V56>0),5,IF(V56/P56>5,5,IF(V56/P56=0,0.0000001,V56/P56))) -> 0.79480558 | Y56: =IFERROR(VLOOKUP(B56,'Факт продаж'!AB:AH,7,0),"-") -> 2.0778533 | Z56: =IF(AND(F56=0,V56>0),5,IF(V56/F56>5,5,IF(V56/F56=0,0.0000001,V56/F56))) -> 2.8773984 | AB56: =IFERROR(VLOOKUP(VALUE(IF(L56<1,1,0)&IF(J56<'Факт продаж'!$M$24,0,1)),$AB$1:$AC$4,2,FALSE),"НЕТ ПРОДАЖ") -> Звезда | AC56: =IFERROR(VLOOKUP(VALUE(IF(R56<1,1,0)&IF(P56<'Факт продаж'!$V$24,0,1)),$AB$1:$AC$4,2,FALSE),"НЕТ ПРОДАЖ") -> Звезда | AD56: =IFERROR(VLOOKUP(VALUE(IF(X56<1,1,0)&IF(V56<'Факт продаж'!$AE$24,0,1)),$AB$1:$AC$4,2,FALSE),"НЕТ ПРОДАЖ") -> Корова | AE56: =IFERROR(VLOOKUP(VALUE(IF(Z56<1,1,0)&IF(V56<'Факт продаж'!$AE$24,0,1)),$AB$1:$AC$4,2,FALSE),"НЕТ ПРОДАЖ") -> Звезда | AF56: =VLOOKUP(B56,'ABC расчет'!B:G,6,0) -> A | AG56: =VLOOKUP(B56,'ABC расчет'!K:P,6,0) -> A | AH56: =VLOOKUP(B56,'ABC расчет'!T:Y,6,0) -> A | AI56: =VLOOKUP(B56,'ABC расчет'!AC:AH,6,0) -> A
A57: КРЕСЛА РУКОВОДИТЕЛЯ | B57: ORION | C57: =IFERROR(VLOOKUP(B57,'Факт продаж'!A:B,2,0),"нет продаж") -> 42 | D57: =IFERROR(VLOOKUP(B57,'Факт продаж'!A:C,3,0),"нет продаж") -> 246234.62 | E57: =IFERROR(VLOOKUP(B57,'Факт продаж'!A:E,5,0),"нет продаж") -> 91265.108 | F57: =IFERROR(VLOOKUP(B57,'Факт продаж'!A:C,3,0)/SUM('План Антонова'!$C$11:$C$13),0) -> 0.0018696856 | G57: =IFERROR(VLOOKUP(B57,'Факт продаж'!J:K,2,0),"нет продаж") -> 164 | H57: =IFERROR(VLOOKUP(B57,'Факт продаж'!J:L,3,0),"нет продаж") -> 1149887.7 | I57: =IFERROR(VLOOKUP(B57,'Факт продаж'!J:N,5,0),"нет продаж") -> 513801.21 | J57: =IFERROR(VLOOKUP(B57,'Факт продаж'!J:L,3,0)/SUM('План Антонова'!$C$14:$C$16),0) -> 0.0079398136 | K57: =IFERROR(VLOOKUP(B57,'Факт продаж'!J:O,6,0),"-") -> 4.6297661 | L57: =IF(AND(F57=0,J57>0),5,IF(J57/F57>5,5,IF(J57/F57=0,0.0000001,J57/F57))) -> 4.2466037 | M57: =IFERROR(VLOOKUP(B57,'Факт продаж'!S:T,2,0),"нет продаж") -> 130 | N57: =IFERROR(VLOOKUP(B57,'Факт продаж'!S:U,3,0),"нет продаж") -> 940250.7 | O57: =IFERROR(VLOOKUP(B57,'Факт продаж'!S:W,5,0),"нет продаж") -> 404540.42 | P57: =IFERROR(VLOOKUP(B57,'Факт продаж'!S:U,3,0)/SUM('План Антонова'!$C$17:$C$19),0) -> 0.0057271144 | Q57: =IFERROR(VLOOKUP(B57,'Факт продаж'!S:X,6,0),"-") -> -0.21265189 | R57: =IF(AND(J57=0,P57>0),5,IF(P57/J57>5,5,IF(P57/J57=0,0.0000001,P57/J57))) -> 0.72131597 | S57: =IFERROR(VLOOKUP(B57,'Факт продаж'!AB:AD,2,0),"нет продаж") -> 205 | T57: =IFERROR(VLOOKUP(B57,'Факт продаж'!AB:AD,3,0),"нет продаж") -> 1463084.9 | U57: =IFERROR(VLOOKUP(B57,'Факт продаж'!AB:AF,5,0),"нет продаж") -> 580004.7 | V57: =IFERROR(VLOOKUP(B57,'Факт продаж'!AB:AD,3,0)/SUM('План Антонова'!$C$20:$C$22),0) -> 0.0095081458 | W57: =IFERROR(VLOOKUP(B57,'Факт продаж'!AB:AG,6,0),"-") -> 0.43373734 | X57: =IF(AND(P57=0,V57>0),5,IF(V57/P57>5,5,IF(V57/P57=0,0.0000001,V57/P57))) -> 1.6601983 | Y57: =IFERROR(VLOOKUP(B57,'Факт продаж'!AB:AH,7,0),"-") -> 5.3551637 | Z57: =IF(AND(F57=0,V57>0),5,IF(V57/F57>5,5,IF(V57/F57=0,0.0000001,V57/F57))) -> 5 | AB57: =IFERROR(VLOOKUP(VALUE(IF(L57<1,1,0)&IF(J57<'Факт продаж'!$M$24,0,1)),$AB$1:$AC$4,2,FALSE),"НЕТ ПРОДАЖ") -> Звезда | AC57: =IFERROR(VLOOKUP(VALUE(IF(R57<1,1,0)&IF(P57<'Факт продаж'!$V$24,0,1)),$AB$1:$AC$4,2,FALSE),"НЕТ ПРОДАЖ") -> Корова | AD57: =IFERROR(VLOOKUP(VALUE(IF(X57<1,1,0)&IF(V57<'Факт продаж'!$AE$24,0,1)),$AB$1:$AC$4,2,FALSE),"НЕТ ПРОДАЖ") -> Звезда | AE57: =IFERROR(VLOOKUP(VALUE(IF(Z57<1,1,0)&IF(V57<'Факт продаж'!$AE$24,0,1)),$AB$1:$AC$4,2,FALSE),"НЕТ ПРОДАЖ") -> Звезда | AF57: =VLOOKUP(B57,'ABC расчет'!B:G,6,0) -> B | AG57: =VLOOKUP(B57,'ABC расчет'!K:P,6,0) -> A | AH57: =VLOOKUP(B57,'ABC расчет'!T:Y,6,0) -> B | AI57: =VLOOKUP(B57,'ABC расчет'!AC:AH,6,0) -> A
A58: КРЕСЛА ОПЕРАТОРСКИЕ | B58: STILO | C58: =IFERROR(VLOOKUP(B58,'Факт продаж'!A:B,2,0),"нет продаж") -> 36 | D58: =IFERROR(VLOOKUP(B58,'Факт продаж'!A:C,3,0),"нет продаж") -> 176529.54 | E58: =IFERROR(VLOOKUP(B58,'Факт продаж'!A:E,5,0),"нет продаж") -> 75609.217 | F58: =IFERROR(VLOOKUP(B58,'Факт продаж'!A:C,3,0)/SUM('План Антонова'!$C$11:$C$13),0) -> 0.0013404075 | G58: =IFERROR(VLOOKUP(B58,'Факт продаж'!J:K,2,0),"нет продаж") -> 174 | H58: =IFERROR(VLOOKUP(B58,'Факт продаж'!J:L,3,0),"нет продаж") -> 974299.45 | I58: =IFERROR(VLOOKUP(B58,'Факт продаж'!J:N,5,0),"нет продаж") -> 436884.36 | J58: =IFERROR(VLOOKUP(B58,'Факт продаж'!J:L,3,0)/SUM('План Антонова'!$C$14:$C$16),0) -> 0.0067274015 | K58: =IFERROR(VLOOKUP(B58,'Факт продаж'!J:O,6,0),"-") -> 4.7781891 | L58: =IF(AND(F58=0,J58>0),5,IF(J58/F58>5,5,IF(J58/F58=0,0.0000001,J58/F58))) -> 5 | M58: =IFERROR(VLOOKUP(B58,'Факт продаж'!S:T,2,0),"нет продаж") -> 181 | N58: =IFERROR(VLOOKUP(B58,'Факт продаж'!S:U,3,0),"нет продаж") -> 994524.07 | O58: =IFERROR(VLOOKUP(B58,'Факт продаж'!S:W,5,0),"нет продаж") -> 428215.43 | P58: =IFERROR(VLOOKUP(B58,'Факт продаж'!S:U,3,0)/SUM('План Антонова'!$C$17:$C$19),0) -> 0.0060576962 | Q58: =IFERROR(VLOOKUP(B58,'Факт продаж'!S:X,6,0),"-") -> -0.019842614 | R58: =IF(AND(J58=0,P58>0),5,IF(P58/J58>5,5,IF(P58/J58=0,0.0000001,P58/J58))) -> 0.90045111 | S58: =IFERROR(VLOOKUP(B58,'Факт продаж'!AB:AD,2,0),"нет продаж") -> 224 | T58: =IFERROR(VLOOKUP(B58,'Факт продаж'!AB:AD,3,0),"нет продаж") -> 1232913.9 | U58: =IFERROR(VLOOKUP(B58,'Факт продаж'!AB:AF,5,0),"нет продаж") -> 572590.7 | V58: =IFERROR(VLOOKUP(B58,'Факт продаж'!AB:AD,3,0)/SUM('План Антонова'!$C$20:$C$22),0) -> 0.0080123345 | W58: =IFERROR(VLOOKUP(B58,'Факт продаж'!AB:AG,6,0),"-") -> 0.3371557 | X58: =IF(AND(P58=0,V58>0),5,IF(V58/P58>5,5,IF(V58/P58=0,0.0000001,V58/P58))) -> 1.3226702 | Y58: =IFERROR(VLOOKUP(B58,'Факт продаж'!AB:AH,7,0),"-") -> 6.5730278 | Z58: =IF(AND(F58=0,V58>0),5,IF(V58/F58>5,5,IF(V58/F58=0,0.0000001,V58/F58))) -> 5 | AB58: =IFERROR(VLOOKUP(VALUE(IF(L58<1,1,0)&IF(J58<'Факт продаж'!$M$24,0,1)),$AB$1:$AC$4,2,FALSE),"НЕТ ПРОДАЖ") -> Звезда | AC58: =IFERROR(VLOOKUP(VALUE(IF(R58<1,1,0)&IF(P58<'Факт продаж'!$V$24,0,1)),$AB$1:$AC$4,2,FALSE),"НЕТ ПРОДАЖ") -> Корова | AD58: =IFERROR(VLOOKUP(VALUE(IF(X58<1,1,0)&IF(V58<'Факт продаж'!$AE$24,0,1)),$AB$1:$AC$4,2,FALSE),"НЕТ ПРОДАЖ") -> Звезда | AE58: =IFERROR(VLOOKUP(VALUE(IF(Z58<1,1,0)&IF(V58<'Факт продаж'!$AE$24,0,1)),$AB$1:$AC$4,2,FALSE),"НЕТ ПРОДАЖ") -> Звезда | AF58: =VLOOKUP(B58,'ABC расчет'!B:G,6,0) -> B | AG58: =VLOOKUP(B58,'ABC расчет'!K:P,6,0) -> A | AH58: =VLOOKUP(B58,'ABC расчет'!T:Y,6,0) -> A | AI58: =VLOOKUP(B58,'ABC расчет'!AC:AH,6,0) -> A
A59: КРЕСЛА РУКОВОДИТЕЛЯ | B59: SOLO | C59: =IFERROR(VLOOKUP(B59,'Факт продаж'!A:B,2,0),"нет продаж") -> 308 | D59: =IFERROR(VLOOKUP(B59,'Факт продаж'!A:C,3,0),"нет продаж") -> 1434969.9 | E59: =IFERROR(VLOOKUP(B59,'Факт продаж'!A:E,5,0),"нет продаж") -> 478257.17 | F59: =IFERROR(VLOOKUP(B59,'Факт продаж'!A:C,3,0)/SUM('План Антонова'!$C$11:$C$13),0) -> 0.010895878 | G59: =IFERROR(VLOOKUP(B59,'Факт продаж'!J:K,2,0),"нет продаж") -> 60 | H59: =IFERROR(VLOOKUP(B59,'Факт продаж'!J:L,3,0),"нет продаж") -> 441038.3 | I59: =IFERROR(VLOOKUP(B59,'Факт продаж'!J:N,5,0),"нет продаж") -> 243986.6 | J59: =IFERROR(VLOOKUP(B59,'Факт продаж'!J:L,3,0)/SUM('План Антонова'!$C$14:$C$16),0) -> 0.0030453078 | K59: =IFERROR(VLOOKUP(B59,'Факт продаж'!J:O,6,0),"-") -> -0.48984226 | L59: =IF(AND(F59=0,J59>0),5,IF(J59/F59>5,5,IF(J59/F59=0,0.0000001,J59/F59))) -> 0.27949173 | M59: =IFERROR(VLOOKUP(B59,'Факт продаж'!S:T,2,0),"нет продаж") -> 21 | N59: =IFERROR(VLOOKUP(B59,'Факт продаж'!S:U,3,0),"нет продаж") -> 179308.2 | O59: =IFERROR(VLOOKUP(B59,'Факт продаж'!S:W,5,0),"нет продаж") -> 98384.914 | P59: =IFERROR(VLOOKUP(B59,'Факт продаж'!S:U,3,0)/SUM('План Антонова'!$C$17:$C$19),0) -> 0.0010921753 | Q59: =IFERROR(VLOOKUP(B59,'Факт продаж'!S:X,6,0),"-") -> -0.59676099 | R59: =IF(AND(J59=0,P59>0),5,IF(P59/J59>5,5,IF(P59/J59=0,0.0000001,P59/J59))) -> 0.358642 | S59: =IFERROR(VLOOKUP(B59,'Факт продаж'!AB:AD,2,0),"нет продаж") -> 113 | T59: =IFERROR(VLOOKUP(B59,'Факт продаж'!AB:AD,3,0),"нет продаж") -> 885966.1 | U59: =IFERROR(VLOOKUP(B59,'Факт продаж'!AB:AF,5,0),"нет продаж") -> 494983.77 | V59: =IFERROR(VLOOKUP(B59,'Факт продаж'!AB:AD,3,0)/SUM('План Антонова'!$C$20:$C$22),0) -> 0.0057576254 | W59: =IFERROR(VLOOKUP(B59,'Факт продаж'!AB:AG,6,0),"-") -> 4.0310942 | X59: =IF(AND(P59=0,V59>0),5,IF(V59/P59>5,5,IF(V59/P59=0,0.0000001,V59/P59))) -> 5 | Y59: =IFERROR(VLOOKUP(B59,'Факт продаж'!AB:AH,7,0),"-") -> 0.034974069 | Z59: =IF(AND(F59=0,V59>0),5,IF(V59/F59>5,5,IF(V59/F59=0,0.0000001,V59/F59))) -> 0.52842234 | AB59: =IFERROR(VLOOKUP(VALUE(IF(L59<1,1,0)&IF(J59<'Факт продаж'!$M$24,0,1)),$AB$1:$AC$4,2,FALSE),"НЕТ ПРОДАЖ") -> Корова | AC59: =IFERROR(VLOOKUP(VALUE(IF(R59<1,1,0)&IF(P59<'Факт продаж'!$V$24,0,1)),$AB$1:$AC$4,2,FALSE),"НЕТ ПРОДАЖ") -> Корова | AD59: =IFERROR(VLOOKUP(VALUE(IF(X59<1,1,0)&IF(V59<'Факт продаж'!$AE$24,0,1)),$AB$1:$AC$4,2,FALSE),"НЕТ ПРОДАЖ") -> Звезда | AE59: =IFERROR(VLOOKUP(VALUE(IF(Z59<1,1,0)&IF(V59<'Факт продаж'!$AE$24,0,1)),$AB$1:$AC$4,2,FALSE),"НЕТ ПРОДАЖ") -> Корова | AF59: =VLOOKUP(B59,'ABC расчет'!B:G,6,0) -> A | AG59: =VLOOKUP(B59,'ABC расчет'!K:P,6,0) -> B | AH59: =VLOOKUP(B59,'ABC расчет'!T:Y,6,0) -> C | AI59: =VLOOKUP(B59,'ABC расчет'!AC:AH,6,0) -> A | AJ59: PROMO
A60: КРЕСЛА/СТУЛЬЯ ОБЕДЕННЫЕ | B60: FORM | C60: =IFERROR(VLOOKUP(B60,'Факт продаж'!A:B,2,0),"нет продаж") -> нет продаж | D60: =IFERROR(VLOOKUP(B60,'Факт продаж'!A:C,3,0),"нет продаж") -> нет продаж | E60: =IFERROR(VLOOKUP(B60,'Факт продаж'!A:E,5,0),"нет продаж") -> нет продаж | F60: =IFERROR(VLOOKUP(B60,'Факт продаж'!A:C,3,0)/SUM('План Антонова'!$C$11:$C$13),0) -> 0 | G60: =IFERROR(VLOOKUP(B60,'Факт продаж'!J:K,2,0),"нет продаж") -> 1493 | H60: =IFERROR(VLOOKUP(B60,'Факт продаж'!J:L,3,0),"нет продаж") -> 2135207.5 | I60: =IFERROR(VLOOKUP(B60,'Факт продаж'!J:N,5,0),"нет продаж") -> 866297.52 | J60: =IFERROR(VLOOKUP(B60,'Факт продаж'!J:L,3,0)/SUM('План Антонова'!$C$14:$C$16),0) -> 0.01474331 | K60: =IFERROR(VLOOKUP(B60,'Факт продаж'!J:O,6,0),"-") -> 1 | L60: =IF(AND(F60=0,J60>0),5,IF(J60/F60>5,5,IF(J60/F60=0,0.0000001,J60/F60))) -> 5 | M60: =IFERROR(VLOOKUP(B60,'Факт продаж'!S:T,2,0),"нет продаж") -> 1048 | N60: =IFERROR(VLOOKUP(B60,'Факт продаж'!S:U,3,0),"нет продаж") -> 1543284.2 | O60: =IFERROR(VLOOKUP(B60,'Факт продаж'!S:W,5,0),"нет продаж") -> 430106.71 | P60: =IFERROR(VLOOKUP(B60,'Факт продаж'!S:U,3,0)/SUM('План Антонова'!$C$17:$C$19),0) -> 0.0094002218 | Q60: =IFERROR(VLOOKUP(B60,'Факт продаж'!S:X,6,0),"-") -> -0.50351156 | R60: =IF(AND(J60=0,P60>0),5,IF(P60/J60>5,5,IF(P60/J60=0,0.0000001,P60/J60))) -> 0.63759237 | S60: =IFERROR(VLOOKUP(B60,'Факт продаж'!AB:AD,2,0),"нет продаж") -> 1094 | T60: =IFERROR(VLOOKUP(B60,'Факт продаж'!AB:AD,3,0),"нет продаж") -> 1709898.1 | U60: =IFERROR(VLOOKUP(B60,'Факт продаж'!AB:AF,5,0),"нет продаж") -> 494394.39 | V60: =IFERROR(VLOOKUP(B60,'Факт продаж'!AB:AD,3,0)/SUM('План Антонова'!$C$20:$C$22),0) -> 0.01111211 | W60: =IFERROR(VLOOKUP(B60,'Факт продаж'!AB:AG,6,0),"-") -> 0.14946915 | X60: =IF(AND(P60=0,V60>0),5,IF(V60/P60>5,5,IF(V60/P60=0,0.0000001,V60/P60))) -> 1.1821115 | Y60: =IFERROR(VLOOKUP(B60,'Факт продаж'!AB:AH,7,0),"-") -> 1 | Z60: =IF(AND(F60=0,V60>0),5,IF(V60/F60>5,5,IF(V60/F60=0,0.0000001,V60/F60))) -> 5 | AB60: =IFERROR(VLOOKUP(VALUE(IF(L60<1,1,0)&IF(J60<'Факт продаж'!$M$24,0,1)),$AB$1:$AC$4,2,FALSE),"НЕТ ПРОДАЖ") -> Звезда | AC60: =IFERROR(VLOOKUP(VALUE(IF(R60<1,1,0)&IF(P60<'Факт продаж'!$V$24,0,1)),$AB$1:$AC$4,2,FALSE),"НЕТ ПРОДАЖ") -> Корова | AD60: =IFERROR(VLOOKUP(VALUE(IF(X60<1,1,0)&IF(V60<'Факт продаж'!$AE$24,0,1)),$AB$1:$AC$4,2,FALSE),"НЕТ ПРОДАЖ") -> Звезда | AE60: =IFERROR(VLOOKUP(VALUE(IF(Z60<1,1,0)&IF(V60<'Факт продаж'!$AE$24,0,1)),$AB$1:$AC$4,2,FALSE),"НЕТ ПРОДАЖ") -> Звезда | AF60: =VLOOKUP(B60,'ABC расчет'!B:G,6,0) -> C | AG60: =VLOOKUP(B60,'ABC расчет'!K:P,6,0) -> A | AH60: =VLOOKUP(B60,'ABC расчет'!T:Y,6,0) -> A | AI60: =VLOOKUP(B60,'ABC расчет'!AC:AH,6,0) -> A | AJ60: PROMO
A61: КРЕСЛА ОПЕРАТОРСКИЕ | B61: LIRA | C61: =IFERROR(VLOOKUP(B61,'Факт продаж'!A:B,2,0),"нет продаж") -> нет продаж | D61: =IFERROR(VLOOKUP(B61,'Факт продаж'!A:C,3,0),"нет продаж") -> нет продаж | E61: =IFERROR(VLOOKUP(B61,'Факт продаж'!A:E,5,0),"нет продаж") -> нет продаж | F61: =IFERROR(VLOOKUP(B61,'Факт продаж'!A:C,3,0)/SUM('План Антонова'!$C$11:$C$13),0) -> 0 | G61: =IFERROR(VLOOKUP(B61,'Факт продаж'!J:K,2,0),"нет продаж") -> 982 | H61: =IFERROR(VLOOKUP(B61,'Факт продаж'!J:L,3,0),"нет продаж") -> 1919498.7 | I61: =IFERROR(VLOOKUP(B61,'Факт продаж'!J:N,5,0),"нет продаж") -> 852024.5 | J61: =IFERROR(VLOOKUP(B61,'Факт продаж'!J:L,3,0)/SUM('План Антонова'!$C$14:$C$16),0) -> 0.01325387 | K61: =IFERROR(VLOOKUP(B61,'Факт продаж'!J:O,6,0),"-") -> 1 | L61: =IF(AND(F61=0,J61>0),5,IF(J61/F61>5,5,IF(J61/F61=0,0.0000001,J61/F61))) -> 5 | M61: =IFERROR(VLOOKUP(B61,'Факт продаж'!S:T,2,0),"нет продаж") -> 917 | N61: =IFERROR(VLOOKUP(B61,'Факт продаж'!S:U,3,0),"нет продаж") -> 1846021.1 | O61: =IFERROR(VLOOKUP(B61,'Факт продаж'!S:W,5,0),"нет продаж") -> 623496.05 | P61: =IFERROR(VLOOKUP(B61,'Факт продаж'!S:U,3,0)/SUM('План Антонова'!$C$17:$C$19),0) -> 0.011244207 | Q61: =IFERROR(VLOOKUP(B61,'Факт продаж'!S:X,6,0),"-") -> -0.26821816 | R61: =IF(AND(J61=0,P61>0),5,IF(P61/J61>5,5,IF(P61/J61=0,0.0000001,P61/J61))) -> 0.84837161 | S61: =IFERROR(VLOOKUP(B61,'Факт продаж'!AB:AD,2,0),"нет продаж") -> 685 | T61: =IFERROR(VLOOKUP(B61,'Факт продаж'!AB:AD,3,0),"нет продаж") -> 1421396.6 | U61: =IFERROR(VLOOKUP(B61,'Факт продаж'!AB:AF,5,0),"нет продаж") -> 493451.08 | V61: =IFERROR(VLOOKUP(B61,'Факт продаж'!AB:AD,3,0)/SUM('План Антонова'!$C$20:$C$22),0) -> 0.0092372262 | W61: =IFERROR(VLOOKUP(B61,'Факт продаж'!AB:AG,6,0),"-") -> -0.20857386 | X61: =IF(AND(P61=0,V61>0),5,IF(V61/P61>5,5,IF(V61/P61=0,0.0000001,V61/P61))) -> 0.82150978 | Y61: =IFERROR(VLOOKUP(B61,'Факт продаж'!AB:AH,7,0),"-") -> 1 | Z61: =IF(AND(F61=0,V61>0),5,IF(V61/F61>5,5,IF(V61/F61=0,0.0000001,V61/F61))) -> 5 | AB61: =IFERROR(VLOOKUP(VALUE(IF(L61<1,1,0)&IF(J61<'Факт продаж'!$M$24,0,1)),$AB$1:$AC$4,2,FALSE),"НЕТ ПРОДАЖ") -> Звезда | AC61: =IFERROR(VLOOKUP(VALUE(IF(R61<1,1,0)&IF(P61<'Факт продаж'!$V$24,0,1)),$AB$1:$AC$4,2,FALSE),"НЕТ ПРОДАЖ") -> Корова | AD61: =IFERROR(VLOOKUP(VALUE(IF(X61<1,1,0)&IF(V61<'Факт продаж'!$AE$24,0,1)),$AB$1:$AC$4,2,FALSE),"НЕТ ПРОДАЖ") -> Корова | AE61: =IFERROR(VLOOKUP(VALUE(IF(Z61<1,1,0)&IF(V61<'Факт продаж'!$AE$24,0,1)),$AB$1:$AC$4,2,FALSE),"НЕТ ПРОДАЖ") -> Звезда | AF61: =VLOOKUP(B61,'ABC расчет'!B:G,6,0) -> C | AG61: =VLOOKUP(B61,'ABC расчет'!K:P,6,0) -> A | AH61: =VLOOKUP(B61,'ABC расчет'!T:Y,6,0) -> A | AI61: =VLOOKUP(B61,'ABC расчет'!AC:AH,6,0) -> A | AJ61: PROMO
A62: КРЕСЛА/СТУЛЬЯ ОБЕДЕННЫЕ | B62: VENUS | C62: =IFERROR(VLOOKUP(B62,'Факт продаж'!A:B,2,0),"нет продаж") -> 626 | D62: =IFERROR(VLOOKUP(B62,'Факт продаж'!A:C,3,0),"нет продаж") -> 336288.91 | E62: =IFERROR(VLOOKUP(B62,'Факт продаж'!A:E,5,0),"нет продаж") -> 111545.32 | F62: =IFERROR(VLOOKUP(B62,'Факт продаж'!A:C,3,0)/SUM('План Антонова'!$C$11:$C$13),0) -> 0.0025534773 | G62: =IFERROR(VLOOKUP(B62,'Факт продаж'!J:K,2,0),"нет продаж") -> 1062 | H62: =IFERROR(VLOOKUP(B62,'Факт продаж'!J:L,3,0),"нет продаж") -> 730565.24 | I62: =IFERROR(VLOOKUP(B62,'Факт продаж'!J:N,5,0),"нет продаж") -> 302599.94 | J62: =IFERROR(VLOOKUP(B62,'Факт продаж'!J:L,3,0)/SUM('План Антонова'!$C$14:$C$16),0) -> 0.0050444509 | K62: =IFERROR(VLOOKUP(B62,'Факт продаж'!J:O,6,0),"-") -> 1.7127982 | L62: =IF(AND(F62=0,J62>0),5,IF(J62/F62>5,5,IF(J62/F62=0,0.0000001,J62/F62))) -> 1.9755221 | M62: =IFERROR(VLOOKUP(B62,'Факт продаж'!S:T,2,0),"нет продаж") -> 1967 | N62: =IFERROR(VLOOKUP(B62,'Факт продаж'!S:U,3,0),"нет продаж") -> 1309786.2 | O62: =IFERROR(VLOOKUP(B62,'Факт продаж'!S:W,5,0),"нет продаж") -> 472510.7 | P62: =IFERROR(VLOOKUP(B62,'Факт продаж'!S:U,3,0)/SUM('План Антонова'!$C$17:$C$19),0) -> 0.0079779737 | Q62: =IFERROR(VLOOKUP(B62,'Факт продаж'!S:X,6,0),"-") -> 0.56150297 | R62: =IF(AND(J62=0,P62>0),5,IF(P62/J62>5,5,IF(P62/J62=0,0.0000001,P62/J62))) -> 1.5815346 | S62: =IFERROR(VLOOKUP(B62,'Факт продаж'!AB:AD,2,0),"нет продаж") -> 2014 | T62: =IFERROR(VLOOKUP(B62,'Факт продаж'!AB:AD,3,0),"нет продаж") -> 1417765.8 | U62: =IFERROR(VLOOKUP(B62,'Факт продаж'!AB:AF,5,0),"нет продаж") -> 482507.76 | V62: =IFERROR(VLOOKUP(B62,'Факт продаж'!AB:AD,3,0)/SUM('План Антонова'!$C$20:$C$22),0) -> 0.0092136309 | W62: =IFERROR(VLOOKUP(B62,'Факт продаж'!AB:AG,6,0),"-") -> 0.021157316 | X62: =IF(AND(P62=0,V62>0),5,IF(V62/P62>5,5,IF(V62/P62=0,0.0000001,V62/P62))) -> 1.1548836 | Y62: =IFERROR(VLOOKUP(B62,'Факт продаж'!AB:AH,7,0),"-") -> 3.3256657 | Z62: =IF(AND(F62=0,V62>0),5,IF(V62/F62>5,5,IF(V62/F62=0,0.0000001,V62/F62))) -> 3.6082681 | AB62: =IFERROR(VLOOKUP(VALUE(IF(L62<1,1,0)&IF(J62<'Факт продаж'!$M$24,0,1)),$AB$1:$AC$4,2,FALSE),"НЕТ ПРОДАЖ") -> Звезда | AC62: =IFERROR(VLOOKUP(VALUE(IF(R62<1,1,0)&IF(P62<'Факт продаж'!$V$24,0,1)),$AB$1:$AC$4,2,FALSE),"НЕТ ПРОДАЖ") -> Звезда | AD62: =IFERROR(VLOOKUP(VALUE(IF(X62<1,1,0)&IF(V62<'Факт продаж'!$AE$24,0,1)),$AB$1:$AC$4,2,FALSE),"НЕТ ПРОДАЖ") -> Звезда | AE62: =IFERROR(VLOOKUP(VALUE(IF(Z62<1,1,0)&IF(V62<'Факт продаж'!$AE$24,0,1)),$AB$1:$AC$4,2,FALSE),"НЕТ ПРОДАЖ") -> Звезда | AF62: =VLOOKUP(B62,'ABC расчет'!B:G,6,0) -> A | AG62: =VLOOKUP(B62,'ABC расчет'!K:P,6,0) -> A | AH62: =VLOOKUP(B62,'ABC расчет'!T:Y,6,0) -> A | AI62: =VLOOKUP(B62,'ABC расчет'!AC:AH,6,0) -> A
A63: КРЕСЛА РУКОВОДИТЕЛЯ | B63: LIBERTY | C63: =IFERROR(VLOOKUP(B63,'Факт продаж'!A:B,2,0),"нет продаж") -> 43 | D63: =IFERROR(VLOOKUP(B63,'Факт продаж'!A:C,3,0),"нет продаж") -> 150377.59 | E63: =IFERROR(VLOOKUP(B63,'Факт продаж'!A:E,5,0),"нет продаж") -> 65489.726 | F63: =IFERROR(VLOOKUP(B63,'Факт продаж'!A:C,3,0)/SUM('План Антонова'!$C$11:$C$13),0) -> 0.001141833 | G63: =IFERROR(VLOOKUP(B63,'Факт продаж'!J:K,2,0),"нет продаж") -> 201 | H63: =IFERROR(VLOOKUP(B63,'Факт продаж'!J:L,3,0),"нет продаж") -> 978410.66 | I63: =IFERROR(VLOOKUP(B63,'Факт продаж'!J:N,5,0),"нет продаж") -> 469368.01 | J63: =IFERROR(VLOOKUP(B63,'Факт продаж'!J:L,3,0)/SUM('План Антонова'!$C$14:$C$16),0) -> 0.0067557889 | K63: =IFERROR(VLOOKUP(B63,'Факт продаж'!J:O,6,0),"-") -> 6.1670481 | L63: =IF(AND(F63=0,J63>0),5,IF(J63/F63>5,5,IF(J63/F63=0,0.0000001,J63/F63))) -> 5 | M63: =IFERROR(VLOOKUP(B63,'Факт продаж'!S:T,2,0),"нет продаж") -> 226 | N63: =IFERROR(VLOOKUP(B63,'Факт продаж'!S:U,3,0),"нет продаж") -> 1025256.3 | O63: =IFERROR(VLOOKUP(B63,'Факт продаж'!S:W,5,0),"нет продаж") -> 457388.76 | P63: =IFERROR(VLOOKUP(B63,'Факт продаж'!S:U,3,0)/SUM('План Антонова'!$C$17:$C$19),0) -> 0.0062448877 | Q63: =IFERROR(VLOOKUP(B63,'Факт продаж'!S:X,6,0),"-") -> -0.025522102 | R63: =IF(AND(J63=0,P63>0),5,IF(P63/J63>5,5,IF(P63/J63=0,0.0000001,P63/J63))) -> 0.9243758 | S63: =IFERROR(VLOOKUP(B63,'Факт продаж'!AB:AD,2,0),"нет продаж") -> 222 | T63: =IFERROR(VLOOKUP(B63,'Факт продаж'!AB:AD,3,0),"нет продаж") -> 1030487.2 | U63: =IFERROR(VLOOKUP(B63,'Факт продаж'!AB:AF,5,0),"нет продаж") -> 473056.27 | V63: =IFERROR(VLOOKUP(B63,'Факт продаж'!AB:AD,3,0)/SUM('План Антонова'!$C$20:$C$22),0) -> 0.0066968246 | W63: =IFERROR(VLOOKUP(B63,'Факт продаж'!AB:AG,6,0),"-") -> 0.034254268 | X63: =IF(AND(P63=0,V63>0),5,IF(V63/P63>5,5,IF(V63/P63=0,0.0000001,V63/P63))) -> 1.0723691 | Y63: =IFERROR(VLOOKUP(B63,'Факт продаж'!AB:AH,7,0),"-") -> 6.2233663 | Z63: =IF(AND(F63=0,V63>0),5,IF(V63/F63>5,5,IF(V63/F63=0,0.0000001,V63/F63))) -> 5 | AB63: =IFERROR(VLOOKUP(VALUE(IF(L63<1,1,0)&IF(J63<'Факт продаж'!$M$24,0,1)),$AB$1:$AC$4,2,FALSE),"НЕТ ПРОДАЖ") -> Звезда | AC63: =IFERROR(VLOOKUP(VALUE(IF(R63<1,1,0)&IF(P63<'Факт продаж'!$V$24,0,1)),$AB$1:$AC$4,2,FALSE),"НЕТ ПРОДАЖ") -> Корова | AD63: =IFERROR(VLOOKUP(VALUE(IF(X63<1,1,0)&IF(V63<'Факт продаж'!$AE$24,0,1)),$AB$1:$AC$4,2,FALSE),"НЕТ ПРОДАЖ") -> Звезда | AE63: =IFERROR(VLOOKUP(VALUE(IF(Z63<1,1,0)&IF(V63<'Факт продаж'!$AE$24,0,1)),$AB$1:$AC$4,2,FALSE),"НЕТ ПРОДАЖ") -> Звезда | AF63: =VLOOKUP(B63,'ABC расчет'!B:G,6,0) -> B | AG63: =VLOOKUP(B63,'ABC расчет'!K:P,6,0) -> B | AH63: =VLOOKUP(B63,'ABC расчет'!T:Y,6,0) -> A | AI63: =VLOOKUP(B63,'ABC расчет'!AC:AH,6,0) -> A
A64: КРЕСЛА ОПЕРАТОРСКИЕ | B64: FRAME | C64: =IFERROR(VLOOKUP(B64,'Факт продаж'!A:B,2,0),"нет продаж") -> 115 | D64: =IFERROR(VLOOKUP(B64,'Факт продаж'!A:C,3,0),"нет продаж") -> 422296.68 | E64: =IFERROR(VLOOKUP(B64,'Факт продаж'!A:E,5,0),"нет продаж") -> 80857.873 | F64: =IFERROR(VLOOKUP(B64,'Факт продаж'!A:C,3,0)/SUM('План Антонова'!$C$11:$C$13),0) -> 0.0032065434 | G64: =IFERROR(VLOOKUP(B64,'Факт продаж'!J:K,2,0),"нет продаж") -> 16 | H64: =IFERROR(VLOOKUP(B64,'Факт продаж'!J:L,3,0),"нет продаж") -> 103587.5 | I64: =IFERROR(VLOOKUP(B64,'Факт продаж'!J:N,5,0),"нет продаж") -> 44547.689 | J64: =IFERROR(VLOOKUP(B64,'Факт продаж'!J:L,3,0)/SUM('План Антонова'!$C$14:$C$16),0) -> 0.00071525721 | K64: =IFERROR(VLOOKUP(B64,'Факт продаж'!J:O,6,0),"-") -> -0.44906182 | L64: =IF(AND(F64=0,J64>0),5,IF(J64/F64>5,5,IF(J64/F64=0,0.0000001,J64/F64))) -> 0.22306176 | M64: =IFERROR(VLOOKUP(B64,'Факт продаж'!S:T,2,0),"нет продаж") -> 117 | N64: =IFERROR(VLOOKUP(B64,'Факт продаж'!S:U,3,0),"нет продаж") -> 619658.84 | O64: =IFERROR(VLOOKUP(B64,'Факт продаж'!S:W,5,0),"нет продаж") -> 254427.89 | P64: =IFERROR(VLOOKUP(B64,'Факт продаж'!S:U,3,0)/SUM('План Антонова'!$C$17:$C$19),0) -> 0.0037743732 | Q64: =IFERROR(VLOOKUP(B64,'Факт продаж'!S:X,6,0),"-") -> 4.7113599 | R64: =IF(AND(J64=0,P64>0),5,IF(P64/J64>5,5,IF(P64/J64=0,0.0000001,P64/J64))) -> 5 | S64: =IFERROR(VLOOKUP(B64,'Факт продаж'!AB:AD,2,0),"нет продаж") -> 175 | T64: =IFERROR(VLOOKUP(B64,'Факт продаж'!AB:AD,3,0),"нет продаж") -> 1006197.2 | U64: =IFERROR(VLOOKUP(B64,'Факт продаж'!AB:AF,5,0),"нет продаж") -> 457710.64 | V64: =IFERROR(VLOOKUP(B64,'Факт продаж'!AB:AD,3,0)/SUM('План Антонова'!$C$20:$C$22),0) -> 0.0065389706 | W64: =IFERROR(VLOOKUP(B64,'Факт продаж'!AB:AG,6,0),"-") -> 0.79897983 | X64: =IF(AND(P64=0,V64>0),5,IF(V64/P64>5,5,IF(V64/P64=0,0.0000001,V64/P64))) -> 1.7324653 | Y64: =IFERROR(VLOOKUP(B64,'Факт продаж'!AB:AH,7,0),"-") -> 4.6606812 | Z64: =IF(AND(F64=0,V64>0),5,IF(V64/F64>5,5,IF(V64/F64=0,0.0000001,V64/F64))) -> 2.0392584 | AB64: =IFERROR(VLOOKUP(VALUE(IF(L64<1,1,0)&IF(J64<'Факт продаж'!$M$24,0,1)),$AB$1:$AC$4,2,FALSE),"НЕТ ПРОДАЖ") -> Собака | AC64: =IFERROR(VLOOKUP(VALUE(IF(R64<1,1,0)&IF(P64<'Факт продаж'!$V$24,0,1)),$AB$1:$AC$4,2,FALSE),"НЕТ ПРОДАЖ") -> Звезда | AD64: =IFERROR(VLOOKUP(VALUE(IF(X64<1,1,0)&IF(V64<'Факт продаж'!$AE$24,0,1)),$AB$1:$AC$4,2,FALSE),"НЕТ ПРОДАЖ") -> Звезда | AE64: =IFERROR(VLOOKUP(VALUE(IF(Z64<1,1,0)&IF(V64<'Факт продаж'!$AE$24,0,1)),$AB$1:$AC$4,2,FALSE),"НЕТ ПРОДАЖ") -> Звезда | AF64: =VLOOKUP(B64,'ABC расчет'!B:G,6,0) -> B | AG64: =VLOOKUP(B64,'ABC расчет'!K:P,6,0) -> C | AH64: =VLOOKUP(B64,'ABC расчет'!T:Y,6,0) -> B | AI64: =VLOOKUP(B64,'ABC расчет'!AC:AH,6,0) -> A | AJ64: PROMO
A65: СТУЛЬЯ ПОСЕТИТЕЛЬСКИЕ | B65: BESTA | C65: =IFERROR(VLOOKUP(B65,'Факт продаж'!A:B,2,0),"нет продаж") -> 804 | D65: =IFERROR(VLOOKUP(B65,'Факт продаж'!A:C,3,0),"нет продаж") -> 441726.86 | E65: =IFERROR(VLOOKUP(B65,'Факт продаж'!A:E,5,0),"нет продаж") -> 132097.13 | F65: =IFERROR(VLOOKUP(B65,'Факт продаж'!A:C,3,0)/SUM('План Антонова'!$C$11:$C$13),0) -> 0.0033540789 | G65: =IFERROR(VLOOKUP(B65,'Факт продаж'!J:K,2,0),"нет продаж") -> 515 | H65: =IFERROR(VLOOKUP(B65,'Факт продаж'!J:L,3,0),"нет продаж") -> 384141.8 | I65: =IFERROR(VLOOKUP(B65,'Факт продаж'!J:N,5,0),"нет продаж") -> 143807.19 | J65: =IFERROR(VLOOKUP(B65,'Факт продаж'!J:L,3,0)/SUM('План Антонова'!$C$14:$C$16),0) -> 0.0026524454 | K65: =IFERROR(VLOOKUP(B65,'Факт продаж'!J:O,6,0),"-") -> 0.088647364 | L65: =IF(AND(F65=0,J65>0),5,IF(J65/F65>5,5,IF(J65/F65=0,0.0000001,J65/F65))) -> 0.79081189 | M65: =IFERROR(VLOOKUP(B65,'Факт продаж'!S:T,2,0),"нет продаж") -> 459 | N65: =IFERROR(VLOOKUP(B65,'Факт продаж'!S:U,3,0),"нет продаж") -> 338740.9 | O65: =IFERROR(VLOOKUP(B65,'Факт продаж'!S:W,5,0),"нет продаж") -> 112896.08 | P65: =IFERROR(VLOOKUP(B65,'Факт продаж'!S:U,3,0)/SUM('План Антонова'!$C$17:$C$19),0) -> 0.0020632879 | Q65: =IFERROR(VLOOKUP(B65,'Факт продаж'!S:X,6,0),"-") -> -0.21494834 | R65: =IF(AND(J65=0,P65>0),5,IF(P65/J65>5,5,IF(P65/J65=0,0.0000001,P65/J65))) -> 0.77788137 | S65: =IFERROR(VLOOKUP(B65,'Факт продаж'!AB:AD,2,0),"нет продаж") -> 1848 | T65: =IFERROR(VLOOKUP(B65,'Факт продаж'!AB:AD,3,0),"нет продаж") -> 1294956.3 | U65: =IFERROR(VLOOKUP(B65,'Факт продаж'!AB:AF,5,0),"нет продаж") -> 448043.65 | V65: =IFERROR(VLOOKUP(B65,'Факт продаж'!AB:AD,3,0)/SUM('План Антонова'!$C$20:$C$22),0) -> 0.0084155289 | W65: =IFERROR(VLOOKUP(B65,'Факт продаж'!AB:AG,6,0),"-") -> 2.968638 | X65: =IF(AND(P65=0,V65>0),5,IF(V65/P65>5,5,IF(V65/P65=0,0.0000001,V65/P65))) -> 4.0786984 | Y65: =IFERROR(VLOOKUP(B65,'Факт продаж'!AB:AH,7,0),"-") -> 2.3917743 | Z65: =IF(AND(F65=0,V65>0),5,IF(V65/F65>5,5,IF(V65/F65=0,0.0000001,V65/F65))) -> 2.5090432 | AB65: =IFERROR(VLOOKUP(VALUE(IF(L65<1,1,0)&IF(J65<'Факт продаж'!$M$24,0,1)),$AB$1:$AC$4,2,FALSE),"НЕТ ПРОДАЖ") -> Корова | AC65: =IFERROR(VLOOKUP(VALUE(IF(R65<1,1,0)&IF(P65<'Факт продаж'!$V$24,0,1)),$AB$1:$AC$4,2,FALSE),"НЕТ ПРОДАЖ") -> Корова | AD65: =IFERROR(VLOOKUP(VALUE(IF(X65<1,1,0)&IF(V65<'Факт продаж'!$AE$24,0,1)),$AB$1:$AC$4,2,FALSE),"НЕТ ПРОДАЖ") -> Звезда | AE65: =IFERROR(VLOOKUP(VALUE(IF(Z65<1,1,0)&IF(V65<'Факт продаж'!$AE$24,0,1)),$AB$1:$AC$4,2,FALSE),"НЕТ ПРОДАЖ") -> Звезда | AF65: =VLOOKUP(B65,'ABC расчет'!B:G,6,0) -> C | AG65: =VLOOKUP(B65,'ABC расчет'!K:P,6,0) -> C | AH65: =VLOOKUP(B65,'ABC расчет'!T:Y,6,0) -> C | AI65: =VLOOKUP(B65,'ABC расчет'!AC:AH,6,0) -> B | AJ65: PROMO
A66: КРЕСЛА НА РОЛИКАХ | B66: NICOLE GTS | C66: =IFERROR(VLOOKUP(B66,'Факт продаж'!A:B,2,0),"нет продаж") -> 26 | D66: =IFERROR(VLOOKUP(B66,'Факт продаж'!A:C,3,0),"нет продаж") -> 61283.488 | E66: =IFERROR(VLOOKUP(B66,'Факт продаж'!A:E,5,0),"нет продаж") -> 30868.364 | F66: =IFERROR(VLOOKUP(B66,'Факт продаж'!A:C,3,0)/SUM('План Антонова'!$C$11:$C$13),0) -> 0.00046533202 | G66: =IFERROR(VLOOKUP(B66,'Факт продаж'!J:K,2,0),"нет продаж") -> 160 | H66: =IFERROR(VLOOKUP(B66,'Факт продаж'!J:L,3,0),"нет продаж") -> 380757.9 | I66: =IFERROR(VLOOKUP(B66,'Факт продаж'!J:N,5,0),"нет продаж") -> 152073.89 | J66: =IFERROR(VLOOKUP(B66,'Факт продаж'!J:L,3,0)/SUM('План Антонова'!$C$14:$C$16),0) -> 0.0026290801 | K66: =IFERROR(VLOOKUP(B66,'Факт продаж'!J:O,6,0),"-") -> 3.9265291 | L66: =IF(AND(F66=0,J66>0),5,IF(J66/F66>5,5,IF(J66/F66=0,0.0000001,J66/F66))) -> 5 | M66: =IFERROR(VLOOKUP(B66,'Факт продаж'!S:T,2,0),"нет продаж") -> 503 | N66: =IFERROR(VLOOKUP(B66,'Факт продаж'!S:U,3,0),"нет продаж") -> 1238670.5 | O66: =IFERROR(VLOOKUP(B66,'Факт продаж'!S:W,5,0),"нет продаж") -> 436602.9 | P66: =IFERROR(VLOOKUP(B66,'Факт продаж'!S:U,3,0)/SUM('План Антонова'!$C$17:$C$19),0) -> 0.0075448042 | Q66: =IFERROR(VLOOKUP(B66,'Факт продаж'!S:X,6,0),"-") -> 1.8709918 | R66: =IF(AND(J66=0,P66>0),5,IF(P66/J66>5,5,IF(P66/J66=0,0.0000001,P66/J66))) -> 2.8697506 | S66: =IFERROR(VLOOKUP(B66,'Факт продаж'!AB:AD,2,0),"нет продаж") -> 406 | T66: =IFERROR(VLOOKUP(B66,'Факт продаж'!AB:AD,3,0),"нет продаж") -> 1096071.8 | U66: =IFERROR(VLOOKUP(B66,'Факт продаж'!AB:AF,5,0),"нет продаж") -> 435856.25 | V66: =IFERROR(VLOOKUP(B66,'Факт продаж'!AB:AD,3,0)/SUM('План Антонова'!$C$20:$C$22),0) -> 0.0071230386 | W66: =IFERROR(VLOOKUP(B66,'Факт продаж'!AB:AG,6,0),"-") -> -0.001710134 | X66: =IF(AND(P66=0,V66>0),5,IF(V66/P66>5,5,IF(V66/P66=0,0.0000001,V66/P66))) -> 0.94409855 | Y66: =IFERROR(VLOOKUP(B66,'Факт продаж'!AB:AH,7,0),"-") -> 13.119837 | Z66: =IF(AND(F66=0,V66>0),5,IF(V66/F66>5,5,IF(V66/F66=0,0.0000001,V66/F66))) -> 5 | AB66: =IFERROR(VLOOKUP(VALUE(IF(L66<1,1,0)&IF(J66<'Факт продаж'!$M$24,0,1)),$AB$1:$AC$4,2,FALSE),"НЕТ ПРОДАЖ") -> Звезда | AC66: =IFERROR(VLOOKUP(VALUE(IF(R66<1,1,0)&IF(P66<'Факт продаж'!$V$24,0,1)),$AB$1:$AC$4,2,FALSE),"НЕТ ПРОДАЖ") -> Звезда | AD66: =IFERROR(VLOOKUP(VALUE(IF(X66<1,1,0)&IF(V66<'Факт продаж'!$AE$24,0,1)),$AB$1:$AC$4,2,FALSE),"НЕТ ПРОДАЖ") -> Корова | AE66: =IFERROR(VLOOKUP(VALUE(IF(Z66<1,1,0)&IF(V66<'Факт продаж'!$AE$24,0,1)),$AB$1:$AC$4,2,FALSE),"НЕТ ПРОДАЖ") -> Звезда | AF66: =VLOOKUP(B66,'ABC расчет'!B:G,6,0) -> A | AG66: =VLOOKUP(B66,'ABC расчет'!K:P,6,0) -> A | AH66: =VLOOKUP(B66,'ABC расчет'!T:Y,6,0) -> A | AI66: =VLOOKUP(B66,'ABC расчет'!AC:AH,6,0) -> A | AJ66: PROMO
A67: КРЕСЛА РУКОВОДИТЕЛЯ | B67: MANAGER | C67: =IFERROR(VLOOKUP(B67,'Факт продаж'!A:B,2,0),"нет продаж") -> 472 | D67: =IFERROR(VLOOKUP(B67,'Факт продаж'!A:C,3,0),"нет продаж") -> 1350660.4 | E67: =IFERROR(VLOOKUP(B67,'Факт продаж'!A:E,5,0),"нет продаж") -> 493733.77 | F67: =IFERROR(VLOOKUP(B67,'Факт продаж'!A:C,3,0)/SUM('План Антонова'!$C$11:$C$13),0) -> 0.010255707 | G67: =IFERROR(VLOOKUP(B67,'Факт продаж'!J:K,2,0),"нет продаж") -> 242 | H67: =IFERROR(VLOOKUP(B67,'Факт продаж'!J:L,3,0),"нет продаж") -> 998963.65 | I67: =IFERROR(VLOOKUP(B67,'Факт продаж'!J:N,5,0),"нет продаж") -> 470369.83 | J67: =IFERROR(VLOOKUP(B67,'Факт продаж'!J:L,3,0)/SUM('План Антонова'!$C$14:$C$16),0) -> 0.0068977044 | K67: =IFERROR(VLOOKUP(B67,'Факт продаж'!J:O,6,0),"-") -> -0.04732092 | L67: =IF(AND(F67=0,J67>0),5,IF(J67/F67>5,5,IF(J67/F67=0,0.0000001,J67/F67))) -> 0.67257228 | M67: =IFERROR(VLOOKUP(B67,'Факт продаж'!S:T,2,0),"нет продаж") -> 185 | N67: =IFERROR(VLOOKUP(B67,'Факт продаж'!S:U,3,0),"нет продаж") -> 906799.3 | O67: =IFERROR(VLOOKUP(B67,'Факт продаж'!S:W,5,0),"нет продаж") -> 398009.92 | P67: =IFERROR(VLOOKUP(B67,'Факт продаж'!S:U,3,0)/SUM('План Антонова'!$C$17:$C$19),0) -> 0.0055233602 | Q67: =IFERROR(VLOOKUP(B67,'Факт продаж'!S:X,6,0),"-") -> -0.15383622 | R67: =IF(AND(J67=0,P67>0),5,IF(P67/J67>5,5,IF(P67/J67=0,0.0000001,P67/J67))) -> 0.8007534 | S67: =IFERROR(VLOOKUP(B67,'Факт продаж'!AB:AD,2,0),"нет продаж") -> 187 | T67: =IFERROR(VLOOKUP(B67,'Факт продаж'!AB:AD,3,0),"нет продаж") -> 943714.37 | U67: =IFERROR(VLOOKUP(B67,'Факт продаж'!AB:AF,5,0),"нет продаж") -> 400027.13 | V67: =IFERROR(VLOOKUP(B67,'Факт продаж'!AB:AD,3,0)/SUM('План Антонова'!$C$20:$C$22),0) -> 0.006132914 | W67: =IFERROR(VLOOKUP(B67,'Факт продаж'!AB:AG,6,0),"-") -> 0.0050682379 | X67: =IF(AND(P67=0,V67>0),5,IF(V67/P67>5,5,IF(V67/P67=0,0.0000001,V67/P67))) -> 1.1103592 | Y67: =IFERROR(VLOOKUP(B67,'Факт продаж'!AB:AH,7,0),"-") -> -0.18979185 | Z67: =IF(AND(F67=0,V67>0),5,IF(V67/F67>5,5,IF(V67/F67=0,0.0000001,V67/F67))) -> 0.5980001 | AB67: =IFERROR(VLOOKUP(VALUE(IF(L67<1,1,0)&IF(J67<'Факт продаж'!$M$24,0,1)),$AB$1:$AC$4,2,FALSE),"НЕТ ПРОДАЖ") -> Корова | AC67: =IFERROR(VLOOKUP(VALUE(IF(R67<1,1,0)&IF(P67<'Факт продаж'!$V$24,0,1)),$AB$1:$AC$4,2,FALSE),"НЕТ ПРОДАЖ") -> Корова | AD67: =IFERROR(VLOOKUP(VALUE(IF(X67<1,1,0)&IF(V67<'Факт продаж'!$AE$24,0,1)),$AB$1:$AC$4,2,FALSE),"НЕТ ПРОДАЖ") -> Звезда | AE67: =IFERROR(VLOOKUP(VALUE(IF(Z67<1,1,0)&IF(V67<'Факт продаж'!$AE$24,0,1)),$AB$1:$AC$4,2,FALSE),"НЕТ ПРОДАЖ") -> Корова | AF67: =VLOOKUP(B67,'ABC расчет'!B:G,6,0) -> A | AG67: =VLOOKUP(B67,'ABC расчет'!K:P,6,0) -> A | AH67: =VLOOKUP(B67,'ABC расчет'!T:Y,6,0) -> B | AI67: =VLOOKUP(B67,'ABC расчет'!AC:AH,6,0) -> A
A68: СТУЛЬЯ ПОСЕТИТЕЛЬСКИЕ | B68: SEVEN | C68: =IFERROR(VLOOKUP(B68,'Факт продаж'!A:B,2,0),"нет продаж") -> 670 | D68: =IFERROR(VLOOKUP(B68,'Факт продаж'!A:C,3,0),"нет продаж") -> 362662.19 | E68: =IFERROR(VLOOKUP(B68,'Факт продаж'!A:E,5,0),"нет продаж") -> 174152.03 | F68: =IFERROR(VLOOKUP(B68,'Факт продаж'!A:C,3,0)/SUM('План Антонова'!$C$11:$C$13),0) -> 0.0027537324 | G68: =IFERROR(VLOOKUP(B68,'Факт продаж'!J:K,2,0),"нет продаж") -> 890 | H68: =IFERROR(VLOOKUP(B68,'Факт продаж'!J:L,3,0),"нет продаж") -> 575228.6 | I68: =IFERROR(VLOOKUP(B68,'Факт продаж'!J:N,5,0),"нет продаж") -> 273815.41 | J68: =IFERROR(VLOOKUP(B68,'Факт продаж'!J:L,3,0)/SUM('План Антонова'!$C$14:$C$16),0) -> 0.0039718731 | K68: =IFERROR(VLOOKUP(B68,'Факт продаж'!J:O,6,0),"-") -> 0.57227807 | L68: =IF(AND(F68=0,J68>0),5,IF(J68/F68>5,5,IF(J68/F68=0,0.0000001,J68/F68))) -> 1.4423599 | M68: =IFERROR(VLOOKUP(B68,'Факт продаж'!S:T,2,0),"нет продаж") -> 1196 | N68: =IFERROR(VLOOKUP(B68,'Факт продаж'!S:U,3,0),"нет продаж") -> 704493.3 | O68: =IFERROR(VLOOKUP(B68,'Факт продаж'!S:W,5,0),"нет продаж") -> 311279.19 | P68: =IFERROR(VLOOKUP(B68,'Факт продаж'!S:U,3,0)/SUM('План Антонова'!$C$17:$C$19),0) -> 0.0042911042 | Q68: =IFERROR(VLOOKUP(B68,'Факт продаж'!S:X,6,0),"-") -> 0.13682129 | R68: =IF(AND(J68=0,P68>0),5,IF(P68/J68>5,5,IF(P68/J68=0,0.0000001,P68/J68))) -> 1.0803729 | S68: =IFERROR(VLOOKUP(B68,'Факт продаж'!AB:AD,2,0),"нет продаж") -> 1373 | T68: =IFERROR(VLOOKUP(B68,'Факт продаж'!AB:AD,3,0),"нет продаж") -> 869469.8 | U68: =IFERROR(VLOOKUP(B68,'Факт продаж'!AB:AF,5,0),"нет продаж") -> 385261.31 | V68: =IFERROR(VLOOKUP(B68,'Факт продаж'!AB:AD,3,0)/SUM('План Антонова'!$C$20:$C$22),0) -> 0.005650421 | W68: =IFERROR(VLOOKUP(B68,'Факт продаж'!AB:AG,6,0),"-") -> 0.23767128 | X68: =IF(AND(P68=0,V68>0),5,IF(V68/P68>5,5,IF(V68/P68=0,0.0000001,V68/P68))) -> 1.3167755 | Y68: =IFERROR(VLOOKUP(B68,'Факт продаж'!AB:AH,7,0),"-") -> 1.2122126 | Z68: =IF(AND(F68=0,V68>0),5,IF(V68/F68>5,5,IF(V68/F68=0,0.0000001,V68/F68))) -> 2.0519136 | AB68: =IFERROR(VLOOKUP(VALUE(IF(L68<1,1,0)&IF(J68<'Факт продаж'!$M$24,0,1)),$AB$1:$AC$4,2,FALSE),"НЕТ ПРОДАЖ") -> Звезда | AC68: =IFERROR(VLOOKUP(VALUE(IF(R68<1,1,0)&IF(P68<'Факт продаж'!$V$24,0,1)),$AB$1:$AC$4,2,FALSE),"НЕТ ПРОДАЖ") -> Звезда | AD68: =IFERROR(VLOOKUP(VALUE(IF(X68<1,1,0)&IF(V68<'Факт продаж'!$AE$24,0,1)),$AB$1:$AC$4,2,FALSE),"НЕТ ПРОДАЖ") -> Звезда | AE68: =IFERROR(VLOOKUP(VALUE(IF(Z68<1,1,0)&IF(V68<'Факт продаж'!$AE$24,0,1)),$AB$1:$AC$4,2,FALSE),"НЕТ ПРОДАЖ") -> Звезда | AF68: =VLOOKUP(B68,'ABC расчет'!B:G,6,0) -> C | AG68: =VLOOKUP(B68,'ABC расчет'!K:P,6,0) -> B | AH68: =VLOOKUP(B68,'ABC расчет'!T:Y,6,0) -> C | AI68: =VLOOKUP(B68,'ABC расчет'!AC:AH,6,0) -> B
A69: СТОЛЫ ОБЕДЕННЫЕ | B69: MODERN | C69: =IFERROR(VLOOKUP(B69,'Факт продаж'!A:B,2,0),"нет продаж") -> 13 | D69: =IFERROR(VLOOKUP(B69,'Факт продаж'!A:C,3,0),"нет продаж") -> 18603.996 | E69: =IFERROR(VLOOKUP(B69,'Факт продаж'!A:E,5,0),"нет продаж") -> 8408.7872 | F69: =IFERROR(VLOOKUP(B69,'Факт продаж'!A:C,3,0)/SUM('План Антонова'!$C$11:$C$13),0) -> 0.00014126211 | G69: =IFERROR(VLOOKUP(B69,'Факт продаж'!J:K,2,0),"нет продаж") -> 882 | H69: =IFERROR(VLOOKUP(B69,'Факт продаж'!J:L,3,0),"нет продаж") -> 1483791.6 | I69: =IFERROR(VLOOKUP(B69,'Факт продаж'!J:N,5,0),"нет продаж") -> 695507.75 | J69: =IFERROR(VLOOKUP(B69,'Факт продаж'!J:L,3,0)/SUM('План Антонова'!$C$14:$C$16),0) -> 0.010245373 | K69: =IFERROR(VLOOKUP(B69,'Факт продаж'!J:O,6,0),"-") -> 81.712017 | L69: =IF(AND(F69=0,J69>0),5,IF(J69/F69>5,5,IF(J69/F69=0,0.0000001,J69/F69))) -> 5 | M69: =IFERROR(VLOOKUP(B69,'Факт продаж'!S:T,2,0),"нет продаж") -> 699 | N69: =IFERROR(VLOOKUP(B69,'Факт продаж'!S:U,3,0),"нет продаж") -> 1181636.8 | O69: =IFERROR(VLOOKUP(B69,'Факт продаж'!S:W,5,0),"нет продаж") -> 496310.46 | P69: =IFERROR(VLOOKUP(B69,'Факт продаж'!S:U,3,0)/SUM('План Антонова'!$C$17:$C$19),0) -> 0.0071974094 | Q69: =IFERROR(VLOOKUP(B69,'Факт продаж'!S:X,6,0),"-") -> -0.28640556 | R69: =IF(AND(J69=0,P69>0),5,IF(P69/J69>5,5,IF(P69/J69=0,0.0000001,P69/J69))) -> 0.70250338 | S69: =IFERROR(VLOOKUP(B69,'Факт продаж'!AB:AD,2,0),"нет продаж") -> 507 | T69: =IFERROR(VLOOKUP(B69,'Факт продаж'!AB:AD,3,0),"нет продаж") -> 821493.15 | U69: =IFERROR(VLOOKUP(B69,'Факт продаж'!AB:AF,5,0),"нет продаж") -> 367692.23 | V69: =IFERROR(VLOOKUP(B69,'Факт продаж'!AB:AD,3,0)/SUM('План Антонова'!$C$20:$C$22),0) -> 0.0053386353 | W69: =IFERROR(VLOOKUP(B69,'Факт продаж'!AB:AG,6,0),"-") -> -0.25914874 | X69: =IF(AND(P69=0,V69>0),5,IF(V69/P69>5,5,IF(V69/P69=0,0.0000001,V69/P69))) -> 0.741744 | Y69: =IFERROR(VLOOKUP(B69,'Факт продаж'!AB:AH,7,0),"-") -> 42.727142 | Z69: =IF(AND(F69=0,V69>0),5,IF(V69/F69>5,5,IF(V69/F69=0,0.0000001,V69/F69))) -> 5 | AB69: =IFERROR(VLOOKUP(VALUE(IF(L69<1,1,0)&IF(J69<'Факт продаж'!$M$24,0,1)),$AB$1:$AC$4,2,FALSE),"НЕТ ПРОДАЖ") -> Звезда | AC69: =IFERROR(VLOOKUP(VALUE(IF(R69<1,1,0)&IF(P69<'Факт продаж'!$V$24,0,1)),$AB$1:$AC$4,2,FALSE),"НЕТ ПРОДАЖ") -> Корова | AD69: =IFERROR(VLOOKUP(VALUE(IF(X69<1,1,0)&IF(V69<'Факт продаж'!$AE$24,0,1)),$AB$1:$AC$4,2,FALSE),"НЕТ ПРОДАЖ") -> Корова | AE69: =IFERROR(VLOOKUP(VALUE(IF(Z69<1,1,0)&IF(V69<'Факт продаж'!$AE$24,0,1)),$AB$1:$AC$4,2,FALSE),"НЕТ ПРОДАЖ") -> Звезда | AF69: =VLOOKUP(B69,'ABC расчет'!B:G,6,0) -> B | AG69: =VLOOKUP(B69,'ABC расчет'!K:P,6,0) -> A | AH69: =VLOOKUP(B69,'ABC расчет'!T:Y,6,0) -> A | AI69: =VLOOKUP(B69,'ABC расчет'!AC:AH,6,0) -> A | AJ69: PROMO
A70: КРЕСЛА ОПЕРАТОРСКИЕ | B70: NETWORK | C70: =IFERROR(VLOOKUP(B70,'Факт продаж'!A:B,2,0),"нет продаж") -> 8 | D70: =IFERROR(VLOOKUP(B70,'Факт продаж'!A:C,3,0),"нет продаж") -> 16160.651 | E70: =IFERROR(VLOOKUP(B70,'Факт продаж'!A:E,5,0),"нет продаж") -> 6821.5916 | F70: =IFERROR(VLOOKUP(B70,'Факт продаж'!A:C,3,0)/SUM('План Антонова'!$C$11:$C$13),0) -> 0.00012270953 | G70: =IFERROR(VLOOKUP(B70,'Факт продаж'!J:K,2,0),"нет продаж") -> 202 | H70: =IFERROR(VLOOKUP(B70,'Факт продаж'!J:L,3,0),"нет продаж") -> 445019.5 | I70: =IFERROR(VLOOKUP(B70,'Факт продаж'!J:N,5,0),"нет продаж") -> 182145.58 | J70: =IFERROR(VLOOKUP(B70,'Факт продаж'!J:L,3,0)/SUM('План Антонова'!$C$14:$C$16),0) -> 0.0030727974 | K70: =IFERROR(VLOOKUP(B70,'Факт продаж'!J:O,6,0),"-") -> 25.701332 | L70: =IF(AND(F70=0,J70>0),5,IF(J70/F70>5,5,IF(J70/F70=0,0.0000001,J70/F70))) -> 5 | M70: =IFERROR(VLOOKUP(B70,'Факт продаж'!S:T,2,0),"нет продаж") -> 251 | N70: =IFERROR(VLOOKUP(B70,'Факт продаж'!S:U,3,0),"нет продаж") -> 590327.9 | O70: =IFERROR(VLOOKUP(B70,'Факт продаж'!S:W,5,0),"нет продаж") -> 235061.38 | P70: =IFERROR(VLOOKUP(B70,'Факт продаж'!S:U,3,0)/SUM('План Антонова'!$C$17:$C$19),0) -> 0.003595717 | Q70: =IFERROR(VLOOKUP(B70,'Факт продаж'!S:X,6,0),"-") -> 0.29051374 | R70: =IF(AND(J70=0,P70>0),5,IF(P70/J70>5,5,IF(P70/J70=0,0.0000001,P70/J70))) -> 1.170177 | S70: =IFERROR(VLOOKUP(B70,'Факт продаж'!AB:AD,2,0),"нет продаж") -> 401 | T70: =IFERROR(VLOOKUP(B70,'Факт продаж'!AB:AD,3,0),"нет продаж") -> 883632.27 | U70: =IFERROR(VLOOKUP(B70,'Факт продаж'!AB:AF,5,0),"нет продаж") -> 361988.27 | V70: =IFERROR(VLOOKUP(B70,'Факт продаж'!AB:AD,3,0)/SUM('План Антонова'!$C$20:$C$22),0) -> 0.0057424586 | W70: =IFERROR(VLOOKUP(B70,'Факт продаж'!AB:AG,6,0),"-") -> 0.53997338 | X70: =IF(AND(P70=0,V70>0),5,IF(V70/P70>5,5,IF(V70/P70=0,0.0000001,V70/P70))) -> 1.5970274 | Y70: =IFERROR(VLOOKUP(B70,'Факт продаж'!AB:AH,7,0),"-") -> 52.065074 | Z70: =IF(AND(F70=0,V70>0),5,IF(V70/F70>5,5,IF(V70/F70=0,0.0000001,V70/F70))) -> 5 | AB70: =IFERROR(VLOOKUP(VALUE(IF(L70<1,1,0)&IF(J70<'Факт продаж'!$M$24,0,1)),$AB$1:$AC$4,2,FALSE),"НЕТ ПРОДАЖ") -> Звезда | AC70: =IFERROR(VLOOKUP(VALUE(IF(R70<1,1,0)&IF(P70<'Факт продаж'!$V$24,0,1)),$AB$1:$AC$4,2,FALSE),"НЕТ ПРОДАЖ") -> Звезда | AD70: =IFERROR(VLOOKUP(VALUE(IF(X70<1,1,0)&IF(V70<'Факт продаж'!$AE$24,0,1)),$AB$1:$AC$4,2,FALSE),"НЕТ ПРОДАЖ") -> Звезда | AE70: =IFERROR(VLOOKUP(VALUE(IF(Z70<1,1,0)&IF(V70<'Факт продаж'!$AE$24,0,1)),$AB$1:$AC$4,2,FALSE),"НЕТ ПРОДАЖ") -> Звезда | AF70: =VLOOKUP(B70,'ABC расчет'!B:G,6,0) -> C | AG70: =VLOOKUP(B70,'ABC расчет'!K:P,6,0) -> B | AH70: =VLOOKUP(B70,'ABC расчет'!T:Y,6,0) -> B | AI70: =VLOOKUP(B70,'ABC расчет'!AC:AH,6,0) -> A
A71: КРЕСЛА И СТУЛЬЯ СПЕЦИАЛЬНЫЕ | B71: REGAL | C71: =IFERROR(VLOOKUP(B71,'Факт продаж'!A:B,2,0),"нет продаж") -> 272 | D71: =IFERROR(VLOOKUP(B71,'Факт продаж'!A:C,3,0),"нет продаж") -> 371245.99 | E71: =IFERROR(VLOOKUP(B71,'Факт продаж'!A:E,5,0),"нет продаж") -> 132658.15 | F71: =IFERROR(VLOOKUP(B71,'Факт продаж'!A:C,3,0)/SUM('План Антонова'!$C$11:$C$13),0) -> 0.0028189101 | G71: =IFERROR(VLOOKUP(B71,'Факт продаж'!J:K,2,0),"нет продаж") -> 214 | H71: =IFERROR(VLOOKUP(B71,'Факт продаж'!J:L,3,0),"нет продаж") -> 382500.22 | I71: =IFERROR(VLOOKUP(B71,'Факт продаж'!J:N,5,0),"нет продаж") -> 167673.61 | J71: =IFERROR(VLOOKUP(B71,'Факт продаж'!J:L,3,0)/SUM('План Антонова'!$C$14:$C$16),0) -> 0.0026411106 | K71: =IFERROR(VLOOKUP(B71,'Факт продаж'!J:O,6,0),"-") -> 0.26395264 | L71: =IF(AND(F71=0,J71>0),5,IF(J71/F71>5,5,IF(J71/F71=0,0.0000001,J71/F71))) -> 0.93692614 | M71: =IFERROR(VLOOKUP(B71,'Факт продаж'!S:T,2,0),"нет продаж") -> 198 | N71: =IFERROR(VLOOKUP(B71,'Факт продаж'!S:U,3,0),"нет продаж") -> 346213.85 | O71: =IFERROR(VLOOKUP(B71,'Факт продаж'!S:W,5,0),"нет продаж") -> 139151.6 | P71: =IFERROR(VLOOKUP(B71,'Факт продаж'!S:U,3,0)/SUM('План Антонова'!$C$17:$C$19),0) -> 0.002108806 | Q71: =IFERROR(VLOOKUP(B71,'Факт продаж'!S:X,6,0),"-") -> -0.17010437 | R71: =IF(AND(J71=0,P71>0),5,IF(P71/J71>5,5,IF(P71/J71=0,0.0000001,P71/J71))) -> 0.79845427 | S71: =IFERROR(VLOOKUP(B71,'Факт продаж'!AB:AD,2,0),"нет продаж") -> 504 | T71: =IFERROR(VLOOKUP(B71,'Факт продаж'!AB:AD,3,0),"нет продаж") -> 867508.15 | U71: =IFERROR(VLOOKUP(B71,'Факт продаж'!AB:AF,5,0),"нет продаж") -> 332557.16 | V71: =IFERROR(VLOOKUP(B71,'Факт продаж'!AB:AD,3,0)/SUM('План Антонова'!$C$20:$C$22),0) -> 0.0056376728 | W71: =IFERROR(VLOOKUP(B71,'Факт продаж'!AB:AG,6,0),"-") -> 1.389891 | X71: =IF(AND(P71=0,V71>0),5,IF(V71/P71>5,5,IF(V71/P71=0,0.0000001,V71/P71))) -> 2.6733957 | Y71: =IFERROR(VLOOKUP(B71,'Факт продаж'!AB:AH,7,0),"-") -> 1.5068733 | Z71: =IF(AND(F71=0,V71>0),5,IF(V71/F71>5,5,IF(V71/F71=0,0.0000001,V71/F71))) -> 1.9999477 | AB71: =IFERROR(VLOOKUP(VALUE(IF(L71<1,1,0)&IF(J71<'Факт продаж'!$M$24,0,1)),$AB$1:$AC$4,2,FALSE),"НЕТ ПРОДАЖ") -> Корова | AC71: =IFERROR(VLOOKUP(VALUE(IF(R71<1,1,0)&IF(P71<'Факт продаж'!$V$24,0,1)),$AB$1:$AC$4,2,FALSE),"НЕТ ПРОДАЖ") -> Корова | AD71: =IFERROR(VLOOKUP(VALUE(IF(X71<1,1,0)&IF(V71<'Факт продаж'!$AE$24,0,1)),$AB$1:$AC$4,2,FALSE),"НЕТ ПРОДАЖ") -> Звезда | AE71: =IFERROR(VLOOKUP(VALUE(IF(Z71<1,1,0)&IF(V71<'Факт продаж'!$AE$24,0,1)),$AB$1:$AC$4,2,FALSE),"НЕТ ПРОДАЖ") -> Звезда | AF71: =VLOOKUP(B71,'ABC расчет'!B:G,6,0) -> B | AG71: =VLOOKUP(B71,'ABC расчет'!K:P,6,0) -> B | AH71: =VLOOKUP(B71,'ABC расчет'!T:Y,6,0) -> A | AI71: =VLOOKUP(B71,'ABC расчет'!AC:AH,6,0) -> A
A72: КРЕСЛА/СТУЛЬЯ ОБЕДЕННЫЕ | B72: ASTI | C72: =IFERROR(VLOOKUP(B72,'Факт продаж'!A:B,2,0),"нет продаж") -> 96 | D72: =IFERROR(VLOOKUP(B72,'Факт продаж'!A:C,3,0),"нет продаж") -> 78042.849 | E72: =IFERROR(VLOOKUP(B72,'Факт продаж'!A:E,5,0),"нет продаж") -> 20345.976 | F72: =IFERROR(VLOOKUP(B72,'Факт продаж'!A:C,3,0)/SUM('План Антонова'!$C$11:$C$13),0) -> 0.00059258762 | G72: =IFERROR(VLOOKUP(B72,'Факт продаж'!J:K,2,0),"нет продаж") -> 805 | H72: =IFERROR(VLOOKUP(B72,'Факт продаж'!J:L,3,0),"нет продаж") -> 971643.56 | I72: =IFERROR(VLOOKUP(B72,'Факт продаж'!J:N,5,0),"нет продаж") -> 420481.72 | J72: =IFERROR(VLOOKUP(B72,'Факт продаж'!J:L,3,0)/SUM('План Антонова'!$C$14:$C$16),0) -> 0.006709063 | K72: =IFERROR(VLOOKUP(B72,'Факт продаж'!J:O,6,0),"-") -> 19.666578 | L72: =IF(AND(F72=0,J72>0),5,IF(J72/F72>5,5,IF(J72/F72=0,0.0000001,J72/F72))) -> 5 | M72: =IFERROR(VLOOKUP(B72,'Факт продаж'!S:T,2,0),"нет продаж") -> 662 | N72: =IFERROR(VLOOKUP(B72,'Факт продаж'!S:U,3,0),"нет продаж") -> 838683.5 | O72: =IFERROR(VLOOKUP(B72,'Факт продаж'!S:W,5,0),"нет продаж") -> 382076.14 | P72: =IFERROR(VLOOKUP(B72,'Факт продаж'!S:U,3,0)/SUM('План Антонова'!$C$17:$C$19),0) -> 0.0051084634 | Q72: =IFERROR(VLOOKUP(B72,'Факт продаж'!S:X,6,0),"-") -> -0.091337086 | R72: =IF(AND(J72=0,P72>0),5,IF(P72/J72>5,5,IF(P72/J72=0,0.0000001,P72/J72))) -> 0.76142726 | S72: =IFERROR(VLOOKUP(B72,'Факт продаж'!AB:AD,2,0),"нет продаж") -> 658 | T72: =IFERROR(VLOOKUP(B72,'Факт продаж'!AB:AD,3,0),"нет продаж") -> 831261.6 | U72: =IFERROR(VLOOKUP(B72,'Факт продаж'!AB:AF,5,0),"нет продаж") -> 325753.86 | V72: =IFERROR(VLOOKUP(B72,'Факт продаж'!AB:AD,3,0)/SUM('План Антонова'!$C$20:$C$22),0) -> 0.0054021174 | W72: =IFERROR(VLOOKUP(B72,'Факт продаж'!AB:AG,6,0),"-") -> -0.14741115 | X72: =IF(AND(P72=0,V72>0),5,IF(V72/P72>5,5,IF(V72/P72=0,0.0000001,V72/P72))) -> 1.0574838 | Y72: =IFERROR(VLOOKUP(B72,'Факт продаж'!AB:AH,7,0),"-") -> 15.010726 | Z72: =IF(AND(F72=0,V72>0),5,IF(V72/F72>5,5,IF(V72/F72=0,0.0000001,V72/F72))) -> 5 | AB72: =IFERROR(VLOOKUP(VALUE(IF(L72<1,1,0)&IF(J72<'Факт продаж'!$M$24,0,1)),$AB$1:$AC$4,2,FALSE),"НЕТ ПРОДАЖ") -> Звезда | AC72: =IFERROR(VLOOKUP(VALUE(IF(R72<1,1,0)&IF(P72<'Факт продаж'!$V$24,0,1)),$AB$1:$AC$4,2,FALSE),"НЕТ ПРОДАЖ") -> Корова | AD72: =IFERROR(VLOOKUP(VALUE(IF(X72<1,1,0)&IF(V72<'Факт продаж'!$AE$24,0,1)),$AB$1:$AC$4,2,FALSE),"НЕТ ПРОДАЖ") -> Звезда | AE72: =IFERROR(VLOOKUP(VALUE(IF(Z72<1,1,0)&IF(V72<'Факт продаж'!$AE$24,0,1)),$AB$1:$AC$4,2,FALSE),"НЕТ ПРОДАЖ") -> Звезда | AF72: =VLOOKUP(B72,'ABC расчет'!B:G,6,0) -> B | AG72: =VLOOKUP(B72,'ABC расчет'!K:P,6,0) -> A | AH72: =VLOOKUP(B72,'ABC расчет'!T:Y,6,0) -> A | AI72: =VLOOKUP(B72,'ABC расчет'!AC:AH,6,0) -> A | AJ72: PROMO
A73: МЕБЕЛЬ КОРПУСНАЯ | B73: Меган | C73: =IFERROR(VLOOKUP(B73,'Факт продаж'!A:B,2,0),"нет продаж") -> 12 | D73: =IFERROR(VLOOKUP(B73,'Факт продаж'!A:C,3,0),"нет продаж") -> 31711.828 | E73: =IFERROR(VLOOKUP(B73,'Факт продаж'!A:E,5,0),"нет продаж") -> 13503.375 | F73: =IFERROR(VLOOKUP(B73,'Факт продаж'!A:C,3,0)/SUM('План Антонова'!$C$11:$C$13),0) -> 0.00024079127 | G73: =IFERROR(VLOOKUP(B73,'Факт продаж'!J:K,2,0),"нет продаж") -> 655 | H73: =IFERROR(VLOOKUP(B73,'Факт продаж'!J:L,3,0),"нет продаж") -> 2246460.6 | I73: =IFERROR(VLOOKUP(B73,'Факт продаж'!J:N,5,0),"нет продаж") -> 742850.49 | J73: =IFERROR(VLOOKUP(B73,'Факт продаж'!J:L,3,0)/SUM('План Антонова'!$C$14:$C$16),0) -> 0.015511496 | K73: =IFERROR(VLOOKUP(B73,'Факт продаж'!J:O,6,0),"-") -> 54.012209 | L73: =IF(AND(F73=0,J73>0),5,IF(J73/F73>5,5,IF(J73/F73=0,0.0000001,J73/F73))) -> 5 | M73: =IFERROR(VLOOKUP(B73,'Факт продаж'!S:T,2,0),"нет продаж") -> 196 | N73: =IFERROR(VLOOKUP(B73,'Факт продаж'!S:U,3,0),"нет продаж") -> 610256.42 | O73: =IFERROR(VLOOKUP(B73,'Факт продаж'!S:W,5,0),"нет продаж") -> 228390.01 | P73: =IFERROR(VLOOKUP(B73,'Факт продаж'!S:U,3,0)/SUM('План Антонова'!$C$17:$C$19),0) -> 0.0037171026 | Q73: =IFERROR(VLOOKUP(B73,'Факт продаж'!S:X,6,0),"-") -> -0.69254915 | R73: =IF(AND(J73=0,P73>0),5,IF(P73/J73>5,5,IF(P73/J73=0,0.0000001,P73/J73))) -> 0.23963533 | S73: =IFERROR(VLOOKUP(B73,'Факт продаж'!AB:AD,2,0),"нет продаж") -> 189 | T73: =IFERROR(VLOOKUP(B73,'Факт продаж'!AB:AD,3,0),"нет продаж") -> 754909.05 | U73: =IFERROR(VLOOKUP(B73,'Факт продаж'!AB:AF,5,0),"нет продаж") -> 323856.99 | V73: =IFERROR(VLOOKUP(B73,'Факт продаж'!AB:AD,3,0)/SUM('План Антонова'!$C$20:$C$22),0) -> 0.0049059253 | W73: =IFERROR(VLOOKUP(B73,'Факт продаж'!AB:AG,6,0),"-") -> 0.41799978 | X73: =IF(AND(P73=0,V73>0),5,IF(V73/P73>5,5,IF(V73/P73=0,0.0000001,V73/P73))) -> 1.3198251 | Y73: =IFERROR(VLOOKUP(B73,'Факт продаж'!AB:AH,7,0),"-") -> 22.98341 | Z73: =IF(AND(F73=0,V73>0),5,IF(V73/F73>5,5,IF(V73/F73=0,0.0000001,V73/F73))) -> 5 | AB73: =IFERROR(VLOOKUP(VALUE(IF(L73<1,1,0)&IF(J73<'Факт продаж'!$M$24,0,1)),$AB$1:$AC$4,2,FALSE),"НЕТ ПРОДАЖ") -> Звезда | AC73: =IFERROR(VLOOKUP(VALUE(IF(R73<1,1,0)&IF(P73<'Факт продаж'!$V$24,0,1)),$AB$1:$AC$4,2,FALSE),"НЕТ ПРОДАЖ") -> Корова | AD73: =IFERROR(VLOOKUP(VALUE(IF(X73<1,1,0)&IF(V73<'Факт продаж'!$AE$24,0,1)),$AB$1:$AC$4,2,FALSE),"НЕТ ПРОДАЖ") -> Звезда | AE73: =IFERROR(VLOOKUP(VALUE(IF(Z73<1,1,0)&IF(V73<'Факт продаж'!$AE$24,0,1)),$AB$1:$AC$4,2,FALSE),"НЕТ ПРОДАЖ") -> Звезда | AF73: =VLOOKUP(B73,'ABC расчет'!B:G,6,0) -> C | AG73: =VLOOKUP(B73,'ABC расчет'!K:P,6,0) -> A | AH73: =VLOOKUP(B73,'ABC расчет'!T:Y,6,0) -> B | AI73: =VLOOKUP(B73,'ABC расчет'!AC:AH,6,0) -> A
